Workbook

Sheet GERAL
A1: Panorama Geral das Unidades Escolares
A2: Atualizada em: 15/09/2026
A3: Escolas Novas Rui Costa | B3: Escolas Novas Gov. Jerônimo
A4: (*) - O nº de estudantes em processo de matricula estão sendo atualizados no sigeduc com série/turno, a planilha deverá ser regularizada até 30 de setembro/26.
A5: NTE | B5: MUNICIPIOS | C5: TIPO E - ESCOLA A - ANEXO EFA - ESCOLA AGRÍCOLA | D5: COD_SEC ESCOLA SEDE | E5: COD_SEC ANEXO | F5: COD_MEC | G5: COLÉGIO | H5: ENDEREÇO | I5: BAIRRO | J5: DISTANCIA PARA SEDE | K5: SITUAÇÃO DO PRÉDIO | L5: PORTE | T5: Nº DE SALAS (SIGDUC) | U5: Nº DE SALAS DE AULA VERDE: Atualizado pela nota em 2025 ROXO: Falta atualizar | V5: EDUCAÇÃO INFANTIL | AA5: FUNDAMENTAL | AF5: MÉDIO | AK5: EJA - FUND. | AO5: EJA - MÉDIO | AS5: PROFISSIONAL | AX5: TOTAL GERAL MATRICULADOS | AY5: TOTAL POR TURNO | BA5: Nº DE ESTUDANTES EM PROCESSO DE MATRICULA (*) | BB5: (*) TOTAL ESTUDANTES | BC5: MODALIDADE | BD5: CATEGORIA | BE5: ENSINO | BF5: OBS | BG5: cod sec ( para transferência dos dados) | BH5: Coordenadas Google Maps | BI5: N° de salas ( resumo) | BJ5: PADRÃO | BK5: MATRICULA INTEGRAL | BM5: POVOS
M6: DIRETOR(A) | N6: CELULAR | O6: VICE -DIRETOR(A) 1 | P6: CELULAR | Q6: VICE -DIRETOR(A) 2 | R6: CELULAR | S6: TELEFONE DA UEE | V6: MAT | W6: VES | X6: NOT | Y6: INTEG. | Z6: TOTAL | AA6: MAT | AB6: VES | AC6: NOT | AD6: INTEG. | AE6: TOTAL | AF6: MAT | AG6: VES | AH6: NOT | AI6: INTEGR. | AJ6: TOTAL | AK6: MAT | AL6: VES | AM6: NOT | AN6: TOTAL | AO6: MAT | AP6: VES | AQ6: NOT | AR6: TOTAL | AS6: MAT | AT6: VES | AU6: NOT | AV6: INTEGR. | AW6: TOTAL | AY6: DIURNO | AZ6: NOTURNO
A8: NTE 01 - IRECÊ | B8: AMERICA DOURADA | C8: ESCOLA | D8: 1125747 | F8: 29057809 | G8: COLÉGIO ESTADUAL SÃO SEBASTIÃO | H8: RUA NESTOR BORGES - 100 | I8: CENTRO | J8: SEDE | K8: PRÓPRIO | L8: GRANDE | M8: =IFERROR(__xludf.DUMMYFUNCTION("(VLOOKUP(D8, IMPORTRANGE(""https://docs.google.com/spreadsheets/d/1MjHtlUikwobi2MaWJgy7tfLeBmhj1u-dRFRs_8GwSoA/edit#gid=0"",""Gestores Escolares!D7:J""),3,0))"),"AURIVAN OLIVEIRA DE SOUZA") -> AURIVAN OLIVEIRA DE SOUZA | N8: =IFERROR(__xludf.DUMMYFUNCTION("IFERROR(VLOOKUP(D8, IMPORTRANGE(""https://docs.google.com/spreadsheets/d/1MjHtlUikwobi2MaWJgy7tfLeBmhj1u-dRFRs_8GwSoA/edit#gid=0"",""Gestores Escolares!D7:J""),4,0),""VERIFICAR CÓD SEC"")"),"(74) 9 9922-7133") -> (74) 9 9922-7133 | O8: =IFERROR(__xludf.DUMMYFUNCTION("IFERROR(VLOOKUP(D8, IMPORTRANGE(""https://docs.google.com/spreadsheets/d/1MjHtlUikwobi2MaWJgy7tfLeBmhj1u-dRFRs_8GwSoA/edit#gid=0"",""Gestores Escolares!D7:J""),6,0),""VERIFICAR CÓD SEC"")"),"LUCAS BORGES DOS SANTOS") -> LUCAS BORGES DOS SANTOS | P8: =IFERROR(__xludf.DUMMYFUNCTION("IFERROR(VLOOKUP(D8, IMPORTRANGE(""https://docs.google.com/spreadsheets/d/1MjHtlUikwobi2MaWJgy7tfLeBmhj1u-dRFRs_8GwSoA/edit#gid=0"",""Gestores Escolares!D7:J""),7,0),""VERIFICAR CÓD SEC"")"),"(74) 9 9816-6696") -> (74) 9 9816-6696 | Q8: =IFERROR(__xludf.DUMMYFUNCTION("IFERROR(VLOOKUP(D8, IMPORTRANGE(""https://docs.google.com/spreadsheets/d/1MjHtlUikwobi2MaWJgy7tfLeBmhj1u-dRFRs_8GwSoA/edit#gid=0"",""Gestores Escolares!D7:m""),9,0),""VERIFICAR CÓD SEC"")"),"") | R8: =IFERROR(__xludf.DUMMYFUNCTION("IFERROR(VLOOKUP(D8, IMPORTRANGE(""https://docs.google.com/spreadsheets/d/1MjHtlUikwobi2MaWJgy7tfLeBmhj1u-dRFRs_8GwSoA/edit#gid=0"",""Gestores Escolares!D7:m""),10,0),""VERIFICAR CÓD SEC"")"),"") | T8: 8 | U8: 8 | V8: 0 | W8: 0 | X8: 0 | Y8: 0 | Z8: =SUM(V8:Y8) -> 0 | AA8: 0 | AB8: 0 | AC8: 0 | AD8: 0 | AE8: =SUM(AA8:AD8) -> 0 | AF8: 183 | AG8: 172 | AH8: 0 | AI8: 0 | AJ8: =SUM(AF8:AI8) -> 355 | AK8: 0 | AL8: 0 | AM8: 0 | AN8: =SUM(AK8:AM8) -> 0 | AO8: 0 | AP8: 0 | AQ8: 74 | AR8: =SUM(AO8:AQ8) -> 74 | AS8: 0 | AT8: 0 | AU8: 32 | AV8: 0 | AW8: =SUM(AS8:AV8) -> 32 | AX8: =SUM(AY8:AZ8) -> 461 | AY8: =SUM(AV8,AT8,AS8,AP8,AO8,AL8,AK8,AI8,AG8,AF8,AD8,AB8,AA8,Y8,W8,V8) -> 355 | AZ8: =SUM(AU8,AQ8,AM8,AH8,AC8,X8) -> 106 | BA8: 0 | BB8: =SUM(AX8+BA8) -> 461 | BC8: ESCOLA SEDE | BD8: A DEFINIR | BE8: A DEFINIR | BG8: 1125747 | BH8: -11.456445479476455, -41.43890636036543 | BI8: 8 | BJ8: PADRÃO ANTIGO | BK8: =Y8+AD8+AI8+AV8 -> 0 | BL8: =V8+W8+AA8+AB8+AF8+AG8+AK8+AL8+AO8+AP8+AS8+AT8 -> 355 | BM8: =IFERROR(__xludf.DUMMYFUNCTION("IFERROR(VLOOKUP(BG8,IMPORTRANGE(""https://docs.google.com/spreadsheets/d/1juPI-Fb8LD0YtltB2mlGEnp_R3UVu1t3wSFPzgCyHXE/edit?gid=0#gid=0"",""GERAL!A2:C""),3,0),""-"")"),"-") -> -
A9: NTE 01 - IRECÊ | B9: AMERICA DOURADA | C9: ESCOLA | D9: 1179795 | F9: 29488974 | G9: COLÉGIO ESTADUAL DE TEMPO INTEGRAL PROFESSORA NANCY DA ROCHA CARDOSO - DIST. DE SOARES | H9: ESTRADA BA 052 - 88188 - N S/N Bairro: CENTRO CEP: 44910-000 | I9: CENTRO | K9: PRÓPRIO | L9: GRANDE | M9: =IFERROR(__xludf.DUMMYFUNCTION("IFERROR(VLOOKUP(D9, IMPORTRANGE(""https://docs.google.com/spreadsheets/d/1MjHtlUikwobi2MaWJgy7tfLeBmhj1u-dRFRs_8GwSoA/edit#gid=0"",""Gestores Escolares!D7:J""),3,0),""VERIFICAR CÓD SEC"")"),"ARIVONE MARIA DA SILVA SANTOS ") -> ARIVONE MARIA DA SILVA SANTOS | N9: =IFERROR(__xludf.DUMMYFUNCTION("IFERROR(VLOOKUP(D9, IMPORTRANGE(""https://docs.google.com/spreadsheets/d/1MjHtlUikwobi2MaWJgy7tfLeBmhj1u-dRFRs_8GwSoA/edit#gid=0"",""Gestores Escolares!D7:J""),4,0),""VERIFICAR CÓD SEC"")"),"(74) 9 8836-0537/ 9 9925-8934 (ZAP)") -> (74) 9 8836-0537/ 9 9925-8934 (ZAP) | O9: =IFERROR(__xludf.DUMMYFUNCTION("IFERROR(VLOOKUP(D9, IMPORTRANGE(""https://docs.google.com/spreadsheets/d/1MjHtlUikwobi2MaWJgy7tfLeBmhj1u-dRFRs_8GwSoA/edit#gid=0"",""Gestores Escolares!D7:J""),6,0),""VERIFICAR CÓD SEC"")"),"RODRIGO SILVA DE OLIVEIRA") -> RODRIGO SILVA DE OLIVEIRA | P9: =IFERROR(__xludf.DUMMYFUNCTION("IFERROR(VLOOKUP(D9, IMPORTRANGE(""https://docs.google.com/spreadsheets/d/1MjHtlUikwobi2MaWJgy7tfLeBmhj1u-dRFRs_8GwSoA/edit#gid=0"",""Gestores Escolares!D7:J""),7,0),""VERIFICAR CÓD SEC"")"),"(74) 9 9996-0577") -> (74) 9 9996-0577 | Q9: =IFERROR(__xludf.DUMMYFUNCTION("IFERROR(VLOOKUP(D9, IMPORTRANGE(""https://docs.google.com/spreadsheets/d/1MjHtlUikwobi2MaWJgy7tfLeBmhj1u-dRFRs_8GwSoA/edit#gid=0"",""Gestores Escolares!D7:m""),9,0),""VERIFICAR CÓD SEC"")"),"") | R9: =IFERROR(__xludf.DUMMYFUNCTION("IFERROR(VLOOKUP(D9, IMPORTRANGE(""https://docs.google.com/spreadsheets/d/1MjHtlUikwobi2MaWJgy7tfLeBmhj1u-dRFRs_8GwSoA/edit#gid=0"",""Gestores Escolares!D7:m""),10,0),""VERIFICAR CÓD SEC"")"),"") | T9: 12 | U9: 12 | V9: 0 | W9: 0 | X9: 0 | Y9: 0 | Z9: =SUM(V9:Y9) -> 0 | AA9: 0 | AB9: 0 | AC9: 0 | AD9: 0 | AE9: =SUM(AA9:AD9) -> 0 | AF9: 104 | AG9: 0 | AH9: 0 | AI9: 211 | AJ9: =SUM(AF9:AI9) -> 315 | AK9: 0 | AL9: 0 | AM9: 0 | AN9: =SUM(AK9:AM9) -> 0 | AO9: 0 | AP9: 0 | AQ9: 58 | AR9: =SUM(AO9:AQ9) -> 58 | AS9: 0 | AT9: 0 | AU9: 0 | AV9: 0 | AW9: =SUM(AS9:AV9) -> 0 | AX9: =SUM(AY9:AZ9) -> 373 | AY9: =SUM(AV9,AT9,AS9,AP9,AO9,AL9,AK9,AI9,AG9,AF9,AD9,AB9,AA9,Y9,W9,V9) -> 315 | AZ9: =SUM(AU9,AQ9,AM9,AH9,AC9,X9) -> 58 | BA9: 0 | BB9: =SUM(AX9+BA9) -> 373 | BG9: 1179795 | BH9: -11.313835928826945, -41.47264134866215 | BI9: 12 | BJ9: NOVO PADRÃO (NOVA ESCOLA) | BK9: =Y9+AD9+AI9+AV9 -> 211 | BL9: =V9+W9+AA9+AB9+AF9+AG9+AK9+AL9+AO9+AP9+AS9+AT9 -> 104 | BM9: =IFERROR(__xludf.DUMMYFUNCTION("IFERROR(VLOOKUP(BG9,IMPORTRANGE(""https://docs.google.com/spreadsheets/d/1juPI-Fb8LD0YtltB2mlGEnp_R3UVu1t3wSFPzgCyHXE/edit?gid=0#gid=0"",""GERAL!A2:C""),3,0),""-"")"),"-") -> -
A10: NTE 01 - IRECÊ | B10: AMERICA DOURADA | C10: ANEXO | D10: 1179281 | E10: 1178787 | F10: 29459141 | G10: ANEXO - CEMIT - IRECÊ - DISTRITO DE BELO CAMPO | H10: DISTRITO DE BELO CAMPO - SN(00004) | I10: CENTRO | J10: 31KM | K10: CEDIDO | L10: PEQUENO | M10: =IFERROR(__xludf.DUMMYFUNCTION("IFERROR(VLOOKUP(D10, IMPORTRANGE(""https://docs.google.com/spreadsheets/d/1MjHtlUikwobi2MaWJgy7tfLeBmhj1u-dRFRs_8GwSoA/edit#gid=0"",""Gestores Escolares!D7:J""),3,0),""VERIFICAR CÓD SEC"")"),"MARCOS PAULO DA SILVA ALMEIDA") -> MARCOS PAULO DA SILVA ALMEIDA | N10: =IFERROR(__xludf.DUMMYFUNCTION("IFERROR(VLOOKUP(D10, IMPORTRANGE(""https://docs.google.com/spreadsheets/d/1MjHtlUikwobi2MaWJgy7tfLeBmhj1u-dRFRs_8GwSoA/edit#gid=0"",""Gestores Escolares!D7:J""),4,0),""VERIFICAR CÓD SEC"")"),"(74) 9 9998-8112") -> (74) 9 9998-8112 | O10: =IFERROR(__xludf.DUMMYFUNCTION("IFERROR(VLOOKUP(D10, IMPORTRANGE(""https://docs.google.com/spreadsheets/d/1MjHtlUikwobi2MaWJgy7tfLeBmhj1u-dRFRs_8GwSoA/edit#gid=0"",""Gestores Escolares!D7:J""),6,0),""VERIFICAR CÓD SEC"")"),"FERNANDA MIRANDA CAMPOS") -> FERNANDA MIRANDA CAMPOS | P10: =IFERROR(__xludf.DUMMYFUNCTION("IFERROR(VLOOKUP(D10, IMPORTRANGE(""https://docs.google.com/spreadsheets/d/1MjHtlUikwobi2MaWJgy7tfLeBmhj1u-dRFRs_8GwSoA/edit#gid=0"",""Gestores Escolares!D7:J""),7,0),""VERIFICAR CÓD SEC"")"),"(74) 9 9963-4717") -> (74) 9 9963-4717 | Q10: =IFERROR(__xludf.DUMMYFUNCTION("IFERROR(VLOOKUP(D10, IMPORTRANGE(""https://docs.google.com/spreadsheets/d/1MjHtlUikwobi2MaWJgy7tfLeBmhj1u-dRFRs_8GwSoA/edit#gid=0"",""Gestores Escolares!D7:m""),9,0),""VERIFICAR CÓD SEC"")"),"") | R10: =IFERROR(__xludf.DUMMYFUNCTION("IFERROR(VLOOKUP(D10, IMPORTRANGE(""https://docs.google.com/spreadsheets/d/1MjHtlUikwobi2MaWJgy7tfLeBmhj1u-dRFRs_8GwSoA/edit#gid=0"",""Gestores Escolares!D7:m""),10,0),""VERIFICAR CÓD SEC"")"),"") | T10: 3 | U10: 3 | V10: 0 | W10: 0 | X10: 0 | Y10: 0 | Z10: =SUM(V10:Y10) -> 0 | AA10: 0 | AB10: 0 | AC10: 0 | AD10: 0 | AE10: =SUM(AA10:AD10) -> 0 | AF10: 0 | AG10: 0 | AH10: 23 | AI10: 0 | AJ10: =SUM(AF10:AI10) -> 23 | AK10: 0 | AL10: 0 | AM10: 0 | AN10: =SUM(AK10:AM10) -> 0 | AO10: 0 | AP10: 0 | AQ10: 0 | AR10: =SUM(AO10:AQ10) -> 0 | AS10: 0 | AT10: 0 | AU10: 0 | AV10: 0 | AW10: =SUM(AS10:AV10) -> 0 | AX10: =SUM(AY10:AZ10) -> 23 | AY10: =SUM(AV10,AT10,AS10,AP10,AO10,AL10,AK10,AI10,AG10,AF10,AD10,AB10,AA10,Y10,W10,V10) -> 0 | AZ10: =SUM(AU10,AQ10,AM10,AH10,AC10,X10) -> 23 | BA10: 0 | BB10: =SUM(AX10+BA10) -> 23 | BC10: A DEFINIR | BD10: CEMIT | BE10: PROFISSIONAL | BG10: 1178787 | BI10: 3 | BJ10: PADRÃO ANTIGO | BK10: =Y10+AD10+AI10+AV10 -> 0 | BL10: =V10+W10+AA10+AB10+AF10+AG10+AK10+AL10+AO10+AP10+AS10+AT10 -> 0 | BM10: =IFERROR(__xludf.DUMMYFUNCTION("IFERROR(VLOOKUP(BG10,IMPORTRANGE(""https://docs.google.com/spreadsheets/d/1juPI-Fb8LD0YtltB2mlGEnp_R3UVu1t3wSFPzgCyHXE/edit?gid=0#gid=0"",""GERAL!A2:C""),3,0),""-"")"),"-") -> -
A11: NTE 01 - IRECÊ | B11: BARRA DO MENDES | C11: ESCOLA | D11: 1125925 | F11: 29058244 | G11: COLEGIO ESTADUAL DE TEMPO INTEGRAL EDIVALDO MACHADO BOAVENTURA | H11: RUA JURACY MAGALHÃES - S/N | I11: CENTRO | J11: SEDE | K11: PRÓPRIO | L11: MÉDIO | M11: =IFERROR(__xludf.DUMMYFUNCTION("IFERROR(VLOOKUP(D11, IMPORTRANGE(""https://docs.google.com/spreadsheets/d/1MjHtlUikwobi2MaWJgy7tfLeBmhj1u-dRFRs_8GwSoA/edit#gid=0"",""Gestores Escolares!D7:J""),3,0),""VERIFICAR CÓD SEC"")"),"ANTÔNIO FRANCISCO RODRIGUES DE FREITAS") -> ANTÔNIO FRANCISCO RODRIGUES DE FREITAS | N11: =IFERROR(__xludf.DUMMYFUNCTION("IFERROR(VLOOKUP(D11, IMPORTRANGE(""https://docs.google.com/spreadsheets/d/1MjHtlUikwobi2MaWJgy7tfLeBmhj1u-dRFRs_8GwSoA/edit#gid=0"",""Gestores Escolares!D7:J""),4,0),""VERIFICAR CÓD SEC"")"),"(74) 9 9924-5179") -> (74) 9 9924-5179 | O11: =IFERROR(__xludf.DUMMYFUNCTION("IFERROR(VLOOKUP(D11, IMPORTRANGE(""https://docs.google.com/spreadsheets/d/1MjHtlUikwobi2MaWJgy7tfLeBmhj1u-dRFRs_8GwSoA/edit#gid=0"",""Gestores Escolares!D7:J""),6,0),""VERIFICAR CÓD SEC"")"),"SHIRLEY MENDES BARRETO") -> SHIRLEY MENDES BARRETO | P11: =IFERROR(__xludf.DUMMYFUNCTION("IFERROR(VLOOKUP(D11, IMPORTRANGE(""https://docs.google.com/spreadsheets/d/1MjHtlUikwobi2MaWJgy7tfLeBmhj1u-dRFRs_8GwSoA/edit#gid=0"",""Gestores Escolares!D7:J""),7,0),""VERIFICAR CÓD SEC"")"),"(74) 9 9801-4575") -> (74) 9 9801-4575 | Q11: =IFERROR(__xludf.DUMMYFUNCTION("IFERROR(VLOOKUP(D11, IMPORTRANGE(""https://docs.google.com/spreadsheets/d/1MjHtlUikwobi2MaWJgy7tfLeBmhj1u-dRFRs_8GwSoA/edit#gid=0"",""Gestores Escolares!D7:m""),9,0),""VERIFICAR CÓD SEC"")"),"") | R11: =IFERROR(__xludf.DUMMYFUNCTION("IFERROR(VLOOKUP(D11, IMPORTRANGE(""https://docs.google.com/spreadsheets/d/1MjHtlUikwobi2MaWJgy7tfLeBmhj1u-dRFRs_8GwSoA/edit#gid=0"",""Gestores Escolares!D7:m""),10,0),""VERIFICAR CÓD SEC"")"),"") | T11: 6 | U11: 11 salas, sendo 08 salas de aula, e 03 adaptadas para Sala de AEE e salas de oficinas do Educa Mais. | V11: 0 | W11: 0 | X11: 0 | Y11: 0 | Z11: =SUM(V11:Y11) -> 0 | AA11: 0 | AB11: 0 | AC11: 0 | AD11: 0 | AE11: =SUM(AA11:AD11) -> 0 | AF11: 63 | AG11: 59 | AH11: 0 | AI11: 127 | AJ11: =SUM(AF11:AI11) -> 249 | AK11: 0 | AL11: 0 | AM11: 0 | AN11: =SUM(AK11:AM11) -> 0 | AO11: 0 | AP11: 0 | AQ11: 40 | AR11: =SUM(AO11:AQ11) -> 40 | AS11: 0 | AT11: 0 | AU11: 0 | AV11: 118 | AW11: =SUM(AS11:AV11) -> 118 | AX11: =SUM(AY11:AZ11) -> 407 | AY11: =SUM(AV11,AT11,AS11,AP11,AO11,AL11,AK11,AI11,AG11,AF11,AD11,AB11,AA11,Y11,W11,V11) -> 367 | AZ11: =SUM(AU11,AQ11,AM11,AH11,AC11,X11) -> 40 | BA11: 0 | BB11: =SUM(AX11+BA11) -> 407 | BC11: ESCOLA SEDE | BD11: A DEFINIR | BE11: A DEFINIR | BG11: 1125925 | BH11: -11.804665179549133, -42.058620844234696 | BI11: 6 | BJ11: NOVO PADRÃO (AMPLIAÇÃO COM MODERNIZAÇÃO) | BK11: =Y11+AD11+AI11+AV11 -> 245 | BL11: =V11+W11+AA11+AB11+AF11+AG11+AK11+AL11+AO11+AP11+AS11+AT11 -> 122 | BM11: =IFERROR(__xludf.DUMMYFUNCTION("IFERROR(VLOOKUP(BG11,IMPORTRANGE(""https://docs.google.com/spreadsheets/d/1juPI-Fb8LD0YtltB2mlGEnp_R3UVu1t3wSFPzgCyHXE/edit?gid=0#gid=0"",""GERAL!A2:C""),3,0),""-"")"),"-") -> -
A12: NTE 01 - IRECÊ | B12: BARRA DO MENDES | C12: ANEXO | D12: 1125925 | E12: 1178206 | F12: 29491916 | G12: ANEXO-COL EST DE T. INTEG EDIVALDO MACHADO BOAVENTURA-DIST DE CANARINA | H12: DISTRITO DE CANARINA - S/N | I12: CANARINA | J12: 60KM | K12: CEDIDO | L12: PEQUENO | M12: =IFERROR(__xludf.DUMMYFUNCTION("IFERROR(VLOOKUP(D12, IMPORTRANGE(""https://docs.google.com/spreadsheets/d/1MjHtlUikwobi2MaWJgy7tfLeBmhj1u-dRFRs_8GwSoA/edit#gid=0"",""Gestores Escolares!D7:J""),3,0),""VERIFICAR CÓD SEC"")"),"ANTÔNIO FRANCISCO RODRIGUES DE FREITAS") -> ANTÔNIO FRANCISCO RODRIGUES DE FREITAS | N12: =IFERROR(__xludf.DUMMYFUNCTION("IFERROR(VLOOKUP(D12, IMPORTRANGE(""https://docs.google.com/spreadsheets/d/1MjHtlUikwobi2MaWJgy7tfLeBmhj1u-dRFRs_8GwSoA/edit#gid=0"",""Gestores Escolares!D7:J""),4,0),""VERIFICAR CÓD SEC"")"),"(74) 9 9924-5179") -> (74) 9 9924-5179 | O12: =IFERROR(__xludf.DUMMYFUNCTION("IFERROR(VLOOKUP(D12, IMPORTRANGE(""https://docs.google.com/spreadsheets/d/1MjHtlUikwobi2MaWJgy7tfLeBmhj1u-dRFRs_8GwSoA/edit#gid=0"",""Gestores Escolares!D7:J""),6,0),""VERIFICAR CÓD SEC"")"),"SHIRLEY MENDES BARRETO") -> SHIRLEY MENDES BARRETO | P12: =IFERROR(__xludf.DUMMYFUNCTION("IFERROR(VLOOKUP(D12, IMPORTRANGE(""https://docs.google.com/spreadsheets/d/1MjHtlUikwobi2MaWJgy7tfLeBmhj1u-dRFRs_8GwSoA/edit#gid=0"",""Gestores Escolares!D7:J""),7,0),""VERIFICAR CÓD SEC"")"),"(74) 9 9801-4575") -> (74) 9 9801-4575 | Q12: =IFERROR(__xludf.DUMMYFUNCTION("IFERROR(VLOOKUP(D12, IMPORTRANGE(""https://docs.google.com/spreadsheets/d/1MjHtlUikwobi2MaWJgy7tfLeBmhj1u-dRFRs_8GwSoA/edit#gid=0"",""Gestores Escolares!D7:m""),9,0),""VERIFICAR CÓD SEC"")"),"") | R12: =IFERROR(__xludf.DUMMYFUNCTION("IFERROR(VLOOKUP(D12, IMPORTRANGE(""https://docs.google.com/spreadsheets/d/1MjHtlUikwobi2MaWJgy7tfLeBmhj1u-dRFRs_8GwSoA/edit#gid=0"",""Gestores Escolares!D7:m""),10,0),""VERIFICAR CÓD SEC"")"),"") | T12: 4 | U12: 4 | V12: 0 | W12: 0 | X12: 0 | Y12: 0 | Z12: =SUM(V12:Y12) -> 0 | AA12: 0 | AB12: 0 | AC12: 0 | AD12: 0 | AE12: =SUM(AA12:AD12) -> 0 | AF12: 73 | AG12: 0 | AH12: 0 | AI12: 0 | AJ12: =SUM(AF12:AI12) -> 73 | AK12: 0 | AL12: 0 | AM12: 0 | AN12: =SUM(AK12:AM12) -> 0 | AO12: 0 | AP12: 0 | AQ12: 0 | AR12: =SUM(AO12:AQ12) -> 0 | AS12: 0 | AT12: 0 | AU12: 0 | AV12: 0 | AW12: =SUM(AS12:AV12) -> 0 | AX12: =SUM(AY12:AZ12) -> 73 | AY12: =SUM(AV12,AT12,AS12,AP12,AO12,AL12,AK12,AI12,AG12,AF12,AD12,AB12,AA12,Y12,W12,V12) -> 73 | AZ12: =SUM(AU12,AQ12,AM12,AH12,AC12,X12) -> 0 | BA12: 0 | BB12: =SUM(AX12+BA12) -> 73 | BC12: QUILOMBOLA | BD12: A DEFINIR | BE12: A DEFINIR | BG12: 1178206 | BH12: -11.804665179549133, -42.058620844234696 | BI12: 4 | BJ12: PADRÃO ANTIGO | BK12: =Y12+AD12+AI12+AV12 -> 0 | BL12: =V12+W12+AA12+AB12+AF12+AG12+AK12+AL12+AO12+AP12+AS12+AT12 -> 73 | BM12: =IFERROR(__xludf.DUMMYFUNCTION("IFERROR(VLOOKUP(BG12,IMPORTRANGE(""https://docs.google.com/spreadsheets/d/1juPI-Fb8LD0YtltB2mlGEnp_R3UVu1t3wSFPzgCyHXE/edit?gid=0#gid=0"",""GERAL!A2:C""),3,0),""-"")"),"QUILOMBOLAS") -> QUILOMBOLAS
A13: NTE 01 - IRECÊ | B13: BARRA DO MENDES | C13: ANEXO | D13: 1179281 | E13: 1178790 | F13: 29459141 | G13: ANEXO - CEMIT - IRECÊ - DISTRITO DE MILAGRES | H13: DISTRITO DE MILAGRES - S/N | I13: DISTRITO DE MILAGRES | J13: 30KM | K13: CEDIDO | L13: PEQUENO | M13: =IFERROR(__xludf.DUMMYFUNCTION("IFERROR(VLOOKUP(D13, IMPORTRANGE(""https://docs.google.com/spreadsheets/d/1MjHtlUikwobi2MaWJgy7tfLeBmhj1u-dRFRs_8GwSoA/edit#gid=0"",""Gestores Escolares!D7:J""),3,0),""VERIFICAR CÓD SEC"")"),"MARCOS PAULO DA SILVA ALMEIDA") -> MARCOS PAULO DA SILVA ALMEIDA | N13: =IFERROR(__xludf.DUMMYFUNCTION("IFERROR(VLOOKUP(D13, IMPORTRANGE(""https://docs.google.com/spreadsheets/d/1MjHtlUikwobi2MaWJgy7tfLeBmhj1u-dRFRs_8GwSoA/edit#gid=0"",""Gestores Escolares!D7:J""),4,0),""VERIFICAR CÓD SEC"")"),"(74) 9 9998-8112") -> (74) 9 9998-8112 | O13: =IFERROR(__xludf.DUMMYFUNCTION("IFERROR(VLOOKUP(D13, IMPORTRANGE(""https://docs.google.com/spreadsheets/d/1MjHtlUikwobi2MaWJgy7tfLeBmhj1u-dRFRs_8GwSoA/edit#gid=0"",""Gestores Escolares!D7:J""),6,0),""VERIFICAR CÓD SEC"")"),"FERNANDA MIRANDA CAMPOS") -> FERNANDA MIRANDA CAMPOS | P13: =IFERROR(__xludf.DUMMYFUNCTION("IFERROR(VLOOKUP(D13, IMPORTRANGE(""https://docs.google.com/spreadsheets/d/1MjHtlUikwobi2MaWJgy7tfLeBmhj1u-dRFRs_8GwSoA/edit#gid=0"",""Gestores Escolares!D7:J""),7,0),""VERIFICAR CÓD SEC"")"),"(74) 9 9963-4717") -> (74) 9 9963-4717 | Q13: =IFERROR(__xludf.DUMMYFUNCTION("IFERROR(VLOOKUP(D13, IMPORTRANGE(""https://docs.google.com/spreadsheets/d/1MjHtlUikwobi2MaWJgy7tfLeBmhj1u-dRFRs_8GwSoA/edit#gid=0"",""Gestores Escolares!D7:m""),9,0),""VERIFICAR CÓD SEC"")"),"") | R13: =IFERROR(__xludf.DUMMYFUNCTION("IFERROR(VLOOKUP(D13, IMPORTRANGE(""https://docs.google.com/spreadsheets/d/1MjHtlUikwobi2MaWJgy7tfLeBmhj1u-dRFRs_8GwSoA/edit#gid=0"",""Gestores Escolares!D7:m""),10,0),""VERIFICAR CÓD SEC"")"),"") | T13: 2 | U13: 2 | V13: 0 | W13: 0 | X13: 0 | Y13: 0 | Z13: =SUM(V13:Y13) -> 0 | AA13: 0 | AB13: 0 | AC13: 0 | AD13: 0 | AE13: =SUM(AA13:AD13) -> 0 | AF13: 0 | AG13: 0 | AH13: 55 | AI13: 0 | AJ13: =SUM(AF13:AI13) -> 55 | AK13: 0 | AL13: 0 | AM13: 0 | AN13: =SUM(AK13:AM13) -> 0 | AO13: 0 | AP13: 0 | AQ13: 0 | AR13: =SUM(AO13:AQ13) -> 0 | AS13: 0 | AT13: 0 | AU13: 0 | AV13: 0 | AW13: =SUM(AS13:AV13) -> 0 | AX13: =SUM(AY13:AZ13) -> 55 | AY13: =SUM(AV13,AT13,AS13,AP13,AO13,AL13,AK13,AI13,AG13,AF13,AD13,AB13,AA13,Y13,W13,V13) -> 0 | AZ13: =SUM(AU13,AQ13,AM13,AH13,AC13,X13) -> 55 | BA13: 0 | BB13: =SUM(AX13+BA13) -> 55 | BC13: A DEFINIR | BD13: CEMIT | BE13: PROFISSIONAL | BG13: 1178790 | BI13: 2 | BJ13: PADRÃO ANTIGO | BK13: =Y13+AD13+AI13+AV13 -> 0 | BL13: =V13+W13+AA13+AB13+AF13+AG13+AK13+AL13+AO13+AP13+AS13+AT13 -> 0 | BM13: =IFERROR(__xludf.DUMMYFUNCTION("IFERROR(VLOOKUP(BG13,IMPORTRANGE(""https://docs.google.com/spreadsheets/d/1juPI-Fb8LD0YtltB2mlGEnp_R3UVu1t3wSFPzgCyHXE/edit?gid=0#gid=0"",""GERAL!A2:C""),3,0),""-"")"),"-") -> -
A14: NTE 01 - IRECÊ | B14: BARRA DO MENDES | C14: ANEXO | D14: 1179281 | E14: 1178789 | F14: 29459141 | G14: ANEXO - CEMIT - IRECÊ - DISTRITO DE CAPIM DURO | H14: DISTRITO DE CAPIM DURO - S/N | I14: DISTRITO DE CAPIM DURO | J14: 37KM | K14: CEDIDO | L14: PEQUENO | M14: =IFERROR(__xludf.DUMMYFUNCTION("IFERROR(VLOOKUP(D14, IMPORTRANGE(""https://docs.google.com/spreadsheets/d/1MjHtlUikwobi2MaWJgy7tfLeBmhj1u-dRFRs_8GwSoA/edit#gid=0"",""Gestores Escolares!D7:J""),3,0),""VERIFICAR CÓD SEC"")"),"MARCOS PAULO DA SILVA ALMEIDA") -> MARCOS PAULO DA SILVA ALMEIDA | N14: =IFERROR(__xludf.DUMMYFUNCTION("IFERROR(VLOOKUP(D14, IMPORTRANGE(""https://docs.google.com/spreadsheets/d/1MjHtlUikwobi2MaWJgy7tfLeBmhj1u-dRFRs_8GwSoA/edit#gid=0"",""Gestores Escolares!D7:J""),4,0),""VERIFICAR CÓD SEC"")"),"(74) 9 9998-8112") -> (74) 9 9998-8112 | O14: =IFERROR(__xludf.DUMMYFUNCTION("IFERROR(VLOOKUP(D14, IMPORTRANGE(""https://docs.google.com/spreadsheets/d/1MjHtlUikwobi2MaWJgy7tfLeBmhj1u-dRFRs_8GwSoA/edit#gid=0"",""Gestores Escolares!D7:J""),6,0),""VERIFICAR CÓD SEC"")"),"FERNANDA MIRANDA CAMPOS") -> FERNANDA MIRANDA CAMPOS | P14: =IFERROR(__xludf.DUMMYFUNCTION("IFERROR(VLOOKUP(D14, IMPORTRANGE(""https://docs.google.com/spreadsheets/d/1MjHtlUikwobi2MaWJgy7tfLeBmhj1u-dRFRs_8GwSoA/edit#gid=0"",""Gestores Escolares!D7:J""),7,0),""VERIFICAR CÓD SEC"")"),"(74) 9 9963-4717") -> (74) 9 9963-4717 | Q14: =IFERROR(__xludf.DUMMYFUNCTION("IFERROR(VLOOKUP(D14, IMPORTRANGE(""https://docs.google.com/spreadsheets/d/1MjHtlUikwobi2MaWJgy7tfLeBmhj1u-dRFRs_8GwSoA/edit#gid=0"",""Gestores Escolares!D7:m""),9,0),""VERIFICAR CÓD SEC"")"),"") | R14: =IFERROR(__xludf.DUMMYFUNCTION("IFERROR(VLOOKUP(D14, IMPORTRANGE(""https://docs.google.com/spreadsheets/d/1MjHtlUikwobi2MaWJgy7tfLeBmhj1u-dRFRs_8GwSoA/edit#gid=0"",""Gestores Escolares!D7:m""),10,0),""VERIFICAR CÓD SEC"")"),"") | T14: 4 | U14: 4 | V14: 0 | W14: 0 | X14: 0 | Y14: 0 | Z14: =SUM(V14:Y14) -> 0 | AA14: 0 | AB14: 0 | AC14: 0 | AD14: 0 | AE14: =SUM(AA14:AD14) -> 0 | AF14: 26 | AG14: 0 | AH14: 84 | AI14: 0 | AJ14: =SUM(AF14:AI14) -> 110 | AK14: 0 | AL14: 0 | AM14: 0 | AN14: =SUM(AK14:AM14) -> 0 | AO14: 0 | AP14: 0 | AQ14: 0 | AR14: =SUM(AO14:AQ14) -> 0 | AS14: 0 | AT14: 0 | AU14: 0 | AV14: 0 | AW14: =SUM(AS14:AV14) -> 0 | AX14: =SUM(AY14:AZ14) -> 110 | AY14: =SUM(AV14,AT14,AS14,AP14,AO14,AL14,AK14,AI14,AG14,AF14,AD14,AB14,AA14,Y14,W14,V14) -> 26 | AZ14: =SUM(AU14,AQ14,AM14,AH14,AC14,X14) -> 84 | BA14: 0 | BB14: =SUM(AX14+BA14) -> 110 | BC14: A DEFINIR | BD14: CEMIT | BE14: PROFISSIONAL | BG14: 1178789 | BI14: 4 | BJ14: PADRÃO ANTIGO | BK14: =Y14+AD14+AI14+AV14 -> 0 | BL14: =V14+W14+AA14+AB14+AF14+AG14+AK14+AL14+AO14+AP14+AS14+AT14 -> 26 | BM14: =IFERROR(__xludf.DUMMYFUNCTION("IFERROR(VLOOKUP(BG14,IMPORTRANGE(""https://docs.google.com/spreadsheets/d/1juPI-Fb8LD0YtltB2mlGEnp_R3UVu1t3wSFPzgCyHXE/edit?gid=0#gid=0"",""GERAL!A2:C""),3,0),""-"")"),"-") -> -
A15: NTE 01 - IRECÊ | B15: BARRO ALTO | C15: ESCOLA | D15: 1179833 | F15: 29496969 | G15: COLEGIO ESTADUAL DO CAMPO DE GAMELEIRA | H15: RUA SETE DE SETEMBRO, Nº S/N | I15: CENTRO | K15: PRÓPRIO | L15: PEQUENO | M15: =IFERROR(__xludf.DUMMYFUNCTION("IFERROR(VLOOKUP(D15, IMPORTRANGE(""https://docs.google.com/spreadsheets/d/1MjHtlUikwobi2MaWJgy7tfLeBmhj1u-dRFRs_8GwSoA/edit#gid=0"",""Gestores Escolares!D7:J""),3,0),""VERIFICAR CÓD SEC"")"),"JANIVALDA ROSA MIRANDA") -> JANIVALDA ROSA MIRANDA | N15: =IFERROR(__xludf.DUMMYFUNCTION("IFERROR(VLOOKUP(D15, IMPORTRANGE(""https://docs.google.com/spreadsheets/d/1MjHtlUikwobi2MaWJgy7tfLeBmhj1u-dRFRs_8GwSoA/edit#gid=0"",""Gestores Escolares!D7:J""),4,0),""VERIFICAR CÓD SEC"")"),"(74) 9 9806-9091") -> (74) 9 9806-9091 | O15: =IFERROR(__xludf.DUMMYFUNCTION("IFERROR(VLOOKUP(D15, IMPORTRANGE(""https://docs.google.com/spreadsheets/d/1MjHtlUikwobi2MaWJgy7tfLeBmhj1u-dRFRs_8GwSoA/edit#gid=0"",""Gestores Escolares!D7:J""),6,0),""VERIFICAR CÓD SEC"")"),"") | P15: =IFERROR(__xludf.DUMMYFUNCTION("IFERROR(VLOOKUP(D15, IMPORTRANGE(""https://docs.google.com/spreadsheets/d/1MjHtlUikwobi2MaWJgy7tfLeBmhj1u-dRFRs_8GwSoA/edit#gid=0"",""Gestores Escolares!D7:J""),7,0),""VERIFICAR CÓD SEC"")"),"") | Q15: =IFERROR(__xludf.DUMMYFUNCTION("IFERROR(VLOOKUP(D15, IMPORTRANGE(""https://docs.google.com/spreadsheets/d/1MjHtlUikwobi2MaWJgy7tfLeBmhj1u-dRFRs_8GwSoA/edit#gid=0"",""Gestores Escolares!D7:m""),9,0),""VERIFICAR CÓD SEC"")"),"") | R15: =IFERROR(__xludf.DUMMYFUNCTION("IFERROR(VLOOKUP(D15, IMPORTRANGE(""https://docs.google.com/spreadsheets/d/1MjHtlUikwobi2MaWJgy7tfLeBmhj1u-dRFRs_8GwSoA/edit#gid=0"",""Gestores Escolares!D7:m""),10,0),""VERIFICAR CÓD SEC"")"),"") | V15: 0 | W15: 0 | X15: 0 | Y15: 0 | Z15: =SUM(V15:Y15) -> 0 | AA15: 0 | AB15: 0 | AC15: 0 | AD15: 0 | AE15: =SUM(AA15:AD15) -> 0 | AF15: 59 | AG15: 121 | AH15: 0 | AI15: 0 | AJ15: =SUM(AF15:AI15) -> 180 | AK15: 0 | AL15: 0 | AM15: 0 | AN15: =SUM(AK15:AM15) -> 0 | AO15: 0 | AP15: 0 | AQ15: 54 | AR15: =SUM(AO15:AQ15) -> 54 | AS15: 0 | AT15: 0 | AU15: 21 | AV15: 0 | AW15: =SUM(AS15:AV15) -> 21 | AX15: =SUM(AY15:AZ15) -> 255 | AY15: =SUM(AV15,AT15,AS15,AP15,AO15,AL15,AK15,AI15,AG15,AF15,AD15,AB15,AA15,Y15,W15,V15) -> 180 | AZ15: =SUM(AU15,AQ15,AM15,AH15,AC15,X15) -> 75 | BA15: 0 | BB15: =SUM(AX15+BA15) -> 255 | BC15: A DEFINIR | BD15: A DEFINIR | BE15: A DEFINIR | BG15: 1179833 | BK15: =Y15+AD15+AI15+AV15 -> 0 | BL15: =V15+W15+AA15+AB15+AF15+AG15+AK15+AL15+AO15+AP15+AS15+AT15 -> 180 | BM15: =IFERROR(__xludf.DUMMYFUNCTION("IFERROR(VLOOKUP(BG15,IMPORTRANGE(""https://docs.google.com/spreadsheets/d/1juPI-Fb8LD0YtltB2mlGEnp_R3UVu1t3wSFPzgCyHXE/edit?gid=0#gid=0"",""GERAL!A2:C""),3,0),""-"")"),"CAMPO") -> CAMPO
A16: NTE 01 - IRECÊ | B16: BARRO ALTO | C16: ESCOLA | D16: 1126212 | F16: 29059380 | G16: COLEGIO ESTADUAL DE TEMPO INTEGRAL NECY NOVAIS | H16: PRACA DA BANDEIRA - 282 | I16: CENTRO | J16: SEDE | K16: PRÓPRIO | L16: MÉDIO | M16: =IFERROR(__xludf.DUMMYFUNCTION("IFERROR(VLOOKUP(D16, IMPORTRANGE(""https://docs.google.com/spreadsheets/d/1MjHtlUikwobi2MaWJgy7tfLeBmhj1u-dRFRs_8GwSoA/edit#gid=0"",""Gestores Escolares!D7:J""),3,0),""VERIFICAR CÓD SEC"")"),"ARMANDA ANDRADE BARRETO RAMOS") -> ARMANDA ANDRADE BARRETO RAMOS | N16: =IFERROR(__xludf.DUMMYFUNCTION("IFERROR(VLOOKUP(D16, IMPORTRANGE(""https://docs.google.com/spreadsheets/d/1MjHtlUikwobi2MaWJgy7tfLeBmhj1u-dRFRs_8GwSoA/edit#gid=0"",""Gestores Escolares!D7:J""),4,0),""VERIFICAR CÓD SEC"")"),"(74) 9 9936-0280") -> (74) 9 9936-0280 | O16: =IFERROR(__xludf.DUMMYFUNCTION("IFERROR(VLOOKUP(D16, IMPORTRANGE(""https://docs.google.com/spreadsheets/d/1MjHtlUikwobi2MaWJgy7tfLeBmhj1u-dRFRs_8GwSoA/edit#gid=0"",""Gestores Escolares!D7:J""),6,0),""VERIFICAR CÓD SEC"")")," RAMON ROCHA RIBEIRO") -> RAMON ROCHA RIBEIRO | P16: =IFERROR(__xludf.DUMMYFUNCTION("IFERROR(VLOOKUP(D16, IMPORTRANGE(""https://docs.google.com/spreadsheets/d/1MjHtlUikwobi2MaWJgy7tfLeBmhj1u-dRFRs_8GwSoA/edit#gid=0"",""Gestores Escolares!D7:J""),7,0),""VERIFICAR CÓD SEC"")"),"(74) 9 8114-6964") -> (74) 9 8114-6964 | Q16: =IFERROR(__xludf.DUMMYFUNCTION("IFERROR(VLOOKUP(D16, IMPORTRANGE(""https://docs.google.com/spreadsheets/d/1MjHtlUikwobi2MaWJgy7tfLeBmhj1u-dRFRs_8GwSoA/edit#gid=0"",""Gestores Escolares!D7:m""),9,0),""VERIFICAR CÓD SEC"")"),"") | R16: =IFERROR(__xludf.DUMMYFUNCTION("IFERROR(VLOOKUP(D16, IMPORTRANGE(""https://docs.google.com/spreadsheets/d/1MjHtlUikwobi2MaWJgy7tfLeBmhj1u-dRFRs_8GwSoA/edit#gid=0"",""Gestores Escolares!D7:m""),10,0),""VERIFICAR CÓD SEC"")"),"") | T16: 5 | U16: 06 salas, sendo 05 utilizadas para aula, 01 adaptada para biblioteca e sala de vídeo. | V16: 0 | W16: 0 | X16: 0 | Y16: 0 | Z16: =SUM(V16:Y16) -> 0 | AA16: 0 | AB16: 0 | AC16: 0 | AD16: 0 | AE16: =SUM(AA16:AD16) -> 0 | AF16: 133 | AG16: 123 | AH16: 0 | AI16: 0 | AJ16: =SUM(AF16:AI16) -> 256 | AK16: 0 | AL16: 0 | AM16: 0 | AN16: =SUM(AK16:AM16) -> 0 | AO16: 0 | AP16: 0 | AQ16: 0 | AR16: =SUM(AO16:AQ16) -> 0 | AS16: 31 | AT16: 24 | AU16: 26 | AV16: 0 | AW16: =SUM(AS16:AV16) -> 81 | AX16: =SUM(AY16:AZ16) -> 337 | AY16: =SUM(AV16,AT16,AS16,AP16,AO16,AL16,AK16,AI16,AG16,AF16,AD16,AB16,AA16,Y16,W16,V16) -> 311 | AZ16: =SUM(AU16,AQ16,AM16,AH16,AC16,X16) -> 26 | BA16: 0 | BB16: =SUM(AX16+BA16) -> 337 | BC16: A DEFINIR | BD16: A DEFINIR | BE16: A DEFINIR | BG16: 1126212 | BH16: -11.317796181873934, -39.85582524236693 | BI16: 5 | BJ16: PADRÃO ANTIGO | BK16: =Y16+AD16+AI16+AV16 -> 0 | BL16: =V16+W16+AA16+AB16+AF16+AG16+AK16+AL16+AO16+AP16+AS16+AT16 -> 311 | BM16: =IFERROR(__xludf.DUMMYFUNCTION("IFERROR(VLOOKUP(BG16,IMPORTRANGE(""https://docs.google.com/spreadsheets/d/1juPI-Fb8LD0YtltB2mlGEnp_R3UVu1t3wSFPzgCyHXE/edit?gid=0#gid=0"",""GERAL!A2:C""),3,0),""-"")"),"-") -> -
A17: NTE 01 - IRECÊ | B17: CAFARNAUM | C17: ESCOLA | D17: 1126247 | F17: 29060001 | G17: COLÉGIO ESTADUAL DE TEMPO INTEGRAL IMACULADA CONCEIÇÃO | H17: CIRILO TOME DA SILVA - SN(00028) | I17: CENTRO | J17: SEDE | K17: PRÓPRIO | L17: GRANDE | M17: =IFERROR(__xludf.DUMMYFUNCTION("IFERROR(VLOOKUP(D17, IMPORTRANGE(""https://docs.google.com/spreadsheets/d/1MjHtlUikwobi2MaWJgy7tfLeBmhj1u-dRFRs_8GwSoA/edit#gid=0"",""Gestores Escolares!D7:J""),3,0),""VERIFICAR CÓD SEC"")"),"CÍCERA MARIA PIRES") -> CÍCERA MARIA PIRES | N17: =IFERROR(__xludf.DUMMYFUNCTION("IFERROR(VLOOKUP(D17, IMPORTRANGE(""https://docs.google.com/spreadsheets/d/1MjHtlUikwobi2MaWJgy7tfLeBmhj1u-dRFRs_8GwSoA/edit#gid=0"",""Gestores Escolares!D7:J""),4,0),""VERIFICAR CÓD SEC"")"),"(62) 9 9607-3189") -> (62) 9 9607-3189 | O17: =IFERROR(__xludf.DUMMYFUNCTION("IFERROR(VLOOKUP(D17, IMPORTRANGE(""https://docs.google.com/spreadsheets/d/1MjHtlUikwobi2MaWJgy7tfLeBmhj1u-dRFRs_8GwSoA/edit#gid=0"",""Gestores Escolares!D7:J""),6,0),""VERIFICAR CÓD SEC"")"),"CEZAR LOPES DE SOUZA") -> CEZAR LOPES DE SOUZA | P17: =IFERROR(__xludf.DUMMYFUNCTION("IFERROR(VLOOKUP(D17, IMPORTRANGE(""https://docs.google.com/spreadsheets/d/1MjHtlUikwobi2MaWJgy7tfLeBmhj1u-dRFRs_8GwSoA/edit#gid=0"",""Gestores Escolares!D7:J""),7,0),""VERIFICAR CÓD SEC"")"),"(74) 9 9804-9765") -> (74) 9 9804-9765 | Q17: =IFERROR(__xludf.DUMMYFUNCTION("IFERROR(VLOOKUP(D17, IMPORTRANGE(""https://docs.google.com/spreadsheets/d/1MjHtlUikwobi2MaWJgy7tfLeBmhj1u-dRFRs_8GwSoA/edit#gid=0"",""Gestores Escolares!D7:m""),9,0),""VERIFICAR CÓD SEC"")"),"") | R17: =IFERROR(__xludf.DUMMYFUNCTION("IFERROR(VLOOKUP(D17, IMPORTRANGE(""https://docs.google.com/spreadsheets/d/1MjHtlUikwobi2MaWJgy7tfLeBmhj1u-dRFRs_8GwSoA/edit#gid=0"",""Gestores Escolares!D7:m""),10,0),""VERIFICAR CÓD SEC"")"),"") | T17: 9 | U17: 17 | V17: 0 | W17: 0 | X17: 0 | Y17: 0 | Z17: =SUM(V17:Y17) -> 0 | AA17: 0 | AB17: 0 | AC17: 0 | AD17: 0 | AE17: =SUM(AA17:AD17) -> 0 | AF17: 0 | AG17: 0 | AH17: 0 | AI17: 555 | AJ17: =SUM(AF17:AI17) -> 555 | AK17: 0 | AL17: 0 | AM17: 0 | AN17: =SUM(AK17:AM17) -> 0 | AO17: 0 | AP17: 0 | AQ17: 108 | AR17: =SUM(AO17:AQ17) -> 108 | AS17: 0 | AT17: 0 | AU17: 0 | AV17: 82 | AW17: =SUM(AS17:AV17) -> 82 | AX17: =SUM(AY17:AZ17) -> 745 | AY17: =SUM(AV17,AT17,AS17,AP17,AO17,AL17,AK17,AI17,AG17,AF17,AD17,AB17,AA17,Y17,W17,V17) -> 637 | AZ17: =SUM(AU17,AQ17,AM17,AH17,AC17,X17) -> 108 | BA17: 0 | BB17: =SUM(AX17+BA17) -> 745 | BC17: A DEFINIR | BD17: A DEFINIR | BE17: A DEFINIR | BG17: 1126247 | BH17: -11.689388913938808, -41.475732103318904 | BI17: 9 | BJ17: NOVO PADRÃO (NOVA ESCOLA) | BK17: =Y17+AD17+AI17+AV17 -> 637 | BL17: =V17+W17+AA17+AB17+AF17+AG17+AK17+AL17+AO17+AP17+AS17+AT17 -> 0 | BM17: =IFERROR(__xludf.DUMMYFUNCTION("IFERROR(VLOOKUP(BG17,IMPORTRANGE(""https://docs.google.com/spreadsheets/d/1juPI-Fb8LD0YtltB2mlGEnp_R3UVu1t3wSFPzgCyHXE/edit?gid=0#gid=0"",""GERAL!A2:C""),3,0),""-"")"),"-") -> -
A18: NTE 01 - IRECÊ | B18: CAFARNAUM | C18: ANEXO | D18: 1179281 | E18: 1178792 | F18: 29459141 | G18: ANEXO - CEMIT - IRECÊ - DISTRITO DE CANAL | H18: HELIO MARQUES BARRETO - SN(00006) | I18: DISTRITO DE CANAL | J18: 22KM | K18: PRÓPRIO | L18: PEQUENO | M18: =IFERROR(__xludf.DUMMYFUNCTION("IFERROR(VLOOKUP(D18, IMPORTRANGE(""https://docs.google.com/spreadsheets/d/1MjHtlUikwobi2MaWJgy7tfLeBmhj1u-dRFRs_8GwSoA/edit#gid=0"",""Gestores Escolares!D7:J""),3,0),""VERIFICAR CÓD SEC"")"),"MARCOS PAULO DA SILVA ALMEIDA") -> MARCOS PAULO DA SILVA ALMEIDA | N18: =IFERROR(__xludf.DUMMYFUNCTION("IFERROR(VLOOKUP(D18, IMPORTRANGE(""https://docs.google.com/spreadsheets/d/1MjHtlUikwobi2MaWJgy7tfLeBmhj1u-dRFRs_8GwSoA/edit#gid=0"",""Gestores Escolares!D7:J""),4,0),""VERIFICAR CÓD SEC"")"),"(74) 9 9998-8112") -> (74) 9 9998-8112 | O18: =IFERROR(__xludf.DUMMYFUNCTION("IFERROR(VLOOKUP(D18, IMPORTRANGE(""https://docs.google.com/spreadsheets/d/1MjHtlUikwobi2MaWJgy7tfLeBmhj1u-dRFRs_8GwSoA/edit#gid=0"",""Gestores Escolares!D7:J""),6,0),""VERIFICAR CÓD SEC"")"),"FERNANDA MIRANDA CAMPOS") -> FERNANDA MIRANDA CAMPOS | P18: =IFERROR(__xludf.DUMMYFUNCTION("IFERROR(VLOOKUP(D18, IMPORTRANGE(""https://docs.google.com/spreadsheets/d/1MjHtlUikwobi2MaWJgy7tfLeBmhj1u-dRFRs_8GwSoA/edit#gid=0"",""Gestores Escolares!D7:J""),7,0),""VERIFICAR CÓD SEC"")"),"(74) 9 9963-4717") -> (74) 9 9963-4717 | Q18: =IFERROR(__xludf.DUMMYFUNCTION("IFERROR(VLOOKUP(D18, IMPORTRANGE(""https://docs.google.com/spreadsheets/d/1MjHtlUikwobi2MaWJgy7tfLeBmhj1u-dRFRs_8GwSoA/edit#gid=0"",""Gestores Escolares!D7:m""),9,0),""VERIFICAR CÓD SEC"")"),"") | R18: =IFERROR(__xludf.DUMMYFUNCTION("IFERROR(VLOOKUP(D18, IMPORTRANGE(""https://docs.google.com/spreadsheets/d/1MjHtlUikwobi2MaWJgy7tfLeBmhj1u-dRFRs_8GwSoA/edit#gid=0"",""Gestores Escolares!D7:m""),10,0),""VERIFICAR CÓD SEC"")"),"") | T18: 3 | U18: 1 | V18: 0 | W18: 0 | X18: 0 | Y18: 0 | Z18: =SUM(V18:Y18) -> 0 | AA18: 0 | AB18: 0 | AC18: 0 | AD18: 0 | AE18: =SUM(AA18:AD18) -> 0 | AF18: 0 | AG18: 0 | AH18: 60 | AI18: 0 | AJ18: =SUM(AF18:AI18) -> 60 | AK18: 0 | AL18: 0 | AM18: 0 | AN18: =SUM(AK18:AM18) -> 0 | AO18: 0 | AP18: 0 | AQ18: 0 | AR18: =SUM(AO18:AQ18) -> 0 | AS18: 0 | AT18: 0 | AU18: 0 | AV18: 0 | AW18: =SUM(AS18:AV18) -> 0 | AX18: =SUM(AY18:AZ18) -> 60 | AY18: =SUM(AV18,AT18,AS18,AP18,AO18,AL18,AK18,AI18,AG18,AF18,AD18,AB18,AA18,Y18,W18,V18) -> 0 | AZ18: =SUM(AU18,AQ18,AM18,AH18,AC18,X18) -> 60 | BA18: 0 | BB18: =SUM(AX18+BA18) -> 60 | BC18: A DEFINIR | BD18: CEMIT | BE18: PROFISSIONAL | BG18: 1178792 | BI18: 3 | BJ18: PADRÃO ANTIGO | BK18: =Y18+AD18+AI18+AV18 -> 0 | BL18: =V18+W18+AA18+AB18+AF18+AG18+AK18+AL18+AO18+AP18+AS18+AT18 -> 0 | BM18: =IFERROR(__xludf.DUMMYFUNCTION("IFERROR(VLOOKUP(BG18,IMPORTRANGE(""https://docs.google.com/spreadsheets/d/1juPI-Fb8LD0YtltB2mlGEnp_R3UVu1t3wSFPzgCyHXE/edit?gid=0#gid=0"",""GERAL!A2:C""),3,0),""-"")"),"-") -> -
A19: NTE 01 - IRECÊ | B19: CANARANA | C19: ESCOLA | D19: 1163100 | F19: 29060214 | G19: COLÉGIO ESTADUAL JOSÉ RIBEIRO DE ARAUJO | H19: RUA 16 DE JULHO - 177 | I19: CENTRO | J19: SEDE | K19: PRÓPRIO | L19: GRANDE | M19: =IFERROR(__xludf.DUMMYFUNCTION("IFERROR(VLOOKUP(D19, IMPORTRANGE(""https://docs.google.com/spreadsheets/d/1MjHtlUikwobi2MaWJgy7tfLeBmhj1u-dRFRs_8GwSoA/edit#gid=0"",""Gestores Escolares!D7:J""),3,0),""VERIFICAR CÓD SEC"")"),"OSIAS CARDOSO PIMENTA") -> OSIAS CARDOSO PIMENTA | N19: =IFERROR(__xludf.DUMMYFUNCTION("IFERROR(VLOOKUP(D19, IMPORTRANGE(""https://docs.google.com/spreadsheets/d/1MjHtlUikwobi2MaWJgy7tfLeBmhj1u-dRFRs_8GwSoA/edit#gid=0"",""Gestores Escolares!D7:J""),4,0),""VERIFICAR CÓD SEC"")"),"(74) 9 9988-0421") -> (74) 9 9988-0421 | O19: =IFERROR(__xludf.DUMMYFUNCTION("IFERROR(VLOOKUP(D19, IMPORTRANGE(""https://docs.google.com/spreadsheets/d/1MjHtlUikwobi2MaWJgy7tfLeBmhj1u-dRFRs_8GwSoA/edit#gid=0"",""Gestores Escolares!D7:J""),6,0),""VERIFICAR CÓD SEC"")"),"MONICA ALMEIDA DA SILVA GONÇALVES") -> MONICA ALMEIDA DA SILVA GONÇALVES | P19: =IFERROR(__xludf.DUMMYFUNCTION("IFERROR(VLOOKUP(D19, IMPORTRANGE(""https://docs.google.com/spreadsheets/d/1MjHtlUikwobi2MaWJgy7tfLeBmhj1u-dRFRs_8GwSoA/edit#gid=0"",""Gestores Escolares!D7:J""),7,0),""VERIFICAR CÓD SEC"")"),"(74) 9 9973-3834") -> (74) 9 9973-3834 | Q19: =IFERROR(__xludf.DUMMYFUNCTION("IFERROR(VLOOKUP(D19, IMPORTRANGE(""https://docs.google.com/spreadsheets/d/1MjHtlUikwobi2MaWJgy7tfLeBmhj1u-dRFRs_8GwSoA/edit#gid=0"",""Gestores Escolares!D7:m""),9,0),""VERIFICAR CÓD SEC"")"),"CALEBE MIRANDA DA SILVA") -> CALEBE MIRANDA DA SILVA | R19: =IFERROR(__xludf.DUMMYFUNCTION("IFERROR(VLOOKUP(D19, IMPORTRANGE(""https://docs.google.com/spreadsheets/d/1MjHtlUikwobi2MaWJgy7tfLeBmhj1u-dRFRs_8GwSoA/edit#gid=0"",""Gestores Escolares!D7:m""),10,0),""VERIFICAR CÓD SEC"")"),"(74) 9 9969-0595") -> (74) 9 9969-0595 | T19: 13 | U19: 10 + 03 (Adapt) | V19: 0 | W19: 0 | X19: 0 | Y19: 0 | Z19: =SUM(V19:Y19) -> 0 | AA19: 0 | AB19: 0 | AC19: 0 | AD19: 0 | AE19: =SUM(AA19:AD19) -> 0 | AF19: 0 | AG19: 0 | AH19: 0 | AI19: 489 | AJ19: =SUM(AF19:AI19) -> 489 | AK19: 0 | AL19: 0 | AM19: 0 | AN19: =SUM(AK19:AM19) -> 0 | AO19: 0 | AP19: 0 | AQ19: 0 | AR19: =SUM(AO19:AQ19) -> 0 | AS19: 0 | AT19: 0 | AU19: 98 | AV19: 0 | AW19: =SUM(AS19:AV19) -> 98 | AX19: =SUM(AY19:AZ19) -> 587 | AY19: =SUM(AV19,AT19,AS19,AP19,AO19,AL19,AK19,AI19,AG19,AF19,AD19,AB19,AA19,Y19,W19,V19) -> 489 | AZ19: =SUM(AU19,AQ19,AM19,AH19,AC19,X19) -> 98 | BA19: 0 | BB19: =SUM(AX19+BA19) -> 587 | BC19: A DEFINIR | BD19: A DEFINIR | BE19: A DEFINIR | BG19: 1163100 | BH19: -11.686352338828677, -41.769402236241454 | BI19: 10 | BJ19: PADRÃO ANTIGO | BK19: =Y19+AD19+AI19+AV19 -> 489 | BL19: =V19+W19+AA19+AB19+AF19+AG19+AK19+AL19+AO19+AP19+AS19+AT19 -> 0 | BM19: =IFERROR(__xludf.DUMMYFUNCTION("IFERROR(VLOOKUP(BG19,IMPORTRANGE(""https://docs.google.com/spreadsheets/d/1juPI-Fb8LD0YtltB2mlGEnp_R3UVu1t3wSFPzgCyHXE/edit?gid=0#gid=0"",""GERAL!A2:C""),3,0),""-"")"),"-") -> -
A20: NTE 01 - IRECÊ | B20: CANARANA | C20: ESCOLA | D20: 1137583 | F20: 29060206 | G20: COLÉGIO ESTADUAL DO CAMPO MAXIMINO MARTINS - DISTRITO DE SALOBRO | H20: PRAÇA CATÃO DOURADO - SN(00020) | I20: CENTRO | J20: 22KM | K20: PRÓPRIO | L20: MÉDIO | M20: =IFERROR(__xludf.DUMMYFUNCTION("IFERROR(VLOOKUP(D20, IMPORTRANGE(""https://docs.google.com/spreadsheets/d/1MjHtlUikwobi2MaWJgy7tfLeBmhj1u-dRFRs_8GwSoA/edit#gid=0"",""Gestores Escolares!D7:J""),3,0),""VERIFICAR CÓD SEC"")"),"LEDA DOURADO CARNEIRO MARTINS") -> LEDA DOURADO CARNEIRO MARTINS | N20: =IFERROR(__xludf.DUMMYFUNCTION("IFERROR(VLOOKUP(D20, IMPORTRANGE(""https://docs.google.com/spreadsheets/d/1MjHtlUikwobi2MaWJgy7tfLeBmhj1u-dRFRs_8GwSoA/edit#gid=0"",""Gestores Escolares!D7:J""),4,0),""VERIFICAR CÓD SEC"")"),"(74) 9 9996-9536") -> (74) 9 9996-9536 | O20: =IFERROR(__xludf.DUMMYFUNCTION("IFERROR(VLOOKUP(D20, IMPORTRANGE(""https://docs.google.com/spreadsheets/d/1MjHtlUikwobi2MaWJgy7tfLeBmhj1u-dRFRs_8GwSoA/edit#gid=0"",""Gestores Escolares!D7:J""),6,0),""VERIFICAR CÓD SEC"")"),"VAGNER NASCIMENTO MACHADO") -> VAGNER NASCIMENTO MACHADO | P20: =IFERROR(__xludf.DUMMYFUNCTION("IFERROR(VLOOKUP(D20, IMPORTRANGE(""https://docs.google.com/spreadsheets/d/1MjHtlUikwobi2MaWJgy7tfLeBmhj1u-dRFRs_8GwSoA/edit#gid=0"",""Gestores Escolares!D7:J""),7,0),""VERIFICAR CÓD SEC"")"),"(74) 9 9996-9006") -> (74) 9 9996-9006 | Q20: =IFERROR(__xludf.DUMMYFUNCTION("IFERROR(VLOOKUP(D20, IMPORTRANGE(""https://docs.google.com/spreadsheets/d/1MjHtlUikwobi2MaWJgy7tfLeBmhj1u-dRFRs_8GwSoA/edit#gid=0"",""Gestores Escolares!D7:m""),9,0),""VERIFICAR CÓD SEC"")"),"") | R20: =IFERROR(__xludf.DUMMYFUNCTION("IFERROR(VLOOKUP(D20, IMPORTRANGE(""https://docs.google.com/spreadsheets/d/1MjHtlUikwobi2MaWJgy7tfLeBmhj1u-dRFRs_8GwSoA/edit#gid=0"",""Gestores Escolares!D7:m""),10,0),""VERIFICAR CÓD SEC"")"),"") | T20: 8 | U20: 8 | V20: 0 | W20: 0 | X20: 0 | Y20: 0 | Z20: =SUM(V20:Y20) -> 0 | AA20: 0 | AB20: 0 | AC20: 0 | AD20: 0 | AE20: =SUM(AA20:AD20) -> 0 | AF20: 149 | AG20: 0 | AH20: 0 | AI20: 78 | AJ20: =SUM(AF20:AI20) -> 227 | AK20: 0 | AL20: 0 | AM20: 0 | AN20: =SUM(AK20:AM20) -> 0 | AO20: 0 | AP20: 0 | AQ20: 30 | AR20: =SUM(AO20:AQ20) -> 30 | AS20: 0 | AT20: 0 | AU20: 0 | AV20: 0 | AW20: =SUM(AS20:AV20) -> 0 | AX20: =SUM(AY20:AZ20) -> 257 | AY20: =SUM(AV20,AT20,AS20,AP20,AO20,AL20,AK20,AI20,AG20,AF20,AD20,AB20,AA20,Y20,W20,V20) -> 227 | AZ20: =SUM(AU20,AQ20,AM20,AH20,AC20,X20) -> 30 | BA20: 0 | BB20: =SUM(AX20+BA20) -> 257 | BC20: DO CAMPO | BD20: A DEFINIR | BE20: A DEFINIR | BG20: 1137583 | BH20: -11.859144622782148, -41.75367598550662 | BI20: 7 | BJ20: PADRÃO ANTIGO | BK20: =Y20+AD20+AI20+AV20 -> 78 | BL20: =V20+W20+AA20+AB20+AF20+AG20+AK20+AL20+AO20+AP20+AS20+AT20 -> 149 | BM20: =IFERROR(__xludf.DUMMYFUNCTION("IFERROR(VLOOKUP(BG20,IMPORTRANGE(""https://docs.google.com/spreadsheets/d/1juPI-Fb8LD0YtltB2mlGEnp_R3UVu1t3wSFPzgCyHXE/edit?gid=0#gid=0"",""GERAL!A2:C""),3,0),""-"")"),"CAMPO") -> CAMPO
A21: NTE 01 - IRECÊ | B21: CANARANA | C21: ANEXO | D21: 1179281 | E21: 1179207 | F21: 29459141 | G21: ANEXO - CEMIT - IRECÊ - POVOADO UMBURANA DO QUERE | H21: UMBURANA DO QUERE - SN(00006) | I21: POVOADO UMBURANA DO QUERE | J21: 35KM | K21: CEDIDO | L21: PEQUENO | M21: =IFERROR(__xludf.DUMMYFUNCTION("IFERROR(VLOOKUP(D21, IMPORTRANGE(""https://docs.google.com/spreadsheets/d/1MjHtlUikwobi2MaWJgy7tfLeBmhj1u-dRFRs_8GwSoA/edit#gid=0"",""Gestores Escolares!D7:J""),3,0),""VERIFICAR CÓD SEC"")"),"MARCOS PAULO DA SILVA ALMEIDA") -> MARCOS PAULO DA SILVA ALMEIDA | N21: =IFERROR(__xludf.DUMMYFUNCTION("IFERROR(VLOOKUP(D21, IMPORTRANGE(""https://docs.google.com/spreadsheets/d/1MjHtlUikwobi2MaWJgy7tfLeBmhj1u-dRFRs_8GwSoA/edit#gid=0"",""Gestores Escolares!D7:J""),4,0),""VERIFICAR CÓD SEC"")"),"(74) 9 9998-8112") -> (74) 9 9998-8112 | O21: =IFERROR(__xludf.DUMMYFUNCTION("IFERROR(VLOOKUP(D21, IMPORTRANGE(""https://docs.google.com/spreadsheets/d/1MjHtlUikwobi2MaWJgy7tfLeBmhj1u-dRFRs_8GwSoA/edit#gid=0"",""Gestores Escolares!D7:J""),6,0),""VERIFICAR CÓD SEC"")"),"FERNANDA MIRANDA CAMPOS") -> FERNANDA MIRANDA CAMPOS | P21: =IFERROR(__xludf.DUMMYFUNCTION("IFERROR(VLOOKUP(D21, IMPORTRANGE(""https://docs.google.com/spreadsheets/d/1MjHtlUikwobi2MaWJgy7tfLeBmhj1u-dRFRs_8GwSoA/edit#gid=0"",""Gestores Escolares!D7:J""),7,0),""VERIFICAR CÓD SEC"")"),"(74) 9 9963-4717") -> (74) 9 9963-4717 | Q21: =IFERROR(__xludf.DUMMYFUNCTION("IFERROR(VLOOKUP(D21, IMPORTRANGE(""https://docs.google.com/spreadsheets/d/1MjHtlUikwobi2MaWJgy7tfLeBmhj1u-dRFRs_8GwSoA/edit#gid=0"",""Gestores Escolares!D7:m""),9,0),""VERIFICAR CÓD SEC"")"),"") | R21: =IFERROR(__xludf.DUMMYFUNCTION("IFERROR(VLOOKUP(D21, IMPORTRANGE(""https://docs.google.com/spreadsheets/d/1MjHtlUikwobi2MaWJgy7tfLeBmhj1u-dRFRs_8GwSoA/edit#gid=0"",""Gestores Escolares!D7:m""),10,0),""VERIFICAR CÓD SEC"")"),"") | T21: 3 | U21: 3 | V21: 0 | W21: 0 | X21: 0 | Y21: 0 | Z21: =SUM(V21:Y21) -> 0 | AA21: 0 | AB21: 0 | AC21: 0 | AD21: 0 | AE21: =SUM(AA21:AD21) -> 0 | AF21: 0 | AG21: 0 | AH21: 64 | AI21: 0 | AJ21: =SUM(AF21:AI21) -> 64 | AK21: 0 | AL21: 0 | AM21: 0 | AN21: =SUM(AK21:AM21) -> 0 | AO21: 0 | AP21: 0 | AQ21: 0 | AR21: =SUM(AO21:AQ21) -> 0 | AS21: 0 | AT21: 0 | AU21: 0 | AV21: 0 | AW21: =SUM(AS21:AV21) -> 0 | AX21: =SUM(AY21:AZ21) -> 64 | AY21: =SUM(AV21,AT21,AS21,AP21,AO21,AL21,AK21,AI21,AG21,AF21,AD21,AB21,AA21,Y21,W21,V21) -> 0 | AZ21: =SUM(AU21,AQ21,AM21,AH21,AC21,X21) -> 64 | BA21: 0 | BB21: =SUM(AX21+BA21) -> 64 | BC21: A DEFINIR | BD21: CEMIT | BE21: PROFISSIONAL | BG21: 1179207 | BI21: 3 | BJ21: PADRÃO ANTIGO | BK21: =Y21+AD21+AI21+AV21 -> 0 | BL21: =V21+W21+AA21+AB21+AF21+AG21+AK21+AL21+AO21+AP21+AS21+AT21 -> 0 | BM21: =IFERROR(__xludf.DUMMYFUNCTION("IFERROR(VLOOKUP(BG21,IMPORTRANGE(""https://docs.google.com/spreadsheets/d/1juPI-Fb8LD0YtltB2mlGEnp_R3UVu1t3wSFPzgCyHXE/edit?gid=0#gid=0"",""GERAL!A2:C""),3,0),""-"")"),"-") -> -
A22: NTE 01 - IRECÊ | B22: CANARANA | C22: ANEXO | D22: 1179281 | E22: 1179160 | F22: 29459141 | G22: ANEXO - CEMIT - IRECÊ - DISTRITO LAGOA VELHA | H22: LAGOA VELHA - SN(00012) | I22: DISTRITO LAGOA VELHA | J22: 30KM | K22: CEDIDO | L22: PEQUENO | M22: =IFERROR(__xludf.DUMMYFUNCTION("IFERROR(VLOOKUP(D22, IMPORTRANGE(""https://docs.google.com/spreadsheets/d/1MjHtlUikwobi2MaWJgy7tfLeBmhj1u-dRFRs_8GwSoA/edit#gid=0"",""Gestores Escolares!D7:J""),3,0),""VERIFICAR CÓD SEC"")"),"MARCOS PAULO DA SILVA ALMEIDA") -> MARCOS PAULO DA SILVA ALMEIDA | N22: =IFERROR(__xludf.DUMMYFUNCTION("IFERROR(VLOOKUP(D22, IMPORTRANGE(""https://docs.google.com/spreadsheets/d/1MjHtlUikwobi2MaWJgy7tfLeBmhj1u-dRFRs_8GwSoA/edit#gid=0"",""Gestores Escolares!D7:J""),4,0),""VERIFICAR CÓD SEC"")"),"(74) 9 9998-8112") -> (74) 9 9998-8112 | O22: =IFERROR(__xludf.DUMMYFUNCTION("IFERROR(VLOOKUP(D22, IMPORTRANGE(""https://docs.google.com/spreadsheets/d/1MjHtlUikwobi2MaWJgy7tfLeBmhj1u-dRFRs_8GwSoA/edit#gid=0"",""Gestores Escolares!D7:J""),6,0),""VERIFICAR CÓD SEC"")"),"FERNANDA MIRANDA CAMPOS") -> FERNANDA MIRANDA CAMPOS | P22: =IFERROR(__xludf.DUMMYFUNCTION("IFERROR(VLOOKUP(D22, IMPORTRANGE(""https://docs.google.com/spreadsheets/d/1MjHtlUikwobi2MaWJgy7tfLeBmhj1u-dRFRs_8GwSoA/edit#gid=0"",""Gestores Escolares!D7:J""),7,0),""VERIFICAR CÓD SEC"")"),"(74) 9 9963-4717") -> (74) 9 9963-4717 | Q22: =IFERROR(__xludf.DUMMYFUNCTION("IFERROR(VLOOKUP(D22, IMPORTRANGE(""https://docs.google.com/spreadsheets/d/1MjHtlUikwobi2MaWJgy7tfLeBmhj1u-dRFRs_8GwSoA/edit#gid=0"",""Gestores Escolares!D7:m""),9,0),""VERIFICAR CÓD SEC"")"),"") | R22: =IFERROR(__xludf.DUMMYFUNCTION("IFERROR(VLOOKUP(D22, IMPORTRANGE(""https://docs.google.com/spreadsheets/d/1MjHtlUikwobi2MaWJgy7tfLeBmhj1u-dRFRs_8GwSoA/edit#gid=0"",""Gestores Escolares!D7:m""),10,0),""VERIFICAR CÓD SEC"")"),"") | T22: 3 | U22: 3 | V22: 0 | W22: 0 | X22: 0 | Y22: 0 | Z22: =SUM(V22:Y22) -> 0 | AA22: 0 | AB22: 0 | AC22: 0 | AD22: 0 | AE22: =SUM(AA22:AD22) -> 0 | AF22: 0 | AG22: 0 | AH22: 75 | AI22: 0 | AJ22: =SUM(AF22:AI22) -> 75 | AK22: 0 | AL22: 0 | AM22: 0 | AN22: =SUM(AK22:AM22) -> 0 | AO22: 0 | AP22: 0 | AQ22: 0 | AR22: =SUM(AO22:AQ22) -> 0 | AS22: 0 | AT22: 0 | AU22: 0 | AV22: 0 | AW22: =SUM(AS22:AV22) -> 0 | AX22: =SUM(AY22:AZ22) -> 75 | AY22: =SUM(AV22,AT22,AS22,AP22,AO22,AL22,AK22,AI22,AG22,AF22,AD22,AB22,AA22,Y22,W22,V22) -> 0 | AZ22: =SUM(AU22,AQ22,AM22,AH22,AC22,X22) -> 75 | BA22: 0 | BB22: =SUM(AX22+BA22) -> 75 | BC22: A DEFINIR | BD22: CEMIT | BE22: PROFISSIONAL | BG22: 1179160 | BI22: 3 | BJ22: PADRÃO ANTIGO | BK22: =Y22+AD22+AI22+AV22 -> 0 | BL22: =V22+W22+AA22+AB22+AF22+AG22+AK22+AL22+AO22+AP22+AS22+AT22 -> 0 | BM22: =IFERROR(__xludf.DUMMYFUNCTION("IFERROR(VLOOKUP(BG22,IMPORTRANGE(""https://docs.google.com/spreadsheets/d/1juPI-Fb8LD0YtltB2mlGEnp_R3UVu1t3wSFPzgCyHXE/edit?gid=0#gid=0"",""GERAL!A2:C""),3,0),""-"")"),"-") -> -
A23: NTE 01 - IRECÊ | B23: CENTRAL | C23: ESCOLA | D23: 1163088 | F23: 29061016 | G23: COLÉGIO ESTADUAL DE TEMPO INTEGRAL JOSE DE SOUZA MACHADO | H23: AV. ANTÔNIO CARLOS MAGALHÃES, 42 - CENTRO, CENTRAL - BA, 44940-000 | I23: CENTRO | J23: SEDE | K23: PRÓPRIO | L23: ESPECIAL | M23: =IFERROR(__xludf.DUMMYFUNCTION("IFERROR(VLOOKUP(D23, IMPORTRANGE(""https://docs.google.com/spreadsheets/d/1MjHtlUikwobi2MaWJgy7tfLeBmhj1u-dRFRs_8GwSoA/edit#gid=0"",""Gestores Escolares!D7:J""),3,0),""VERIFICAR CÓD SEC"")"),"TEREZA CRISTINA PORTO DE CARVALHO") -> TEREZA CRISTINA PORTO DE CARVALHO | N23: =IFERROR(__xludf.DUMMYFUNCTION("IFERROR(VLOOKUP(D23, IMPORTRANGE(""https://docs.google.com/spreadsheets/d/1MjHtlUikwobi2MaWJgy7tfLeBmhj1u-dRFRs_8GwSoA/edit#gid=0"",""Gestores Escolares!D7:J""),4,0),""VERIFICAR CÓD SEC"")"),"(77) 9 9940-7430/ 9 9813-4060") -> (77) 9 9940-7430/ 9 9813-4060 | O23: =IFERROR(__xludf.DUMMYFUNCTION("IFERROR(VLOOKUP(D23, IMPORTRANGE(""https://docs.google.com/spreadsheets/d/1MjHtlUikwobi2MaWJgy7tfLeBmhj1u-dRFRs_8GwSoA/edit#gid=0"",""Gestores Escolares!D7:J""),6,0),""VERIFICAR CÓD SEC"")"),"MARCIO SARMENTO AMARAL") -> MARCIO SARMENTO AMARAL | P23: =IFERROR(__xludf.DUMMYFUNCTION("IFERROR(VLOOKUP(D23, IMPORTRANGE(""https://docs.google.com/spreadsheets/d/1MjHtlUikwobi2MaWJgy7tfLeBmhj1u-dRFRs_8GwSoA/edit#gid=0"",""Gestores Escolares!D7:J""),7,0),""VERIFICAR CÓD SEC"")"),"(74) 9 9991-3155") -> (74) 9 9991-3155 | Q23: =IFERROR(__xludf.DUMMYFUNCTION("IFERROR(VLOOKUP(D23, IMPORTRANGE(""https://docs.google.com/spreadsheets/d/1MjHtlUikwobi2MaWJgy7tfLeBmhj1u-dRFRs_8GwSoA/edit#gid=0"",""Gestores Escolares!D7:m""),9,0),""VERIFICAR CÓD SEC"")")," REBECA CARVALHO DOS SANTOS") -> REBECA CARVALHO DOS SANTOS | R23: =IFERROR(__xludf.DUMMYFUNCTION("IFERROR(VLOOKUP(D23, IMPORTRANGE(""https://docs.google.com/spreadsheets/d/1MjHtlUikwobi2MaWJgy7tfLeBmhj1u-dRFRs_8GwSoA/edit#gid=0"",""Gestores Escolares!D7:m""),10,0),""VERIFICAR CÓD SEC"")"),"(74) 9 9943-0353") -> (74) 9 9943-0353 | T23: 10 | U23: 12 | V23: 0 | W23: 0 | X23: 0 | Y23: 0 | Z23: =SUM(V23:Y23) -> 0 | AA23: 0 | AB23: 0 | AC23: 0 | AD23: 0 | AE23: =SUM(AA23:AD23) -> 0 | AF23: 0 | AG23: 0 | AH23: 0 | AI23: 393 | AJ23: =SUM(AF23:AI23) -> 393 | AK23: 0 | AL23: 0 | AM23: 0 | AN23: =SUM(AK23:AM23) -> 0 | AO23: 0 | AP23: 0 | AQ23: 82 | AR23: =SUM(AO23:AQ23) -> 82 | AS23: 0 | AT23: 0 | AU23: 0 | AV23: 79 | AW23: =SUM(AS23:AV23) -> 79 | AX23: =SUM(AY23:AZ23) -> 554 | AY23: =SUM(AV23,AT23,AS23,AP23,AO23,AL23,AK23,AI23,AG23,AF23,AD23,AB23,AA23,Y23,W23,V23) -> 472 | AZ23: =SUM(AU23,AQ23,AM23,AH23,AC23,X23) -> 82 | BA23: 0 | BB23: =SUM(AX23+BA23) -> 554 | BC23: A DEFINIR | BD23: A DEFINIR | BE23: A DEFINIR | BG23: 1163088 | BH23: -11.131275357459675, -42.10954975054417 | BI23: 12 | BJ23: NOVO PADRÃO (NOVA ESCOLA) | BK23: =Y23+AD23+AI23+AV23 -> 472 | BL23: =V23+W23+AA23+AB23+AF23+AG23+AK23+AL23+AO23+AP23+AS23+AT23 -> 0 | BM23: =IFERROR(__xludf.DUMMYFUNCTION("IFERROR(VLOOKUP(BG23,IMPORTRANGE(""https://docs.google.com/spreadsheets/d/1juPI-Fb8LD0YtltB2mlGEnp_R3UVu1t3wSFPzgCyHXE/edit?gid=0#gid=0"",""GERAL!A2:C""),3,0),""-"")"),"-") -> -
A24: NTE 01 - IRECÊ | B24: GENTIO DO OURO | C24: ESCOLA | D24: 1125887 | F24: 29061628 | G24: COLÉGIO ESTADUAL MARIA QUITÉRIA - TEMPO INTEGRAL | H24: PÇA EDMUNDO PEREIRA BASTOS - 212 | I24: CENTRO | J24: SEDE | K24: PRÓPRIO | L24: GRANDE | M24: =IFERROR(__xludf.DUMMYFUNCTION("IFERROR(VLOOKUP(D24, IMPORTRANGE(""https://docs.google.com/spreadsheets/d/1MjHtlUikwobi2MaWJgy7tfLeBmhj1u-dRFRs_8GwSoA/edit#gid=0"",""Gestores Escolares!D7:J""),3,0),""VERIFICAR CÓD SEC"")"),"UMBERTO GOMES LEITE") -> UMBERTO GOMES LEITE | N24: =IFERROR(__xludf.DUMMYFUNCTION("IFERROR(VLOOKUP(D24, IMPORTRANGE(""https://docs.google.com/spreadsheets/d/1MjHtlUikwobi2MaWJgy7tfLeBmhj1u-dRFRs_8GwSoA/edit#gid=0"",""Gestores Escolares!D7:J""),4,0),""VERIFICAR CÓD SEC"")"),"(74) 9 8136-9548") -> (74) 9 8136-9548 | O24: =IFERROR(__xludf.DUMMYFUNCTION("IFERROR(VLOOKUP(D24, IMPORTRANGE(""https://docs.google.com/spreadsheets/d/1MjHtlUikwobi2MaWJgy7tfLeBmhj1u-dRFRs_8GwSoA/edit#gid=0"",""Gestores Escolares!D7:J""),6,0),""VERIFICAR CÓD SEC"")"),"ALESSANDRA DE SENA SILVA") -> ALESSANDRA DE SENA SILVA | P24: =IFERROR(__xludf.DUMMYFUNCTION("IFERROR(VLOOKUP(D24, IMPORTRANGE(""https://docs.google.com/spreadsheets/d/1MjHtlUikwobi2MaWJgy7tfLeBmhj1u-dRFRs_8GwSoA/edit#gid=0"",""Gestores Escolares!D7:J""),7,0),""VERIFICAR CÓD SEC"")"),"") | Q24: =IFERROR(__xludf.DUMMYFUNCTION("IFERROR(VLOOKUP(D24, IMPORTRANGE(""https://docs.google.com/spreadsheets/d/1MjHtlUikwobi2MaWJgy7tfLeBmhj1u-dRFRs_8GwSoA/edit#gid=0"",""Gestores Escolares!D7:m""),9,0),""VERIFICAR CÓD SEC"")"),"EDMILSON SOARES BARBOSA (COORDENADOR PEDAGÓGICO)") -> EDMILSON SOARES BARBOSA (COORDENADOR PEDAGÓGICO) | R24: =IFERROR(__xludf.DUMMYFUNCTION("IFERROR(VLOOKUP(D24, IMPORTRANGE(""https://docs.google.com/spreadsheets/d/1MjHtlUikwobi2MaWJgy7tfLeBmhj1u-dRFRs_8GwSoA/edit#gid=0"",""Gestores Escolares!D7:m""),10,0),""VERIFICAR CÓD SEC"")"),"(77) 9 9958-2972") -> (77) 9 9958-2972 | T24: 9 | U24: 7 | V24: 0 | W24: 0 | X24: 0 | Y24: 0 | Z24: =SUM(V24:Y24) -> 0 | AA24: 0 | AB24: 0 | AC24: 0 | AD24: 0 | AE24: =SUM(AA24:AD24) -> 0 | AF24: 0 | AG24: 0 | AH24: 0 | AI24: 141 | AJ24: =SUM(AF24:AI24) -> 141 | AK24: 0 | AL24: 0 | AM24: 0 | AN24: =SUM(AK24:AM24) -> 0 | AO24: 0 | AP24: 0 | AQ24: 19 | AR24: =SUM(AO24:AQ24) -> 19 | AS24: 0 | AT24: 0 | AU24: 14 | AV24: 99 | AW24: =SUM(AS24:AV24) -> 113 | AX24: =SUM(AY24:AZ24) -> 273 | AY24: =SUM(AV24,AT24,AS24,AP24,AO24,AL24,AK24,AI24,AG24,AF24,AD24,AB24,AA24,Y24,W24,V24) -> 240 | AZ24: =SUM(AU24,AQ24,AM24,AH24,AC24,X24) -> 33 | BA24: 0 | BB24: =SUM(AX24+BA24) -> 273 | BC24: A DEFINIR | BD24: A DEFINIR | BE24: A DEFINIR | BG24: 1125887 | BH24: -11.428866151079575, -42.50793797779119 | BI24: 7 | BJ24: PADRÃO ANTIGO | BK24: =Y24+AD24+AI24+AV24 -> 240 | BL24: =V24+W24+AA24+AB24+AF24+AG24+AK24+AL24+AO24+AP24+AS24+AT24 -> 0 | BM24: =IFERROR(__xludf.DUMMYFUNCTION("IFERROR(VLOOKUP(BG24,IMPORTRANGE(""https://docs.google.com/spreadsheets/d/1juPI-Fb8LD0YtltB2mlGEnp_R3UVu1t3wSFPzgCyHXE/edit?gid=0#gid=0"",""GERAL!A2:C""),3,0),""-"")"),"-") -> -
A25: NTE 01 - IRECÊ | B25: GENTIO DO OURO | C25: ANEXO | D25: 1125887 | E25: 1179258 | F25: 29492742 | G25: ANEXO - COLÉGIO ESTADUAL MARIA QUITÉRIA - DISTRITO DE ITAJUBAQUARA | H25: RUA EDMUNDO PEREIRA BASTOS - 212 | I25: CENTRO | J25: 18KM | K25: CEDIDO | L25: PEQUENO | M25: =IFERROR(__xludf.DUMMYFUNCTION("IFERROR(VLOOKUP(D25, IMPORTRANGE(""https://docs.google.com/spreadsheets/d/1MjHtlUikwobi2MaWJgy7tfLeBmhj1u-dRFRs_8GwSoA/edit#gid=0"",""Gestores Escolares!D7:J""),3,0),""VERIFICAR CÓD SEC"")"),"UMBERTO GOMES LEITE") -> UMBERTO GOMES LEITE | N25: =IFERROR(__xludf.DUMMYFUNCTION("IFERROR(VLOOKUP(D25, IMPORTRANGE(""https://docs.google.com/spreadsheets/d/1MjHtlUikwobi2MaWJgy7tfLeBmhj1u-dRFRs_8GwSoA/edit#gid=0"",""Gestores Escolares!D7:J""),4,0),""VERIFICAR CÓD SEC"")"),"(74) 9 8136-9548") -> (74) 9 8136-9548 | O25: =IFERROR(__xludf.DUMMYFUNCTION("IFERROR(VLOOKUP(D25, IMPORTRANGE(""https://docs.google.com/spreadsheets/d/1MjHtlUikwobi2MaWJgy7tfLeBmhj1u-dRFRs_8GwSoA/edit#gid=0"",""Gestores Escolares!D7:J""),6,0),""VERIFICAR CÓD SEC"")"),"ALESSANDRA DE SENA SILVA") -> ALESSANDRA DE SENA SILVA | P25: =IFERROR(__xludf.DUMMYFUNCTION("IFERROR(VLOOKUP(D25, IMPORTRANGE(""https://docs.google.com/spreadsheets/d/1MjHtlUikwobi2MaWJgy7tfLeBmhj1u-dRFRs_8GwSoA/edit#gid=0"",""Gestores Escolares!D7:J""),7,0),""VERIFICAR CÓD SEC"")"),"") | Q25: =IFERROR(__xludf.DUMMYFUNCTION("IFERROR(VLOOKUP(D25, IMPORTRANGE(""https://docs.google.com/spreadsheets/d/1MjHtlUikwobi2MaWJgy7tfLeBmhj1u-dRFRs_8GwSoA/edit#gid=0"",""Gestores Escolares!D7:m""),9,0),""VERIFICAR CÓD SEC"")"),"EDMILSON SOARES BARBOSA (COORDENADOR PEDAGÓGICO)") -> EDMILSON SOARES BARBOSA (COORDENADOR PEDAGÓGICO) | R25: =IFERROR(__xludf.DUMMYFUNCTION("IFERROR(VLOOKUP(D25, IMPORTRANGE(""https://docs.google.com/spreadsheets/d/1MjHtlUikwobi2MaWJgy7tfLeBmhj1u-dRFRs_8GwSoA/edit#gid=0"",""Gestores Escolares!D7:m""),10,0),""VERIFICAR CÓD SEC"")"),"(77) 9 9958-2972") -> (77) 9 9958-2972 | T25: 4 | U25: 2 | V25: 0 | W25: 0 | X25: 0 | Y25: 0 | Z25: =SUM(V25:Y25) -> 0 | AA25: 0 | AB25: 0 | AC25: 0 | AD25: 0 | AE25: =SUM(AA25:AD25) -> 0 | AF25: 0 | AG25: 0 | AH25: 0 | AI25: 0 | AJ25: =SUM(AF25:AI25) -> 0 | AK25: 0 | AL25: 0 | AM25: 0 | AN25: =SUM(AK25:AM25) -> 0 | AO25: 0 | AP25: 0 | AQ25: 47 | AR25: =SUM(AO25:AQ25) -> 47 | AS25: 0 | AT25: 0 | AU25: 0 | AV25: 0 | AW25: =SUM(AS25:AV25) -> 0 | AX25: =SUM(AY25:AZ25) -> 47 | AY25: =SUM(AV25,AT25,AS25,AP25,AO25,AL25,AK25,AI25,AG25,AF25,AD25,AB25,AA25,Y25,W25,V25) -> 0 | AZ25: =SUM(AU25,AQ25,AM25,AH25,AC25,X25) -> 47 | BA25: 0 | BB25: =SUM(AX25+BA25) -> 47 | BC25: DO CAMPO | BD25: A DEFINIR | BE25: A DEFINIR | BG25: 1179258 | BI25: 4 | BJ25: PADRÃO ANTIGO | BK25: =Y25+AD25+AI25+AV25 -> 0 | BL25: =V25+W25+AA25+AB25+AF25+AG25+AK25+AL25+AO25+AP25+AS25+AT25 -> 0 | BM25: =IFERROR(__xludf.DUMMYFUNCTION("IFERROR(VLOOKUP(BG25,IMPORTRANGE(""https://docs.google.com/spreadsheets/d/1juPI-Fb8LD0YtltB2mlGEnp_R3UVu1t3wSFPzgCyHXE/edit?gid=0#gid=0"",""GERAL!A2:C""),3,0),""-"")"),"CAMPO") -> CAMPO
A26: NTE 01 - IRECÊ | B26: GENTIO DO OURO | C26: ANEXO | D26: 1179281 | E26: 1178795 | F26: 29459141 | G26: ANEXO - CEMIT - IRECÊ- DISTRITO DE IBITUNANE | H26: DISTRITO DE IBITUNANE - S/N | I26: CENTRO | J26: 45KM | K26: CEDIDO | L26: PEQUENO | M26: =IFERROR(__xludf.DUMMYFUNCTION("IFERROR(VLOOKUP(D26, IMPORTRANGE(""https://docs.google.com/spreadsheets/d/1MjHtlUikwobi2MaWJgy7tfLeBmhj1u-dRFRs_8GwSoA/edit#gid=0"",""Gestores Escolares!D7:J""),3,0),""VERIFICAR CÓD SEC"")"),"MARCOS PAULO DA SILVA ALMEIDA") -> MARCOS PAULO DA SILVA ALMEIDA | N26: =IFERROR(__xludf.DUMMYFUNCTION("IFERROR(VLOOKUP(D26, IMPORTRANGE(""https://docs.google.com/spreadsheets/d/1MjHtlUikwobi2MaWJgy7tfLeBmhj1u-dRFRs_8GwSoA/edit#gid=0"",""Gestores Escolares!D7:J""),4,0),""VERIFICAR CÓD SEC"")"),"(74) 9 9998-8112") -> (74) 9 9998-8112 | O26: =IFERROR(__xludf.DUMMYFUNCTION("IFERROR(VLOOKUP(D26, IMPORTRANGE(""https://docs.google.com/spreadsheets/d/1MjHtlUikwobi2MaWJgy7tfLeBmhj1u-dRFRs_8GwSoA/edit#gid=0"",""Gestores Escolares!D7:J""),6,0),""VERIFICAR CÓD SEC"")"),"FERNANDA MIRANDA CAMPOS") -> FERNANDA MIRANDA CAMPOS | P26: =IFERROR(__xludf.DUMMYFUNCTION("IFERROR(VLOOKUP(D26, IMPORTRANGE(""https://docs.google.com/spreadsheets/d/1MjHtlUikwobi2MaWJgy7tfLeBmhj1u-dRFRs_8GwSoA/edit#gid=0"",""Gestores Escolares!D7:J""),7,0),""VERIFICAR CÓD SEC"")"),"(74) 9 9963-4717") -> (74) 9 9963-4717 | Q26: =IFERROR(__xludf.DUMMYFUNCTION("IFERROR(VLOOKUP(D26, IMPORTRANGE(""https://docs.google.com/spreadsheets/d/1MjHtlUikwobi2MaWJgy7tfLeBmhj1u-dRFRs_8GwSoA/edit#gid=0"",""Gestores Escolares!D7:m""),9,0),""VERIFICAR CÓD SEC"")"),"") | R26: =IFERROR(__xludf.DUMMYFUNCTION("IFERROR(VLOOKUP(D26, IMPORTRANGE(""https://docs.google.com/spreadsheets/d/1MjHtlUikwobi2MaWJgy7tfLeBmhj1u-dRFRs_8GwSoA/edit#gid=0"",""Gestores Escolares!D7:m""),10,0),""VERIFICAR CÓD SEC"")"),"") | T26: 3 | U26: 3 | V26: 0 | W26: 0 | X26: 0 | Y26: 0 | Z26: =SUM(V26:Y26) -> 0 | AA26: 0 | AB26: 0 | AC26: 0 | AD26: 0 | AE26: =SUM(AA26:AD26) -> 0 | AF26: 0 | AG26: 0 | AH26: 80 | AI26: 0 | AJ26: =SUM(AF26:AI26) -> 80 | AK26: 0 | AL26: 0 | AM26: 0 | AN26: =SUM(AK26:AM26) -> 0 | AO26: 0 | AP26: 0 | AQ26: 0 | AR26: =SUM(AO26:AQ26) -> 0 | AS26: 0 | AT26: 0 | AU26: 0 | AV26: 0 | AW26: =SUM(AS26:AV26) -> 0 | AX26: =SUM(AY26:AZ26) -> 80 | AY26: =SUM(AV26,AT26,AS26,AP26,AO26,AL26,AK26,AI26,AG26,AF26,AD26,AB26,AA26,Y26,W26,V26) -> 0 | AZ26: =SUM(AU26,AQ26,AM26,AH26,AC26,X26) -> 80 | BA26: 0 | BB26: =SUM(AX26+BA26) -> 80 | BC26: A DEFINIR | BD26: CEMIT | BE26: PROFISSIONAL | BG26: 1178795 | BI26: 3 | BJ26: PADRÃO ANTIGO | BK26: =Y26+AD26+AI26+AV26 -> 0 | BL26: =V26+W26+AA26+AB26+AF26+AG26+AK26+AL26+AO26+AP26+AS26+AT26 -> 0 | BM26: =IFERROR(__xludf.DUMMYFUNCTION("IFERROR(VLOOKUP(BG26,IMPORTRANGE(""https://docs.google.com/spreadsheets/d/1juPI-Fb8LD0YtltB2mlGEnp_R3UVu1t3wSFPzgCyHXE/edit?gid=0#gid=0"",""GERAL!A2:C""),3,0),""-"")"),"-") -> -
A27: NTE 01 - IRECÊ | B27: GENTIO DO OURO | C27: ANEXO | D27: 1179281 | E27: 1178794 | F27: 29459141 | G27: ANEXO - CEMIT - IRECÊ - DISTRITO DE PITUBA | H27: DIST. DE PITUBA - S/N | I27: CENTRO | J27: 59KM | K27: CEDIDO | L27: PEQUENO | M27: =IFERROR(__xludf.DUMMYFUNCTION("IFERROR(VLOOKUP(D27, IMPORTRANGE(""https://docs.google.com/spreadsheets/d/1MjHtlUikwobi2MaWJgy7tfLeBmhj1u-dRFRs_8GwSoA/edit#gid=0"",""Gestores Escolares!D7:J""),3,0),""VERIFICAR CÓD SEC"")"),"MARCOS PAULO DA SILVA ALMEIDA") -> MARCOS PAULO DA SILVA ALMEIDA | N27: =IFERROR(__xludf.DUMMYFUNCTION("IFERROR(VLOOKUP(D27, IMPORTRANGE(""https://docs.google.com/spreadsheets/d/1MjHtlUikwobi2MaWJgy7tfLeBmhj1u-dRFRs_8GwSoA/edit#gid=0"",""Gestores Escolares!D7:J""),4,0),""VERIFICAR CÓD SEC"")"),"(74) 9 9998-8112") -> (74) 9 9998-8112 | O27: =IFERROR(__xludf.DUMMYFUNCTION("IFERROR(VLOOKUP(D27, IMPORTRANGE(""https://docs.google.com/spreadsheets/d/1MjHtlUikwobi2MaWJgy7tfLeBmhj1u-dRFRs_8GwSoA/edit#gid=0"",""Gestores Escolares!D7:J""),6,0),""VERIFICAR CÓD SEC"")"),"FERNANDA MIRANDA CAMPOS") -> FERNANDA MIRANDA CAMPOS | P27: =IFERROR(__xludf.DUMMYFUNCTION("IFERROR(VLOOKUP(D27, IMPORTRANGE(""https://docs.google.com/spreadsheets/d/1MjHtlUikwobi2MaWJgy7tfLeBmhj1u-dRFRs_8GwSoA/edit#gid=0"",""Gestores Escolares!D7:J""),7,0),""VERIFICAR CÓD SEC"")"),"(74) 9 9963-4717") -> (74) 9 9963-4717 | Q27: =IFERROR(__xludf.DUMMYFUNCTION("IFERROR(VLOOKUP(D27, IMPORTRANGE(""https://docs.google.com/spreadsheets/d/1MjHtlUikwobi2MaWJgy7tfLeBmhj1u-dRFRs_8GwSoA/edit#gid=0"",""Gestores Escolares!D7:m""),9,0),""VERIFICAR CÓD SEC"")"),"") | R27: =IFERROR(__xludf.DUMMYFUNCTION("IFERROR(VLOOKUP(D27, IMPORTRANGE(""https://docs.google.com/spreadsheets/d/1MjHtlUikwobi2MaWJgy7tfLeBmhj1u-dRFRs_8GwSoA/edit#gid=0"",""Gestores Escolares!D7:m""),10,0),""VERIFICAR CÓD SEC"")"),"") | T27: 3 | U27: 3 | V27: 0 | W27: 0 | X27: 0 | Y27: 0 | Z27: =SUM(V27:Y27) -> 0 | AA27: 0 | AB27: 0 | AC27: 0 | AD27: 0 | AE27: =SUM(AA27:AD27) -> 0 | AF27: 0 | AG27: 0 | AH27: 32 | AI27: 0 | AJ27: =SUM(AF27:AI27) -> 32 | AK27: 0 | AL27: 0 | AM27: 0 | AN27: =SUM(AK27:AM27) -> 0 | AO27: 0 | AP27: 0 | AQ27: 0 | AR27: =SUM(AO27:AQ27) -> 0 | AS27: 0 | AT27: 0 | AU27: 0 | AV27: 0 | AW27: =SUM(AS27:AV27) -> 0 | AX27: =SUM(AY27:AZ27) -> 32 | AY27: =SUM(AV27,AT27,AS27,AP27,AO27,AL27,AK27,AI27,AG27,AF27,AD27,AB27,AA27,Y27,W27,V27) -> 0 | AZ27: =SUM(AU27,AQ27,AM27,AH27,AC27,X27) -> 32 | BA27: 0 | BB27: =SUM(AX27+BA27) -> 32 | BC27: A DEFINIR | BD27: CEMIT | BE27: PROFISSIONAL | BG27: 1178794 | BI27: 3 | BJ27: PADRÃO ANTIGO | BK27: =Y27+AD27+AI27+AV27 -> 0 | BL27: =V27+W27+AA27+AB27+AF27+AG27+AK27+AL27+AO27+AP27+AS27+AT27 -> 0 | BM27: =IFERROR(__xludf.DUMMYFUNCTION("IFERROR(VLOOKUP(BG27,IMPORTRANGE(""https://docs.google.com/spreadsheets/d/1juPI-Fb8LD0YtltB2mlGEnp_R3UVu1t3wSFPzgCyHXE/edit?gid=0#gid=0"",""GERAL!A2:C""),3,0),""-"")"),"-") -> -
A28: NTE 01 - IRECÊ | B28: IBIPEBA | C28: ESCOLA | D28: 1126050 | F28: 29062519 | G28: COLÉGIO ESTADUAL DO CAMPO DE TEMPO INTEGRAL DE MIROROS | H28: RUA DA IGREJA - SN(00147) | I28: POVOADO DE MIRORÓS | J28: 50KM | K28: PRÓPRIO | L28: GRANDE | M28: =IFERROR(__xludf.DUMMYFUNCTION("IFERROR(VLOOKUP(D28, IMPORTRANGE(""https://docs.google.com/spreadsheets/d/1MjHtlUikwobi2MaWJgy7tfLeBmhj1u-dRFRs_8GwSoA/edit#gid=0"",""Gestores Escolares!D7:J""),3,0),""VERIFICAR CÓD SEC"")"),"SIDON FELIPE SILVA DA CRUZ") -> SIDON FELIPE SILVA DA CRUZ | N28: =IFERROR(__xludf.DUMMYFUNCTION("IFERROR(VLOOKUP(D28, IMPORTRANGE(""https://docs.google.com/spreadsheets/d/1MjHtlUikwobi2MaWJgy7tfLeBmhj1u-dRFRs_8GwSoA/edit#gid=0"",""Gestores Escolares!D7:J""),4,0),""VERIFICAR CÓD SEC"")"),"(74) 9 9929-8067") -> (74) 9 9929-8067 | O28: =IFERROR(__xludf.DUMMYFUNCTION("IFERROR(VLOOKUP(D28, IMPORTRANGE(""https://docs.google.com/spreadsheets/d/1MjHtlUikwobi2MaWJgy7tfLeBmhj1u-dRFRs_8GwSoA/edit#gid=0"",""Gestores Escolares!D7:J""),6,0),""VERIFICAR CÓD SEC"")"),"HIANDRA MUNIQUE DE SOUZA COSTA") -> HIANDRA MUNIQUE DE SOUZA COSTA | P28: =IFERROR(__xludf.DUMMYFUNCTION("IFERROR(VLOOKUP(D28, IMPORTRANGE(""https://docs.google.com/spreadsheets/d/1MjHtlUikwobi2MaWJgy7tfLeBmhj1u-dRFRs_8GwSoA/edit#gid=0"",""Gestores Escolares!D7:J""),7,0),""VERIFICAR CÓD SEC"")")," (74) 9 9910-6082") -> (74) 9 9910-6082 | Q28: =IFERROR(__xludf.DUMMYFUNCTION("IFERROR(VLOOKUP(D28, IMPORTRANGE(""https://docs.google.com/spreadsheets/d/1MjHtlUikwobi2MaWJgy7tfLeBmhj1u-dRFRs_8GwSoA/edit#gid=0"",""Gestores Escolares!D7:m""),9,0),""VERIFICAR CÓD SEC"")"),"") | R28: =IFERROR(__xludf.DUMMYFUNCTION("IFERROR(VLOOKUP(D28, IMPORTRANGE(""https://docs.google.com/spreadsheets/d/1MjHtlUikwobi2MaWJgy7tfLeBmhj1u-dRFRs_8GwSoA/edit#gid=0"",""Gestores Escolares!D7:m""),10,0),""VERIFICAR CÓD SEC"")"),"") | T28: 3 | U28: 6 | V28: 0 | W28: 0 | X28: 0 | Y28: 0 | Z28: =SUM(V28:Y28) -> 0 | AA28: 0 | AB28: 0 | AC28: 0 | AD28: 0 | AE28: =SUM(AA28:AD28) -> 0 | AF28: 0 | AG28: 0 | AH28: 0 | AI28: 161 | AJ28: =SUM(AF28:AI28) -> 161 | AK28: 0 | AL28: 0 | AM28: 0 | AN28: =SUM(AK28:AM28) -> 0 | AO28: 0 | AP28: 0 | AQ28: 31 | AR28: =SUM(AO28:AQ28) -> 31 | AS28: 0 | AT28: 0 | AU28: 0 | AV28: 0 | AW28: =SUM(AS28:AV28) -> 0 | AX28: =SUM(AY28:AZ28) -> 192 | AY28: =SUM(AV28,AT28,AS28,AP28,AO28,AL28,AK28,AI28,AG28,AF28,AD28,AB28,AA28,Y28,W28,V28) -> 161 | AZ28: =SUM(AU28,AQ28,AM28,AH28,AC28,X28) -> 31 | BA28: 0 | BB28: =SUM(AX28+BA28) -> 192 | BC28: DO CAMPO | BD28: A DEFINIR | BE28: A DEFINIR | BG28: 1126050 | BH28: -11.439389308500333, -42.312256697387305 | BI28: 6 | BJ28: NOVO PADRÃO (NOVA ESCOLA) | BK28: =Y28+AD28+AI28+AV28 -> 161 | BL28: =V28+W28+AA28+AB28+AF28+AG28+AK28+AL28+AO28+AP28+AS28+AT28 -> 0 | BM28: =IFERROR(__xludf.DUMMYFUNCTION("IFERROR(VLOOKUP(BG28,IMPORTRANGE(""https://docs.google.com/spreadsheets/d/1juPI-Fb8LD0YtltB2mlGEnp_R3UVu1t3wSFPzgCyHXE/edit?gid=0#gid=0"",""GERAL!A2:C""),3,0),""-"")"),"CAMPO") -> CAMPO
A29: NTE 01 - IRECÊ | B29: IBIPEBA | C29: ESCOLA | D29: 1125968 | F29: 29062250 | G29: COLÉGIO ESTADUAL DE TEMPO INTEGRAL PROFESSORA CÉLIA OLIVEIRA LEITE (ANTIGO CE ACM) | H29: R. ADÉLIA DOURADA 380 - IBIPEBA, BA, 44970-000 | I29: CENTRO | J29: SEDE | K29: PRÓPRIO | L29: ESPECIAL | M29: =IFERROR(__xludf.DUMMYFUNCTION("IFERROR(VLOOKUP(D29, IMPORTRANGE(""https://docs.google.com/spreadsheets/d/1MjHtlUikwobi2MaWJgy7tfLeBmhj1u-dRFRs_8GwSoA/edit#gid=0"",""Gestores Escolares!D7:J""),3,0),""VERIFICAR CÓD SEC"")"),"PAULINY GABRIELA BARRETO") -> PAULINY GABRIELA BARRETO | N29: =IFERROR(__xludf.DUMMYFUNCTION("IFERROR(VLOOKUP(D29, IMPORTRANGE(""https://docs.google.com/spreadsheets/d/1MjHtlUikwobi2MaWJgy7tfLeBmhj1u-dRFRs_8GwSoA/edit#gid=0"",""Gestores Escolares!D7:J""),4,0),""VERIFICAR CÓD SEC"")"),"(74) 9 8135-8606") -> (74) 9 8135-8606 | O29: =IFERROR(__xludf.DUMMYFUNCTION("IFERROR(VLOOKUP(D29, IMPORTRANGE(""https://docs.google.com/spreadsheets/d/1MjHtlUikwobi2MaWJgy7tfLeBmhj1u-dRFRs_8GwSoA/edit#gid=0"",""Gestores Escolares!D7:J""),6,0),""VERIFICAR CÓD SEC"")"),"CASSIO CUNHA DOURADO") -> CASSIO CUNHA DOURADO | P29: =IFERROR(__xludf.DUMMYFUNCTION("IFERROR(VLOOKUP(D29, IMPORTRANGE(""https://docs.google.com/spreadsheets/d/1MjHtlUikwobi2MaWJgy7tfLeBmhj1u-dRFRs_8GwSoA/edit#gid=0"",""Gestores Escolares!D7:J""),7,0),""VERIFICAR CÓD SEC"")"),"(74) 9 9932-6090") -> (74) 9 9932-6090 | Q29: =IFERROR(__xludf.DUMMYFUNCTION("IFERROR(VLOOKUP(D29, IMPORTRANGE(""https://docs.google.com/spreadsheets/d/1MjHtlUikwobi2MaWJgy7tfLeBmhj1u-dRFRs_8GwSoA/edit#gid=0"",""Gestores Escolares!D7:m""),9,0),""VERIFICAR CÓD SEC"")"),"VICTOR DOS ANJOS NUNES DA GAMA") -> VICTOR DOS ANJOS NUNES DA GAMA | R29: =IFERROR(__xludf.DUMMYFUNCTION("IFERROR(VLOOKUP(D29, IMPORTRANGE(""https://docs.google.com/spreadsheets/d/1MjHtlUikwobi2MaWJgy7tfLeBmhj1u-dRFRs_8GwSoA/edit#gid=0"",""Gestores Escolares!D7:m""),10,0),""VERIFICAR CÓD SEC"")"),"(74) 9 8818-9192") -> (74) 9 8818-9192 | T29: 8 | U29: 11 | V29: 0 | W29: 0 | X29: 0 | Y29: 0 | Z29: =SUM(V29:Y29) -> 0 | AA29: 0 | AB29: 0 | AC29: 0 | AD29: 0 | AE29: =SUM(AA29:AD29) -> 0 | AF29: 0 | AG29: 0 | AH29: 0 | AI29: 283 | AJ29: =SUM(AF29:AI29) -> 283 | AK29: 0 | AL29: 0 | AM29: 0 | AN29: =SUM(AK29:AM29) -> 0 | AO29: 0 | AP29: 0 | AQ29: 50 | AR29: =SUM(AO29:AQ29) -> 50 | AS29: 0 | AT29: 0 | AU29: 0 | AV29: 54 | AW29: =SUM(AS29:AV29) -> 54 | AX29: =SUM(AY29:AZ29) -> 387 | AY29: =SUM(AV29,AT29,AS29,AP29,AO29,AL29,AK29,AI29,AG29,AF29,AD29,AB29,AA29,Y29,W29,V29) -> 337 | AZ29: =SUM(AU29,AQ29,AM29,AH29,AC29,X29) -> 50 | BA29: 0 | BB29: =SUM(AX29+BA29) -> 387 | BC29: A DEFINIR | BD29: A DEFINIR | BE29: A DEFINIR | BG29: 1125968 | BH29: -11.645743486851487, -42.0075519870747 | BI29: 6 | BJ29: NOVO PADRÃO (NOVA ESCOLA) | BK29: =Y29+AD29+AI29+AV29 -> 337 | BL29: =V29+W29+AA29+AB29+AF29+AG29+AK29+AL29+AO29+AP29+AS29+AT29 -> 0 | BM29: =IFERROR(__xludf.DUMMYFUNCTION("IFERROR(VLOOKUP(BG29,IMPORTRANGE(""https://docs.google.com/spreadsheets/d/1juPI-Fb8LD0YtltB2mlGEnp_R3UVu1t3wSFPzgCyHXE/edit?gid=0#gid=0"",""GERAL!A2:C""),3,0),""-"")"),"-") -> -
A30: NTE 01 - IRECÊ | B30: IBITITA | C30: ESCOLA | D30: 1162774 | F30: 29062632 | G30: COLÉGIO ESTADUAL DO CAMPO DE TEMPO INTEGRAL DE IBITITÁ | H30: PROFESSORA ELZY OLIVEIRA CARDOSO - SN(00118) | I30: CENTRO | J30: SEDE | K30: PRÓPRIO | L30: GRANDE | M30: =IFERROR(__xludf.DUMMYFUNCTION("IFERROR(VLOOKUP(D30, IMPORTRANGE(""https://docs.google.com/spreadsheets/d/1MjHtlUikwobi2MaWJgy7tfLeBmhj1u-dRFRs_8GwSoA/edit#gid=0"",""Gestores Escolares!D7:J""),3,0),""VERIFICAR CÓD SEC"")"),"ITAMAR FERREIRA DE BRITO") -> ITAMAR FERREIRA DE BRITO | N30: =IFERROR(__xludf.DUMMYFUNCTION("IFERROR(VLOOKUP(D30, IMPORTRANGE(""https://docs.google.com/spreadsheets/d/1MjHtlUikwobi2MaWJgy7tfLeBmhj1u-dRFRs_8GwSoA/edit#gid=0"",""Gestores Escolares!D7:J""),4,0),""VERIFICAR CÓD SEC"")"),"(74) 9 9940-0723") -> (74) 9 9940-0723 | O30: =IFERROR(__xludf.DUMMYFUNCTION("IFERROR(VLOOKUP(D30, IMPORTRANGE(""https://docs.google.com/spreadsheets/d/1MjHtlUikwobi2MaWJgy7tfLeBmhj1u-dRFRs_8GwSoA/edit#gid=0"",""Gestores Escolares!D7:J""),6,0),""VERIFICAR CÓD SEC"")"),"CRISTIANE BARRETO DE ALMEIDA CARDOSO") -> CRISTIANE BARRETO DE ALMEIDA CARDOSO | P30: =IFERROR(__xludf.DUMMYFUNCTION("IFERROR(VLOOKUP(D30, IMPORTRANGE(""https://docs.google.com/spreadsheets/d/1MjHtlUikwobi2MaWJgy7tfLeBmhj1u-dRFRs_8GwSoA/edit#gid=0"",""Gestores Escolares!D7:J""),7,0),""VERIFICAR CÓD SEC"")"),"(74) 9 8121-1706 / 9 9110-5616") -> (74) 9 8121-1706 / 9 9110-5616 | Q30: =IFERROR(__xludf.DUMMYFUNCTION("IFERROR(VLOOKUP(D30, IMPORTRANGE(""https://docs.google.com/spreadsheets/d/1MjHtlUikwobi2MaWJgy7tfLeBmhj1u-dRFRs_8GwSoA/edit#gid=0"",""Gestores Escolares!D7:m""),9,0),""VERIFICAR CÓD SEC"")"),"EDVANIA BEZERRA DE LIMA") -> EDVANIA BEZERRA DE LIMA | R30: =IFERROR(__xludf.DUMMYFUNCTION("IFERROR(VLOOKUP(D30, IMPORTRANGE(""https://docs.google.com/spreadsheets/d/1MjHtlUikwobi2MaWJgy7tfLeBmhj1u-dRFRs_8GwSoA/edit#gid=0"",""Gestores Escolares!D7:m""),10,0),""VERIFICAR CÓD SEC"")"),"(74) 9 9194-4783") -> (74) 9 9194-4783 | T30: 12 | U30: 14 (sendo 11 salas de aula e 01 sala (adapt.) para libras, 01 sala (adapt.) para biblioteca e 01 sala (adapt.) informática) | V30: 0 | W30: 0 | X30: 0 | Y30: 0 | Z30: =SUM(V30:Y30) -> 0 | AA30: 0 | AB30: 0 | AC30: 0 | AD30: 0 | AE30: =SUM(AA30:AD30) -> 0 | AF30: 0 | AG30: 0 | AH30: 0 | AI30: 346 | AJ30: =SUM(AF30:AI30) -> 346 | AK30: 0 | AL30: 0 | AM30: 0 | AN30: =SUM(AK30:AM30) -> 0 | AO30: 0 | AP30: 0 | AQ30: 123 | AR30: =SUM(AO30:AQ30) -> 123 | AS30: 0 | AT30: 0 | AU30: 0 | AV30: 151 | AW30: =SUM(AS30:AV30) -> 151 | AX30: =SUM(AY30:AZ30) -> 620 | AY30: =SUM(AV30,AT30,AS30,AP30,AO30,AL30,AK30,AI30,AG30,AF30,AD30,AB30,AA30,Y30,W30,V30) -> 497 | AZ30: =SUM(AU30,AQ30,AM30,AH30,AC30,X30) -> 123 | BA30: 0 | BB30: =SUM(AX30+BA30) -> 620 | BC30: DO CAMPO | BD30: A DEFINIR | BE30: A DEFINIR | BG30: 1162774 | BH30: -11.54032585532116, -41.97791977474087 | BI30: 11 | BJ30: PADRÃO ANTIGO | BK30: =Y30+AD30+AI30+AV30 -> 497 | BL30: =V30+W30+AA30+AB30+AF30+AG30+AK30+AL30+AO30+AP30+AS30+AT30 -> 0 | BM30: =IFERROR(__xludf.DUMMYFUNCTION("IFERROR(VLOOKUP(BG30,IMPORTRANGE(""https://docs.google.com/spreadsheets/d/1juPI-Fb8LD0YtltB2mlGEnp_R3UVu1t3wSFPzgCyHXE/edit?gid=0#gid=0"",""GERAL!A2:C""),3,0),""-"")"),"CAMPO") -> CAMPO
A31: NTE 01 - IRECÊ | B31: IBITITA | C31: ANEXO | D31: 1179281 | E31: 1179372 | F31: 29459141 | G31: ANEXO - CEMIT IRECÊ - DISTRITO FEIRA NOVA | H31: FEIRA NOVA - SN(00018) | I31: CENTRO | J31: 30KM | K31: CEDIDO | L31: PEQUENO | M31: =IFERROR(__xludf.DUMMYFUNCTION("IFERROR(VLOOKUP(D31, IMPORTRANGE(""https://docs.google.com/spreadsheets/d/1MjHtlUikwobi2MaWJgy7tfLeBmhj1u-dRFRs_8GwSoA/edit#gid=0"",""Gestores Escolares!D7:J""),3,0),""VERIFICAR CÓD SEC"")"),"MARCOS PAULO DA SILVA ALMEIDA") -> MARCOS PAULO DA SILVA ALMEIDA | N31: =IFERROR(__xludf.DUMMYFUNCTION("IFERROR(VLOOKUP(D31, IMPORTRANGE(""https://docs.google.com/spreadsheets/d/1MjHtlUikwobi2MaWJgy7tfLeBmhj1u-dRFRs_8GwSoA/edit#gid=0"",""Gestores Escolares!D7:J""),4,0),""VERIFICAR CÓD SEC"")"),"(74) 9 9998-8112") -> (74) 9 9998-8112 | O31: =IFERROR(__xludf.DUMMYFUNCTION("IFERROR(VLOOKUP(D31, IMPORTRANGE(""https://docs.google.com/spreadsheets/d/1MjHtlUikwobi2MaWJgy7tfLeBmhj1u-dRFRs_8GwSoA/edit#gid=0"",""Gestores Escolares!D7:J""),6,0),""VERIFICAR CÓD SEC"")"),"FERNANDA MIRANDA CAMPOS") -> FERNANDA MIRANDA CAMPOS | P31: =IFERROR(__xludf.DUMMYFUNCTION("IFERROR(VLOOKUP(D31, IMPORTRANGE(""https://docs.google.com/spreadsheets/d/1MjHtlUikwobi2MaWJgy7tfLeBmhj1u-dRFRs_8GwSoA/edit#gid=0"",""Gestores Escolares!D7:J""),7,0),""VERIFICAR CÓD SEC"")"),"(74) 9 9963-4717") -> (74) 9 9963-4717 | Q31: =IFERROR(__xludf.DUMMYFUNCTION("IFERROR(VLOOKUP(D31, IMPORTRANGE(""https://docs.google.com/spreadsheets/d/1MjHtlUikwobi2MaWJgy7tfLeBmhj1u-dRFRs_8GwSoA/edit#gid=0"",""Gestores Escolares!D7:m""),9,0),""VERIFICAR CÓD SEC"")"),"") | R31: =IFERROR(__xludf.DUMMYFUNCTION("IFERROR(VLOOKUP(D31, IMPORTRANGE(""https://docs.google.com/spreadsheets/d/1MjHtlUikwobi2MaWJgy7tfLeBmhj1u-dRFRs_8GwSoA/edit#gid=0"",""Gestores Escolares!D7:m""),10,0),""VERIFICAR CÓD SEC"")"),"") | T31: 3 | U31: 3 | V31: 0 | W31: 0 | X31: 0 | Y31: 0 | Z31: =SUM(V31:Y31) -> 0 | AA31: 0 | AB31: 0 | AC31: 0 | AD31: 0 | AE31: =SUM(AA31:AD31) -> 0 | AF31: 0 | AG31: 0 | AH31: 42 | AI31: 0 | AJ31: =SUM(AF31:AI31) -> 42 | AK31: 0 | AL31: 0 | AM31: 0 | AN31: =SUM(AK31:AM31) -> 0 | AO31: 0 | AP31: 0 | AQ31: 0 | AR31: =SUM(AO31:AQ31) -> 0 | AS31: 0 | AT31: 0 | AU31: 0 | AV31: 0 | AW31: =SUM(AS31:AV31) -> 0 | AX31: =SUM(AY31:AZ31) -> 42 | AY31: =SUM(AV31,AT31,AS31,AP31,AO31,AL31,AK31,AI31,AG31,AF31,AD31,AB31,AA31,Y31,W31,V31) -> 0 | AZ31: =SUM(AU31,AQ31,AM31,AH31,AC31,X31) -> 42 | BA31: 0 | BB31: =SUM(AX31+BA31) -> 42 | BC31: A DEFINIR | BD31: CEMIT | BE31: PROFISSIONAL | BG31: 1179372 | BI31: 3 | BJ31: PADRÃO ANTIGO | BK31: =Y31+AD31+AI31+AV31 -> 0 | BL31: =V31+W31+AA31+AB31+AF31+AG31+AK31+AL31+AO31+AP31+AS31+AT31 -> 0 | BM31: =IFERROR(__xludf.DUMMYFUNCTION("IFERROR(VLOOKUP(BG31,IMPORTRANGE(""https://docs.google.com/spreadsheets/d/1juPI-Fb8LD0YtltB2mlGEnp_R3UVu1t3wSFPzgCyHXE/edit?gid=0#gid=0"",""GERAL!A2:C""),3,0),""-"")"),"-") -> -
A32: NTE 01 - IRECÊ | B32: IPUPIARA | C32: ESCOLA | D32: 1127260 | F32: 29207843 | G32: COLEGIO ESTADUAL DE TEMPO INTEGRAL CASTRO ALVES | H32: PRACA DA BANDEIRA - 36 | I32: CENTRO | J32: SEDE | K32: PRÓPRIO | L32: MÉDIO | M32: =IFERROR(__xludf.DUMMYFUNCTION("IFERROR(VLOOKUP(D32, IMPORTRANGE(""https://docs.google.com/spreadsheets/d/1MjHtlUikwobi2MaWJgy7tfLeBmhj1u-dRFRs_8GwSoA/edit#gid=0"",""Gestores Escolares!D7:J""),3,0),""VERIFICAR CÓD SEC"")"),"ANA MARIA RODRIGUES DA SILVA") -> ANA MARIA RODRIGUES DA SILVA | N32: =IFERROR(__xludf.DUMMYFUNCTION("IFERROR(VLOOKUP(D32, IMPORTRANGE(""https://docs.google.com/spreadsheets/d/1MjHtlUikwobi2MaWJgy7tfLeBmhj1u-dRFRs_8GwSoA/edit#gid=0"",""Gestores Escolares!D7:J""),4,0),""VERIFICAR CÓD SEC"")"),"(77) 9 8127-8663") -> (77) 9 8127-8663 | O32: =IFERROR(__xludf.DUMMYFUNCTION("IFERROR(VLOOKUP(D32, IMPORTRANGE(""https://docs.google.com/spreadsheets/d/1MjHtlUikwobi2MaWJgy7tfLeBmhj1u-dRFRs_8GwSoA/edit#gid=0"",""Gestores Escolares!D7:J""),6,0),""VERIFICAR CÓD SEC"")"),"JOSE CARLOS RODRIGUES NOVAIS") -> JOSE CARLOS RODRIGUES NOVAIS | P32: =IFERROR(__xludf.DUMMYFUNCTION("IFERROR(VLOOKUP(D32, IMPORTRANGE(""https://docs.google.com/spreadsheets/d/1MjHtlUikwobi2MaWJgy7tfLeBmhj1u-dRFRs_8GwSoA/edit#gid=0"",""Gestores Escolares!D7:J""),7,0),""VERIFICAR CÓD SEC"")"),"(77) 9 9129-8664") -> (77) 9 9129-8664 | Q32: =IFERROR(__xludf.DUMMYFUNCTION("IFERROR(VLOOKUP(D32, IMPORTRANGE(""https://docs.google.com/spreadsheets/d/1MjHtlUikwobi2MaWJgy7tfLeBmhj1u-dRFRs_8GwSoA/edit#gid=0"",""Gestores Escolares!D7:m""),9,0),""VERIFICAR CÓD SEC"")"),"") | R32: =IFERROR(__xludf.DUMMYFUNCTION("IFERROR(VLOOKUP(D32, IMPORTRANGE(""https://docs.google.com/spreadsheets/d/1MjHtlUikwobi2MaWJgy7tfLeBmhj1u-dRFRs_8GwSoA/edit#gid=0"",""Gestores Escolares!D7:m""),10,0),""VERIFICAR CÓD SEC"")"),"") | T32: 9 | U32: 8 (sendo 07 como salas de aula e 01 adaptada para informática) | V32: 0 | W32: 0 | X32: 0 | Y32: 0 | Z32: =SUM(V32:Y32) -> 0 | AA32: 0 | AB32: 0 | AC32: 0 | AD32: 0 | AE32: =SUM(AA32:AD32) -> 0 | AF32: 182 | AG32: 168 | AH32: 0 | AI32: 0 | AJ32: =SUM(AF32:AI32) -> 350 | AK32: 0 | AL32: 0 | AM32: 0 | AN32: =SUM(AK32:AM32) -> 0 | AO32: 0 | AP32: 0 | AQ32: 52 | AR32: =SUM(AO32:AQ32) -> 52 | AS32: 0 | AT32: 0 | AU32: 10 | AV32: 0 | AW32: =SUM(AS32:AV32) -> 10 | AX32: =SUM(AY32:AZ32) -> 412 | AY32: =SUM(AV32,AT32,AS32,AP32,AO32,AL32,AK32,AI32,AG32,AF32,AD32,AB32,AA32,Y32,W32,V32) -> 350 | AZ32: =SUM(AU32,AQ32,AM32,AH32,AC32,X32) -> 62 | BA32: 0 | BB32: =SUM(AX32+BA32) -> 412 | BC32: A DEFINIR | BD32: A DEFINIR | BE32: A DEFINIR | BG32: 1127260 | BH32: -11.823454045493607, -42.612628556429286 | BI32: 7 | BJ32: PADRÃO ANTIGO | BK32: =Y32+AD32+AI32+AV32 -> 0 | BL32: =V32+W32+AA32+AB32+AF32+AG32+AK32+AL32+AO32+AP32+AS32+AT32 -> 350 | BM32: =IFERROR(__xludf.DUMMYFUNCTION("IFERROR(VLOOKUP(BG32,IMPORTRANGE(""https://docs.google.com/spreadsheets/d/1juPI-Fb8LD0YtltB2mlGEnp_R3UVu1t3wSFPzgCyHXE/edit?gid=0#gid=0"",""GERAL!A2:C""),3,0),""-"")"),"-") -> -
A33: NTE 01 - IRECÊ | B33: IRECE | C33: ESCOLA | D33: 1126611 | F33: 29064147 | G33: COLÉGIO ESTADUAL DE TEMPO INTEGRAL PROFESSORA DÁRIA DOURADO LOPES (ANTIGO - CE LUIZ VIANA FILHO) | H33: AVENIDA CARAIBAS - 659 | I33: CENTRO | J33: SEDE | K33: PRÓPRIO | L33: ESPECIAL | M33: =IFERROR(__xludf.DUMMYFUNCTION("IFERROR(VLOOKUP(D33, IMPORTRANGE(""https://docs.google.com/spreadsheets/d/1MjHtlUikwobi2MaWJgy7tfLeBmhj1u-dRFRs_8GwSoA/edit#gid=0"",""Gestores Escolares!D7:J""),3,0),""VERIFICAR CÓD SEC"")"),"VIVIANE DA GAMA SILVA") -> VIVIANE DA GAMA SILVA | N33: =IFERROR(__xludf.DUMMYFUNCTION("IFERROR(VLOOKUP(D33, IMPORTRANGE(""https://docs.google.com/spreadsheets/d/1MjHtlUikwobi2MaWJgy7tfLeBmhj1u-dRFRs_8GwSoA/edit#gid=0"",""Gestores Escolares!D7:J""),4,0),""VERIFICAR CÓD SEC"")"),"(74) 9 9955-1444/ 9 8127-5221") -> (74) 9 9955-1444/ 9 8127-5221 | O33: =IFERROR(__xludf.DUMMYFUNCTION("IFERROR(VLOOKUP(D33, IMPORTRANGE(""https://docs.google.com/spreadsheets/d/1MjHtlUikwobi2MaWJgy7tfLeBmhj1u-dRFRs_8GwSoA/edit#gid=0"",""Gestores Escolares!D7:J""),6,0),""VERIFICAR CÓD SEC"")"),"ERIVAL BATISTA DE OLIVEIRA") -> ERIVAL BATISTA DE OLIVEIRA | P33: =IFERROR(__xludf.DUMMYFUNCTION("IFERROR(VLOOKUP(D33, IMPORTRANGE(""https://docs.google.com/spreadsheets/d/1MjHtlUikwobi2MaWJgy7tfLeBmhj1u-dRFRs_8GwSoA/edit#gid=0"",""Gestores Escolares!D7:J""),7,0),""VERIFICAR CÓD SEC"")"),"(74) 9 9985-7659") -> (74) 9 9985-7659 | Q33: =IFERROR(__xludf.DUMMYFUNCTION("IFERROR(VLOOKUP(D33, IMPORTRANGE(""https://docs.google.com/spreadsheets/d/1MjHtlUikwobi2MaWJgy7tfLeBmhj1u-dRFRs_8GwSoA/edit#gid=0"",""Gestores Escolares!D7:m""),9,0),""VERIFICAR CÓD SEC"")"),"GRESIELE DA SILVA CARVALHO") -> GRESIELE DA SILVA CARVALHO | R33: =IFERROR(__xludf.DUMMYFUNCTION("IFERROR(VLOOKUP(D33, IMPORTRANGE(""https://docs.google.com/spreadsheets/d/1MjHtlUikwobi2MaWJgy7tfLeBmhj1u-dRFRs_8GwSoA/edit#gid=0"",""Gestores Escolares!D7:m""),10,0),""VERIFICAR CÓD SEC"")"),"(77) 9 9959-0571") -> (77) 9 9959-0571 | T33: 24 | U33: 16 salas, sendo 15 salas de aula e 01 adaptada para AEE. | V33: 0 | W33: 0 | X33: 0 | Y33: 0 | Z33: =SUM(V33:Y33) -> 0 | AA33: 0 | AB33: 0 | AC33: 0 | AD33: 0 | AE33: =SUM(AA33:AD33) -> 0 | AF33: 0 | AG33: 0 | AH33: 0 | AI33: 364 | AJ33: =SUM(AF33:AI33) -> 364 | AK33: 0 | AL33: 0 | AM33: 0 | AN33: =SUM(AK33:AM33) -> 0 | AO33: 0 | AP33: 0 | AQ33: 179 | AR33: =SUM(AO33:AQ33) -> 179 | AS33: 0 | AT33: 0 | AU33: 0 | AV33: 0 | AW33: =SUM(AS33:AV33) -> 0 | AX33: =SUM(AY33:AZ33) -> 543 | AY33: =SUM(AV33,AT33,AS33,AP33,AO33,AL33,AK33,AI33,AG33,AF33,AD33,AB33,AA33,Y33,W33,V33) -> 364 | AZ33: =SUM(AU33,AQ33,AM33,AH33,AC33,X33) -> 179 | BA33: 0 | BB33: =SUM(AX33+BA33) -> 543 | BC33: A DEFINIR | BD33: A DEFINIR | BE33: A DEFINIR | BG33: 1126611 | BH33: -11.314962763572884, -41.85850190963313 | BI33: 14 | BJ33: NOVO PADRÃO (AMPLIAÇÃO COM MODERNIZAÇÃO) | BK33: =Y33+AD33+AI33+AV33 -> 364 | BL33: =V33+W33+AA33+AB33+AF33+AG33+AK33+AL33+AO33+AP33+AS33+AT33 -> 0 | BM33: =IFERROR(__xludf.DUMMYFUNCTION("IFERROR(VLOOKUP(BG33,IMPORTRANGE(""https://docs.google.com/spreadsheets/d/1juPI-Fb8LD0YtltB2mlGEnp_R3UVu1t3wSFPzgCyHXE/edit?gid=0#gid=0"",""GERAL!A2:C""),3,0),""-"")"),"-") -> -
A34: NTE 01 - IRECÊ | B34: IRECE | C34: ESCOLA | D34: 1176431 | F34: 29403230 | G34: COLÉGIO ESTADUAL DE TEMPO INTEGRAL PROFESSOR JORGE RODRIGUES DOS SANTOS (ANTIGO COLÉGIO MODELO LUIS EDUARDO MAGALHÃES) | H34: RUA RAIMUNDO BONFIM - S/N | I34: CENTRO | J34: SEDE | K34: PRÓPRIO | L34: ESPECIAL | M34: =IFERROR(__xludf.DUMMYFUNCTION("IFERROR(VLOOKUP(D34, IMPORTRANGE(""https://docs.google.com/spreadsheets/d/1MjHtlUikwobi2MaWJgy7tfLeBmhj1u-dRFRs_8GwSoA/edit#gid=0"",""Gestores Escolares!D7:J""),3,0),""VERIFICAR CÓD SEC"")"),"WASHINGTON VINÍCIO MATOS DE SOUZA") -> WASHINGTON VINÍCIO MATOS DE SOUZA | N34: =IFERROR(__xludf.DUMMYFUNCTION("IFERROR(VLOOKUP(D34, IMPORTRANGE(""https://docs.google.com/spreadsheets/d/1MjHtlUikwobi2MaWJgy7tfLeBmhj1u-dRFRs_8GwSoA/edit#gid=0"",""Gestores Escolares!D7:J""),4,0),""VERIFICAR CÓD SEC"")"),"(74) 9 9996-5782") -> (74) 9 9996-5782 | O34: =IFERROR(__xludf.DUMMYFUNCTION("IFERROR(VLOOKUP(D34, IMPORTRANGE(""https://docs.google.com/spreadsheets/d/1MjHtlUikwobi2MaWJgy7tfLeBmhj1u-dRFRs_8GwSoA/edit#gid=0"",""Gestores Escolares!D7:J""),6,0),""VERIFICAR CÓD SEC"")"),"ELIANE LACERDA MACHADO") -> ELIANE LACERDA MACHADO | P34: =IFERROR(__xludf.DUMMYFUNCTION("IFERROR(VLOOKUP(D34, IMPORTRANGE(""https://docs.google.com/spreadsheets/d/1MjHtlUikwobi2MaWJgy7tfLeBmhj1u-dRFRs_8GwSoA/edit#gid=0"",""Gestores Escolares!D7:J""),7,0),""VERIFICAR CÓD SEC"")")," (74) 9 9995-8553") -> (74) 9 9995-8553 | Q34: =IFERROR(__xludf.DUMMYFUNCTION("IFERROR(VLOOKUP(D34, IMPORTRANGE(""https://docs.google.com/spreadsheets/d/1MjHtlUikwobi2MaWJgy7tfLeBmhj1u-dRFRs_8GwSoA/edit#gid=0"",""Gestores Escolares!D7:m""),9,0),""VERIFICAR CÓD SEC"")"),"EUGENIO RODRIGUES DE FREITAS") -> EUGENIO RODRIGUES DE FREITAS | R34: =IFERROR(__xludf.DUMMYFUNCTION("IFERROR(VLOOKUP(D34, IMPORTRANGE(""https://docs.google.com/spreadsheets/d/1MjHtlUikwobi2MaWJgy7tfLeBmhj1u-dRFRs_8GwSoA/edit#gid=0"",""Gestores Escolares!D7:m""),10,0),""VERIFICAR CÓD SEC"")"),"(74) 9 9966-4585/ 9 9949-2841") -> (74) 9 9966-4585/ 9 9949-2841 | T34: 13 | U34: 33 salas, sendo 32 salas de aula e 01 adaptada para AEE. | V34: 0 | W34: 0 | X34: 0 | Y34: 0 | Z34: =SUM(V34:Y34) -> 0 | AA34: 0 | AB34: 0 | AC34: 0 | AD34: 0 | AE34: =SUM(AA34:AD34) -> 0 | AF34: 31 | AG34: 0 | AH34: 0 | AI34: 907 | AJ34: =SUM(AF34:AI34) -> 938 | AK34: 0 | AL34: 0 | AM34: 0 | AN34: =SUM(AK34:AM34) -> 0 | AO34: 0 | AP34: 0 | AQ34: 0 | AR34: =SUM(AO34:AQ34) -> 0 | AS34: 0 | AT34: 0 | AU34: 0 | AV34: 0 | AW34: =SUM(AS34:AV34) -> 0 | AX34: =SUM(AY34:AZ34) -> 938 | AY34: =SUM(AV34,AT34,AS34,AP34,AO34,AL34,AK34,AI34,AG34,AF34,AD34,AB34,AA34,Y34,W34,V34) -> 938 | AZ34: =SUM(AU34,AQ34,AM34,AH34,AC34,X34) -> 0 | BA34: 0 | BB34: =SUM(AX34+BA34) -> 938 | BC34: A DEFINIR | BD34: A DEFINIR | BE34: A DEFINIR | BG34: 1176431 | BH34: -11.310090420860126, -41.85831676037118 | BI34: 13 | BJ34: PADRÃO ANTIGO | BK34: =Y34+AD34+AI34+AV34 -> 907 | BL34: =V34+W34+AA34+AB34+AF34+AG34+AK34+AL34+AO34+AP34+AS34+AT34 -> 31 | BM34: =IFERROR(__xludf.DUMMYFUNCTION("IFERROR(VLOOKUP(BG34,IMPORTRANGE(""https://docs.google.com/spreadsheets/d/1juPI-Fb8LD0YtltB2mlGEnp_R3UVu1t3wSFPzgCyHXE/edit?gid=0#gid=0"",""GERAL!A2:C""),3,0),""-"")"),"-") -> -
A35: NTE 01 - IRECÊ | B35: IRECE | C35: ESCOLA | D35: 1126590 | F35: 29064120 | G35: CENTRO TERRITORIAL DE EDUCAÇÃO PROFISSIONAL DE IRECÊ | H35: EST VELHA DA FAZ. BAIXÃO - S/N | I35: BAX. DE SINESIA | J35: SEDE | K35: PRÓPRIO | L35: ESPECIAL | M35: =IFERROR(__xludf.DUMMYFUNCTION("IFERROR(VLOOKUP(D35, IMPORTRANGE(""https://docs.google.com/spreadsheets/d/1MjHtlUikwobi2MaWJgy7tfLeBmhj1u-dRFRs_8GwSoA/edit#gid=0"",""Gestores Escolares!D7:J""),3,0),""VERIFICAR CÓD SEC"")"),"JOICE MACHADO DE CARVALHO") -> JOICE MACHADO DE CARVALHO | N35: =IFERROR(__xludf.DUMMYFUNCTION("IFERROR(VLOOKUP(D35, IMPORTRANGE(""https://docs.google.com/spreadsheets/d/1MjHtlUikwobi2MaWJgy7tfLeBmhj1u-dRFRs_8GwSoA/edit#gid=0"",""Gestores Escolares!D7:J""),4,0),""VERIFICAR CÓD SEC"")"),"(74) 9 8801-9785") -> (74) 9 8801-9785 | O35: =IFERROR(__xludf.DUMMYFUNCTION("IFERROR(VLOOKUP(D35, IMPORTRANGE(""https://docs.google.com/spreadsheets/d/1MjHtlUikwobi2MaWJgy7tfLeBmhj1u-dRFRs_8GwSoA/edit#gid=0"",""Gestores Escolares!D7:J""),6,0),""VERIFICAR CÓD SEC"")"),"LEANA FERREIRA DE ABREU") -> LEANA FERREIRA DE ABREU | P35: =IFERROR(__xludf.DUMMYFUNCTION("IFERROR(VLOOKUP(D35, IMPORTRANGE(""https://docs.google.com/spreadsheets/d/1MjHtlUikwobi2MaWJgy7tfLeBmhj1u-dRFRs_8GwSoA/edit#gid=0"",""Gestores Escolares!D7:J""),7,0),""VERIFICAR CÓD SEC"")"),"(74) 9 9929-6438") -> (74) 9 9929-6438 | Q35: =IFERROR(__xludf.DUMMYFUNCTION("IFERROR(VLOOKUP(D35, IMPORTRANGE(""https://docs.google.com/spreadsheets/d/1MjHtlUikwobi2MaWJgy7tfLeBmhj1u-dRFRs_8GwSoA/edit#gid=0"",""Gestores Escolares!D7:m""),9,0),""VERIFICAR CÓD SEC"")"),"NAIARA ALVES ANDRADE") -> NAIARA ALVES ANDRADE | R35: =IFERROR(__xludf.DUMMYFUNCTION("IFERROR(VLOOKUP(D35, IMPORTRANGE(""https://docs.google.com/spreadsheets/d/1MjHtlUikwobi2MaWJgy7tfLeBmhj1u-dRFRs_8GwSoA/edit#gid=0"",""Gestores Escolares!D7:m""),10,0),""VERIFICAR CÓD SEC"")"),"(74) 9 9902-4563") -> (74) 9 9902-4563 | T35: 15 | U35: 18 | V35: 0 | W35: 0 | X35: 0 | Y35: 0 | Z35: =SUM(V35:Y35) -> 0 | AA35: 0 | AB35: 0 | AC35: 0 | AD35: 0 | AE35: =SUM(AA35:AD35) -> 0 | AF35: 0 | AG35: 0 | AH35: 0 | AI35: 0 | AJ35: =SUM(AF35:AI35) -> 0 | AK35: 0 | AL35: 0 | AM35: 0 | AN35: =SUM(AK35:AM35) -> 0 | AO35: 0 | AP35: 0 | AQ35: 0 | AR35: =SUM(AO35:AQ35) -> 0 | AS35: 698 | AT35: 673 | AU35: 348 | AV35: 0 | AW35: =SUM(AS35:AV35) -> 1719 | AX35: =SUM(AY35:AZ35) -> 1719 | AY35: =SUM(AV35,AT35,AS35,AP35,AO35,AL35,AK35,AI35,AG35,AF35,AD35,AB35,AA35,Y35,W35,V35) -> 1371 | AZ35: =SUM(AU35,AQ35,AM35,AH35,AC35,X35) -> 348 | BA35: 0 | BB35: =SUM(AX35+BA35) -> 1719 | BC35: A DEFINIR | BD35: CETEP | BE35: PROFISSIONAL | BG35: 1126590 | BH35: -11.29890690984817, -41.85545604586694 | BI35: 16 | BJ35: NOVO PADRÃO (MODERNIZAÇÃO) | BK35: =Y35+AD35+AI35+AV35 -> 0 | BL35: =V35+W35+AA35+AB35+AF35+AG35+AK35+AL35+AO35+AP35+AS35+AT35 -> 1371 | BM35: =IFERROR(__xludf.DUMMYFUNCTION("IFERROR(VLOOKUP(BG35,IMPORTRANGE(""https://docs.google.com/spreadsheets/d/1juPI-Fb8LD0YtltB2mlGEnp_R3UVu1t3wSFPzgCyHXE/edit?gid=0#gid=0"",""GERAL!A2:C""),3,0),""-"")"),"-") -> -
A36: NTE 01 - IRECÊ | B36: IRECE | C36: ESCOLA | D36: 1179281 | F36: 29459141 | G36: CENTRO REGIONAL DE ENSINO MÉDIO COM INTERMEDIAÇÃO TECNOLÓGICA - CEMIT DE IRECÊ | H36: RAIMUNDO BONFIM N SN(00041) Bairro: CENTRO CEP: 44900000 | I36: CENTRO | J36: SEDE | K36: PRÓPRIO | L36: ESPECIAL | M36: =IFERROR(__xludf.DUMMYFUNCTION("IFERROR(VLOOKUP(D36, IMPORTRANGE(""https://docs.google.com/spreadsheets/d/1MjHtlUikwobi2MaWJgy7tfLeBmhj1u-dRFRs_8GwSoA/edit#gid=0"",""Gestores Escolares!D7:J""),3,0),""VERIFICAR CÓD SEC"")"),"MARCOS PAULO DA SILVA ALMEIDA") -> MARCOS PAULO DA SILVA ALMEIDA | N36: =IFERROR(__xludf.DUMMYFUNCTION("IFERROR(VLOOKUP(D36, IMPORTRANGE(""https://docs.google.com/spreadsheets/d/1MjHtlUikwobi2MaWJgy7tfLeBmhj1u-dRFRs_8GwSoA/edit#gid=0"",""Gestores Escolares!D7:J""),4,0),""VERIFICAR CÓD SEC"")"),"(74) 9 9998-8112") -> (74) 9 9998-8112 | O36: =IFERROR(__xludf.DUMMYFUNCTION("IFERROR(VLOOKUP(D36, IMPORTRANGE(""https://docs.google.com/spreadsheets/d/1MjHtlUikwobi2MaWJgy7tfLeBmhj1u-dRFRs_8GwSoA/edit#gid=0"",""Gestores Escolares!D7:J""),6,0),""VERIFICAR CÓD SEC"")"),"FERNANDA MIRANDA CAMPOS") -> FERNANDA MIRANDA CAMPOS | P36: =IFERROR(__xludf.DUMMYFUNCTION("IFERROR(VLOOKUP(D36, IMPORTRANGE(""https://docs.google.com/spreadsheets/d/1MjHtlUikwobi2MaWJgy7tfLeBmhj1u-dRFRs_8GwSoA/edit#gid=0"",""Gestores Escolares!D7:J""),7,0),""VERIFICAR CÓD SEC"")"),"(74) 9 9963-4717") -> (74) 9 9963-4717 | Q36: =IFERROR(__xludf.DUMMYFUNCTION("IFERROR(VLOOKUP(D36, IMPORTRANGE(""https://docs.google.com/spreadsheets/d/1MjHtlUikwobi2MaWJgy7tfLeBmhj1u-dRFRs_8GwSoA/edit#gid=0"",""Gestores Escolares!D7:m""),9,0),""VERIFICAR CÓD SEC"")"),"") | R36: =IFERROR(__xludf.DUMMYFUNCTION("IFERROR(VLOOKUP(D36, IMPORTRANGE(""https://docs.google.com/spreadsheets/d/1MjHtlUikwobi2MaWJgy7tfLeBmhj1u-dRFRs_8GwSoA/edit#gid=0"",""Gestores Escolares!D7:m""),10,0),""VERIFICAR CÓD SEC"")"),"") | T36: - | U36: Não possui salas de aula | V36: 0 | W36: 0 | X36: 0 | Y36: 0 | Z36: =SUM(V36:Y36) -> 0 | AA36: 0 | AB36: 0 | AC36: 0 | AD36: 0 | AE36: =SUM(AA36:AD36) -> 0 | AF36: 0 | AG36: 0 | AH36: 0 | AI36: 0 | AJ36: =SUM(AF36:AI36) -> 0 | AK36: 0 | AL36: 0 | AM36: 0 | AN36: =SUM(AK36:AM36) -> 0 | AO36: 0 | AP36: 0 | AQ36: 0 | AR36: =SUM(AO36:AQ36) -> 0 | AS36: 0 | AT36: 0 | AU36: 0 | AV36: 0 | AW36: =SUM(AS36:AV36) -> 0 | AX36: =SUM(AY36:AZ36) -> 0 | AY36: =SUM(AV36,AT36,AS36,AP36,AO36,AL36,AK36,AI36,AG36,AF36,AD36,AB36,AA36,Y36,W36,V36) -> 0 | AZ36: =SUM(AU36,AQ36,AM36,AH36,AC36,X36) -> 0 | BA36: 0 | BB36: =SUM(AX36+BA36) -> 0 | BC36: A DEFINIR | BD36: CEMIT | BE36: PROFISSIONAL | BF36: UEE ADMINISTRATIVA CEMIT | BG36: 1179281 | BI36: 0 | BJ36: PADRÃO ANTIGO | BK36: =Y36+AD36+AI36+AV36 -> 0 | BL36: =V36+W36+AA36+AB36+AF36+AG36+AK36+AL36+AO36+AP36+AS36+AT36 -> 0 | BM36: =IFERROR(__xludf.DUMMYFUNCTION("IFERROR(VLOOKUP(BG36,IMPORTRANGE(""https://docs.google.com/spreadsheets/d/1juPI-Fb8LD0YtltB2mlGEnp_R3UVu1t3wSFPzgCyHXE/edit?gid=0#gid=0"",""GERAL!A2:C""),3,0),""-"")"),"-") -> -
A37: NTE 01 - IRECÊ | B37: IRECE | C37: ESCOLA | D37: 1179658 | F37: 29474310 | G37: CENTRO JUVENIL DE CIÊNCIA E CULTURA - CJCC IRECÊ | H37: AVENIDA CARAIBAS N 659 Bairro: CENTRO CEP: 44900000 | I37: CENTRO | J37: SEDE | K37: PRÓPRIO | L37: ESPECIAL | M37: =IFERROR(__xludf.DUMMYFUNCTION("IFERROR(VLOOKUP(D37, IMPORTRANGE(""https://docs.google.com/spreadsheets/d/1MjHtlUikwobi2MaWJgy7tfLeBmhj1u-dRFRs_8GwSoA/edit#gid=0"",""Gestores Escolares!D7:J""),3,0),""VERIFICAR CÓD SEC"")"),"MANOEL AUGUSTO MIRANDA DOURADO") -> MANOEL AUGUSTO MIRANDA DOURADO | N37: =IFERROR(__xludf.DUMMYFUNCTION("IFERROR(VLOOKUP(D37, IMPORTRANGE(""https://docs.google.com/spreadsheets/d/1MjHtlUikwobi2MaWJgy7tfLeBmhj1u-dRFRs_8GwSoA/edit#gid=0"",""Gestores Escolares!D7:J""),4,0),""VERIFICAR CÓD SEC"")"),"(74) 9 9968-4497") -> (74) 9 9968-4497 | O37: =IFERROR(__xludf.DUMMYFUNCTION("IFERROR(VLOOKUP(D37, IMPORTRANGE(""https://docs.google.com/spreadsheets/d/1MjHtlUikwobi2MaWJgy7tfLeBmhj1u-dRFRs_8GwSoA/edit#gid=0"",""Gestores Escolares!D7:J""),6,0),""VERIFICAR CÓD SEC"")"),"THIAGO FILGUEIRA PEREIRA") -> THIAGO FILGUEIRA PEREIRA | P37: =IFERROR(__xludf.DUMMYFUNCTION("IFERROR(VLOOKUP(D37, IMPORTRANGE(""https://docs.google.com/spreadsheets/d/1MjHtlUikwobi2MaWJgy7tfLeBmhj1u-dRFRs_8GwSoA/edit#gid=0"",""Gestores Escolares!D7:J""),7,0),""VERIFICAR CÓD SEC"")"),"(74) 9 8829-0038") -> (74) 9 8829-0038 | Q37: =IFERROR(__xludf.DUMMYFUNCTION("IFERROR(VLOOKUP(D37, IMPORTRANGE(""https://docs.google.com/spreadsheets/d/1MjHtlUikwobi2MaWJgy7tfLeBmhj1u-dRFRs_8GwSoA/edit#gid=0"",""Gestores Escolares!D7:m""),9,0),""VERIFICAR CÓD SEC"")"),"") | R37: =IFERROR(__xludf.DUMMYFUNCTION("IFERROR(VLOOKUP(D37, IMPORTRANGE(""https://docs.google.com/spreadsheets/d/1MjHtlUikwobi2MaWJgy7tfLeBmhj1u-dRFRs_8GwSoA/edit#gid=0"",""Gestores Escolares!D7:m""),10,0),""VERIFICAR CÓD SEC"")"),"") | T37: - | U37: 1 | V37: 0 | W37: 0 | X37: 0 | Y37: 0 | Z37: =SUM(V37:Y37) -> 0 | AA37: 0 | AB37: 0 | AC37: 0 | AD37: 0 | AE37: =SUM(AA37:AD37) -> 0 | AF37: 0 | AG37: 0 | AH37: 0 | AI37: 0 | AJ37: =SUM(AF37:AI37) -> 0 | AK37: 0 | AL37: 0 | AM37: 0 | AN37: =SUM(AK37:AM37) -> 0 | AO37: 0 | AP37: 0 | AQ37: 0 | AR37: =SUM(AO37:AQ37) -> 0 | AS37: 0 | AT37: 0 | AU37: 0 | AV37: 0 | AW37: =SUM(AS37:AV37) -> 0 | AX37: =SUM(AY37:AZ37) -> 0 | AY37: =SUM(AV37,AT37,AS37,AP37,AO37,AL37,AK37,AI37,AG37,AF37,AD37,AB37,AA37,Y37,W37,V37) -> 0 | AZ37: =SUM(AU37,AQ37,AM37,AH37,AC37,X37) -> 0 | BA37: 0 | BB37: =SUM(AX37+BA37) -> 0 | BC37: CJCC | BD37: CJCC | BE37: A DEFINIR | BG37: 1179658 | BH37: -11.302379329878278, -41.85370003501203 | BI37: 8 | BJ37: PADRÃO ANTIGO | BK37: =Y37+AD37+AI37+AV37 -> 0 | BL37: =V37+W37+AA37+AB37+AF37+AG37+AK37+AL37+AO37+AP37+AS37+AT37 -> 0 | BM37: =IFERROR(__xludf.DUMMYFUNCTION("IFERROR(VLOOKUP(BG37,IMPORTRANGE(""https://docs.google.com/spreadsheets/d/1juPI-Fb8LD0YtltB2mlGEnp_R3UVu1t3wSFPzgCyHXE/edit?gid=0#gid=0"",""GERAL!A2:C""),3,0),""-"")"),"-") -> -
A38: NTE 01 - IRECÊ | B38: IRECE | C38: ESCOLA | D38: 1179782 | F38: 44169 | G38: CENTRO DE APOIO PEDAGOGICO ESPECIALIZADO IRECE | H38: AVENIDA CARAIBAS -CENTRO N 659 Bairro: CENTRO CEP: 44900-000 | I38: CENTRO | J38: SEDE | K38: PRÓPRIO | L38: ESPECIAL | M38: =IFERROR(__xludf.DUMMYFUNCTION("IFERROR(VLOOKUP(D38, IMPORTRANGE(""https://docs.google.com/spreadsheets/d/1MjHtlUikwobi2MaWJgy7tfLeBmhj1u-dRFRs_8GwSoA/edit#gid=0"",""Gestores Escolares!D7:J""),3,0),""VERIFICAR CÓD SEC"")"),"SEM DIREÇÃO - (AGUARDANDO INDICAÇÃO DO NTE PARA DIREÇÃO DE ESCOLA)") -> SEM DIREÇÃO - (AGUARDANDO INDICAÇÃO DO NTE PARA DIREÇÃO DE ESCOLA) | N38: =IFERROR(__xludf.DUMMYFUNCTION("IFERROR(VLOOKUP(D38, IMPORTRANGE(""https://docs.google.com/spreadsheets/d/1MjHtlUikwobi2MaWJgy7tfLeBmhj1u-dRFRs_8GwSoA/edit#gid=0"",""Gestores Escolares!D7:J""),4,0),""VERIFICAR CÓD SEC"")"),"") | O38: =IFERROR(__xludf.DUMMYFUNCTION("IFERROR(VLOOKUP(D38, IMPORTRANGE(""https://docs.google.com/spreadsheets/d/1MjHtlUikwobi2MaWJgy7tfLeBmhj1u-dRFRs_8GwSoA/edit#gid=0"",""Gestores Escolares!D7:J""),6,0),""VERIFICAR CÓD SEC"")"),"") | P38: =IFERROR(__xludf.DUMMYFUNCTION("IFERROR(VLOOKUP(D38, IMPORTRANGE(""https://docs.google.com/spreadsheets/d/1MjHtlUikwobi2MaWJgy7tfLeBmhj1u-dRFRs_8GwSoA/edit#gid=0"",""Gestores Escolares!D7:J""),7,0),""VERIFICAR CÓD SEC"")"),"") | Q38: =IFERROR(__xludf.DUMMYFUNCTION("IFERROR(VLOOKUP(D38, IMPORTRANGE(""https://docs.google.com/spreadsheets/d/1MjHtlUikwobi2MaWJgy7tfLeBmhj1u-dRFRs_8GwSoA/edit#gid=0"",""Gestores Escolares!D7:m""),9,0),""VERIFICAR CÓD SEC"")"),"") | R38: =IFERROR(__xludf.DUMMYFUNCTION("IFERROR(VLOOKUP(D38, IMPORTRANGE(""https://docs.google.com/spreadsheets/d/1MjHtlUikwobi2MaWJgy7tfLeBmhj1u-dRFRs_8GwSoA/edit#gid=0"",""Gestores Escolares!D7:m""),10,0),""VERIFICAR CÓD SEC"")"),"") | V38: 0 | W38: 0 | X38: 0 | Y38: 0 | Z38: =SUM(V38:Y38) -> 0 | AA38: 0 | AB38: 0 | AC38: 0 | AD38: 0 | AE38: =SUM(AA38:AD38) -> 0 | AF38: 0 | AG38: 0 | AH38: 0 | AI38: 0 | AJ38: =SUM(AF38:AI38) -> 0 | AK38: 0 | AL38: 0 | AM38: 0 | AN38: =SUM(AK38:AM38) -> 0 | AO38: 0 | AP38: 0 | AQ38: 0 | AR38: =SUM(AO38:AQ38) -> 0 | AS38: 0 | AT38: 0 | AU38: 0 | AV38: 0 | AW38: =SUM(AS38:AV38) -> 0 | AX38: =SUM(AY38:AZ38) -> 0 | AY38: =SUM(AV38,AT38,AS38,AP38,AO38,AL38,AK38,AI38,AG38,AF38,AD38,AB38,AA38,Y38,W38,V38) -> 0 | AZ38: =SUM(AU38,AQ38,AM38,AH38,AC38,X38) -> 0 | BA38: 0 | BB38: =SUM(AX38+BA38) -> 0 | BC38: CAP/ESPECIAL | BD38: CAPE | BE38: A DEFINIR | BG38: 1179782 | BK38: =Y38+AD38+AI38+AV38 -> 0 | BL38: =V38+W38+AA38+AB38+AF38+AG38+AK38+AL38+AO38+AP38+AS38+AT38 -> 0 | BM38: =IFERROR(__xludf.DUMMYFUNCTION("IFERROR(VLOOKUP(BG38,IMPORTRANGE(""https://docs.google.com/spreadsheets/d/1juPI-Fb8LD0YtltB2mlGEnp_R3UVu1t3wSFPzgCyHXE/edit?gid=0#gid=0"",""GERAL!A2:C""),3,0),""-"")"),"-") -> -
A39: NTE 01 - IRECÊ | B39: IRECE | C39: ANEXO | D39: 1126611 | E39: 1179803 | F39: 29493374 | G39: ANEXO - COLÉGIO ESTADUAL DE TEMPO INTEGRAL PROFESSORA DÁRIA DOURADO LOPES - POVOADO DE LAGOA NOVA- CONJUNTO PENAL | H39: BA 052 KM 8 LAGOA NOVA ZONA RURAL POVOADO DE LAGOA NOVA N Bairro: - CEP: 44860-089 | J39: - | K39: PRÓPRIO | M39: =IFERROR(__xludf.DUMMYFUNCTION("IFERROR(VLOOKUP(D39, IMPORTRANGE(""https://docs.google.com/spreadsheets/d/1MjHtlUikwobi2MaWJgy7tfLeBmhj1u-dRFRs_8GwSoA/edit#gid=0"",""Gestores Escolares!D7:J""),3,0),""VERIFICAR CÓD SEC"")"),"VIVIANE DA GAMA SILVA") -> VIVIANE DA GAMA SILVA | N39: =IFERROR(__xludf.DUMMYFUNCTION("IFERROR(VLOOKUP(D39, IMPORTRANGE(""https://docs.google.com/spreadsheets/d/1MjHtlUikwobi2MaWJgy7tfLeBmhj1u-dRFRs_8GwSoA/edit#gid=0"",""Gestores Escolares!D7:J""),4,0),""VERIFICAR CÓD SEC"")"),"(74) 9 9955-1444/ 9 8127-5221") -> (74) 9 9955-1444/ 9 8127-5221 | O39: =IFERROR(__xludf.DUMMYFUNCTION("IFERROR(VLOOKUP(D39, IMPORTRANGE(""https://docs.google.com/spreadsheets/d/1MjHtlUikwobi2MaWJgy7tfLeBmhj1u-dRFRs_8GwSoA/edit#gid=0"",""Gestores Escolares!D7:J""),6,0),""VERIFICAR CÓD SEC"")"),"ERIVAL BATISTA DE OLIVEIRA") -> ERIVAL BATISTA DE OLIVEIRA | P39: =IFERROR(__xludf.DUMMYFUNCTION("IFERROR(VLOOKUP(D39, IMPORTRANGE(""https://docs.google.com/spreadsheets/d/1MjHtlUikwobi2MaWJgy7tfLeBmhj1u-dRFRs_8GwSoA/edit#gid=0"",""Gestores Escolares!D7:J""),7,0),""VERIFICAR CÓD SEC"")"),"(74) 9 9985-7659") -> (74) 9 9985-7659 | Q39: =IFERROR(__xludf.DUMMYFUNCTION("IFERROR(VLOOKUP(D39, IMPORTRANGE(""https://docs.google.com/spreadsheets/d/1MjHtlUikwobi2MaWJgy7tfLeBmhj1u-dRFRs_8GwSoA/edit#gid=0"",""Gestores Escolares!D7:m""),9,0),""VERIFICAR CÓD SEC"")"),"GRESIELE DA SILVA CARVALHO") -> GRESIELE DA SILVA CARVALHO | R39: =IFERROR(__xludf.DUMMYFUNCTION("IFERROR(VLOOKUP(D39, IMPORTRANGE(""https://docs.google.com/spreadsheets/d/1MjHtlUikwobi2MaWJgy7tfLeBmhj1u-dRFRs_8GwSoA/edit#gid=0"",""Gestores Escolares!D7:m""),10,0),""VERIFICAR CÓD SEC"")"),"(77) 9 9959-0571") -> (77) 9 9959-0571 | U39: - | V39: 0 | W39: 0 | X39: 0 | Y39: 0 | Z39: =SUM(V39:Y39) -> 0 | AA39: 0 | AB39: 0 | AC39: 0 | AD39: 0 | AE39: =SUM(AA39:AD39) -> 0 | AF39: 0 | AG39: 0 | AH39: 0 | AI39: 0 | AJ39: =SUM(AF39:AI39) -> 0 | AK39: 0 | AL39: 0 | AM39: 0 | AN39: =SUM(AK39:AM39) -> 0 | AO39: 78 | AP39: 0 | AQ39: 17 | AR39: =SUM(AO39:AQ39) -> 95 | AS39: 0 | AT39: 0 | AU39: 0 | AV39: 0 | AW39: =SUM(AS39:AV39) -> 0 | AX39: =SUM(AY39:AZ39) -> 95 | AY39: =SUM(AV39,AT39,AS39,AP39,AO39,AL39,AK39,AI39,AG39,AF39,AD39,AB39,AA39,Y39,W39,V39) -> 78 | AZ39: =SUM(AU39,AQ39,AM39,AH39,AC39,X39) -> 17 | BA39: 0 | BB39: =SUM(AX39+BA39) -> 95 | BC39: PRISIONAL | BG39: 1179803 | BK39: =Y39+AD39+AI39+AV39 -> 0 | BL39: =V39+W39+AA39+AB39+AF39+AG39+AK39+AL39+AO39+AP39+AS39+AT39 -> 78 | BM39: =IFERROR(__xludf.DUMMYFUNCTION("IFERROR(VLOOKUP(BG39,IMPORTRANGE(""https://docs.google.com/spreadsheets/d/1juPI-Fb8LD0YtltB2mlGEnp_R3UVu1t3wSFPzgCyHXE/edit?gid=0#gid=0"",""GERAL!A2:C""),3,0),""-"")"),"-") -> -
A40: NTE 01 - IRECÊ | B40: ITAGUACU DA BAHIA | C40: ESCOLA | D40: 1178258 | F40: 29447755 | G40: COLÉGIO ESTADUAL DO CAMPO FRANCISCO CASTRO LARANJEIRA | H40: RUA DO HOSPITAL - 150 | I40: CENTRO | J40: SEDE | K40: PRÓPRIO | L40: MÉDIO | M40: =IFERROR(__xludf.DUMMYFUNCTION("IFERROR(VLOOKUP(D40, IMPORTRANGE(""https://docs.google.com/spreadsheets/d/1MjHtlUikwobi2MaWJgy7tfLeBmhj1u-dRFRs_8GwSoA/edit#gid=0"",""Gestores Escolares!D7:J""),3,0),""VERIFICAR CÓD SEC"")"),"JOSE WILTON FRANCISCO DA SILVA") -> JOSE WILTON FRANCISCO DA SILVA | N40: =IFERROR(__xludf.DUMMYFUNCTION("IFERROR(VLOOKUP(D40, IMPORTRANGE(""https://docs.google.com/spreadsheets/d/1MjHtlUikwobi2MaWJgy7tfLeBmhj1u-dRFRs_8GwSoA/edit#gid=0"",""Gestores Escolares!D7:J""),4,0),""VERIFICAR CÓD SEC"")"),"(74) 9 9967-4837") -> (74) 9 9967-4837 | O40: =IFERROR(__xludf.DUMMYFUNCTION("IFERROR(VLOOKUP(D40, IMPORTRANGE(""https://docs.google.com/spreadsheets/d/1MjHtlUikwobi2MaWJgy7tfLeBmhj1u-dRFRs_8GwSoA/edit#gid=0"",""Gestores Escolares!D7:J""),6,0),""VERIFICAR CÓD SEC"")"),"DANIELA PIRES BARRETO") -> DANIELA PIRES BARRETO | P40: =IFERROR(__xludf.DUMMYFUNCTION("IFERROR(VLOOKUP(D40, IMPORTRANGE(""https://docs.google.com/spreadsheets/d/1MjHtlUikwobi2MaWJgy7tfLeBmhj1u-dRFRs_8GwSoA/edit#gid=0"",""Gestores Escolares!D7:J""),7,0),""VERIFICAR CÓD SEC"")"),"(74) 9 9935-0933") -> (74) 9 9935-0933 | Q40: =IFERROR(__xludf.DUMMYFUNCTION("IFERROR(VLOOKUP(D40, IMPORTRANGE(""https://docs.google.com/spreadsheets/d/1MjHtlUikwobi2MaWJgy7tfLeBmhj1u-dRFRs_8GwSoA/edit#gid=0"",""Gestores Escolares!D7:m""),9,0),""VERIFICAR CÓD SEC"")"),"") | R40: =IFERROR(__xludf.DUMMYFUNCTION("IFERROR(VLOOKUP(D40, IMPORTRANGE(""https://docs.google.com/spreadsheets/d/1MjHtlUikwobi2MaWJgy7tfLeBmhj1u-dRFRs_8GwSoA/edit#gid=0"",""Gestores Escolares!D7:m""),10,0),""VERIFICAR CÓD SEC"")"),"") | T40: 7 | U40: 09 salas, sendo: 07 utilizadas para aula e 02 adaptadas para laboratórios de 01 informática e 01 ciências. | V40: 0 | W40: 0 | X40: 0 | Y40: 0 | Z40: =SUM(V40:Y40) -> 0 | AA40: 0 | AB40: 0 | AC40: 0 | AD40: 0 | AE40: =SUM(AA40:AD40) -> 0 | AF40: 0 | AG40: 0 | AH40: 0 | AI40: 221 | AJ40: =SUM(AF40:AI40) -> 221 | AK40: 0 | AL40: 0 | AM40: 0 | AN40: =SUM(AK40:AM40) -> 0 | AO40: 0 | AP40: 0 | AQ40: 0 | AR40: =SUM(AO40:AQ40) -> 0 | AS40: 0 | AT40: 0 | AU40: 15 | AV40: 61 | AW40: =SUM(AS40:AV40) -> 76 | AX40: =SUM(AY40:AZ40) -> 297 | AY40: =SUM(AV40,AT40,AS40,AP40,AO40,AL40,AK40,AI40,AG40,AF40,AD40,AB40,AA40,Y40,W40,V40) -> 282 | AZ40: =SUM(AU40,AQ40,AM40,AH40,AC40,X40) -> 15 | BA40: 0 | BB40: =SUM(AX40+BA40) -> 297 | BC40: DO CAMPO | BD40: A DEFINIR | BE40: A DEFINIR | BG40: 1178258 | BH40: -11.009233981867455, -42.3955388386851 | BI40: 6 | BJ40: PADRÃO ANTIGO | BK40: =Y40+AD40+AI40+AV40 -> 282 | BL40: =V40+W40+AA40+AB40+AF40+AG40+AK40+AL40+AO40+AP40+AS40+AT40 -> 0 | BM40: =IFERROR(__xludf.DUMMYFUNCTION("IFERROR(VLOOKUP(BG40,IMPORTRANGE(""https://docs.google.com/spreadsheets/d/1juPI-Fb8LD0YtltB2mlGEnp_R3UVu1t3wSFPzgCyHXE/edit?gid=0#gid=0"",""GERAL!A2:C""),3,0),""-"")"),"CAMPO") -> CAMPO
A41: NTE 01 - IRECÊ | B41: ITAGUACU DA BAHIA | C41: ANEXO | D41: 1179281 | E41: 1179443 | F41: 29459141 | G41: ANEXO -CEMIT - IRECÊ - POVOADO DE MARAVILHA | H41: SN(00002) | I41: CENTRO | J41: 44KM | K41: CEDIDO | L41: PEQUENO | M41: =IFERROR(__xludf.DUMMYFUNCTION("IFERROR(VLOOKUP(D41, IMPORTRANGE(""https://docs.google.com/spreadsheets/d/1MjHtlUikwobi2MaWJgy7tfLeBmhj1u-dRFRs_8GwSoA/edit#gid=0"",""Gestores Escolares!D7:J""),3,0),""VERIFICAR CÓD SEC"")"),"MARCOS PAULO DA SILVA ALMEIDA") -> MARCOS PAULO DA SILVA ALMEIDA | N41: =IFERROR(__xludf.DUMMYFUNCTION("IFERROR(VLOOKUP(D41, IMPORTRANGE(""https://docs.google.com/spreadsheets/d/1MjHtlUikwobi2MaWJgy7tfLeBmhj1u-dRFRs_8GwSoA/edit#gid=0"",""Gestores Escolares!D7:J""),4,0),""VERIFICAR CÓD SEC"")"),"(74) 9 9998-8112") -> (74) 9 9998-8112 | O41: =IFERROR(__xludf.DUMMYFUNCTION("IFERROR(VLOOKUP(D41, IMPORTRANGE(""https://docs.google.com/spreadsheets/d/1MjHtlUikwobi2MaWJgy7tfLeBmhj1u-dRFRs_8GwSoA/edit#gid=0"",""Gestores Escolares!D7:J""),6,0),""VERIFICAR CÓD SEC"")"),"FERNANDA MIRANDA CAMPOS") -> FERNANDA MIRANDA CAMPOS | P41: =IFERROR(__xludf.DUMMYFUNCTION("IFERROR(VLOOKUP(D41, IMPORTRANGE(""https://docs.google.com/spreadsheets/d/1MjHtlUikwobi2MaWJgy7tfLeBmhj1u-dRFRs_8GwSoA/edit#gid=0"",""Gestores Escolares!D7:J""),7,0),""VERIFICAR CÓD SEC"")"),"(74) 9 9963-4717") -> (74) 9 9963-4717 | Q41: =IFERROR(__xludf.DUMMYFUNCTION("IFERROR(VLOOKUP(D41, IMPORTRANGE(""https://docs.google.com/spreadsheets/d/1MjHtlUikwobi2MaWJgy7tfLeBmhj1u-dRFRs_8GwSoA/edit#gid=0"",""Gestores Escolares!D7:m""),9,0),""VERIFICAR CÓD SEC"")"),"") | R41: =IFERROR(__xludf.DUMMYFUNCTION("IFERROR(VLOOKUP(D41, IMPORTRANGE(""https://docs.google.com/spreadsheets/d/1MjHtlUikwobi2MaWJgy7tfLeBmhj1u-dRFRs_8GwSoA/edit#gid=0"",""Gestores Escolares!D7:m""),10,0),""VERIFICAR CÓD SEC"")"),"") | T41: 2 | U41: 1 | V41: 0 | W41: 0 | X41: 0 | Y41: 0 | Z41: =SUM(V41:Y41) -> 0 | AA41: 0 | AB41: 0 | AC41: 0 | AD41: 0 | AE41: =SUM(AA41:AD41) -> 0 | AF41: 0 | AG41: 0 | AH41: 34 | AI41: 0 | AJ41: =SUM(AF41:AI41) -> 34 | AK41: 0 | AL41: 0 | AM41: 0 | AN41: =SUM(AK41:AM41) -> 0 | AO41: 0 | AP41: 0 | AQ41: 0 | AR41: =SUM(AO41:AQ41) -> 0 | AS41: 0 | AT41: 0 | AU41: 0 | AV41: 0 | AW41: =SUM(AS41:AV41) -> 0 | AX41: =SUM(AY41:AZ41) -> 34 | AY41: =SUM(AV41,AT41,AS41,AP41,AO41,AL41,AK41,AI41,AG41,AF41,AD41,AB41,AA41,Y41,W41,V41) -> 0 | AZ41: =SUM(AU41,AQ41,AM41,AH41,AC41,X41) -> 34 | BA41: 0 | BB41: =SUM(AX41+BA41) -> 34 | BC41: A DEFINIR | BD41: CEMIT | BE41: PROFISSIONAL | BG41: 1179443 | BI41: 1 | BJ41: PADRÃO ANTIGO | BK41: =Y41+AD41+AI41+AV41 -> 0 | BL41: =V41+W41+AA41+AB41+AF41+AG41+AK41+AL41+AO41+AP41+AS41+AT41 -> 0 | BM41: =IFERROR(__xludf.DUMMYFUNCTION("IFERROR(VLOOKUP(BG41,IMPORTRANGE(""https://docs.google.com/spreadsheets/d/1juPI-Fb8LD0YtltB2mlGEnp_R3UVu1t3wSFPzgCyHXE/edit?gid=0#gid=0"",""GERAL!A2:C""),3,0),""-"")"),"-") -> -
A42: NTE 01 - IRECÊ | B42: ITAGUACU DA BAHIA | C42: ANEXO | D42: 1179281 | E42: 1179046 | F42: 29459141 | G42: ANEXO - CEMIT - IRECE - POVOADO MUNDINHO | H42: POV. DE MUNDINHO - SN(00002) | I42: CENTRO | J42: 30KM | K42: CEDIDO | L42: PEQUENO | M42: =IFERROR(__xludf.DUMMYFUNCTION("IFERROR(VLOOKUP(D42, IMPORTRANGE(""https://docs.google.com/spreadsheets/d/1MjHtlUikwobi2MaWJgy7tfLeBmhj1u-dRFRs_8GwSoA/edit#gid=0"",""Gestores Escolares!D7:J""),3,0),""VERIFICAR CÓD SEC"")"),"MARCOS PAULO DA SILVA ALMEIDA") -> MARCOS PAULO DA SILVA ALMEIDA | N42: =IFERROR(__xludf.DUMMYFUNCTION("IFERROR(VLOOKUP(D42, IMPORTRANGE(""https://docs.google.com/spreadsheets/d/1MjHtlUikwobi2MaWJgy7tfLeBmhj1u-dRFRs_8GwSoA/edit#gid=0"",""Gestores Escolares!D7:J""),4,0),""VERIFICAR CÓD SEC"")"),"(74) 9 9998-8112") -> (74) 9 9998-8112 | O42: =IFERROR(__xludf.DUMMYFUNCTION("IFERROR(VLOOKUP(D42, IMPORTRANGE(""https://docs.google.com/spreadsheets/d/1MjHtlUikwobi2MaWJgy7tfLeBmhj1u-dRFRs_8GwSoA/edit#gid=0"",""Gestores Escolares!D7:J""),6,0),""VERIFICAR CÓD SEC"")"),"FERNANDA MIRANDA CAMPOS") -> FERNANDA MIRANDA CAMPOS | P42: =IFERROR(__xludf.DUMMYFUNCTION("IFERROR(VLOOKUP(D42, IMPORTRANGE(""https://docs.google.com/spreadsheets/d/1MjHtlUikwobi2MaWJgy7tfLeBmhj1u-dRFRs_8GwSoA/edit#gid=0"",""Gestores Escolares!D7:J""),7,0),""VERIFICAR CÓD SEC"")"),"(74) 9 9963-4717") -> (74) 9 9963-4717 | Q42: =IFERROR(__xludf.DUMMYFUNCTION("IFERROR(VLOOKUP(D42, IMPORTRANGE(""https://docs.google.com/spreadsheets/d/1MjHtlUikwobi2MaWJgy7tfLeBmhj1u-dRFRs_8GwSoA/edit#gid=0"",""Gestores Escolares!D7:m""),9,0),""VERIFICAR CÓD SEC"")"),"") | R42: =IFERROR(__xludf.DUMMYFUNCTION("IFERROR(VLOOKUP(D42, IMPORTRANGE(""https://docs.google.com/spreadsheets/d/1MjHtlUikwobi2MaWJgy7tfLeBmhj1u-dRFRs_8GwSoA/edit#gid=0"",""Gestores Escolares!D7:m""),10,0),""VERIFICAR CÓD SEC"")"),"") | T42: 1 | U42: 2 | V42: 0 | W42: 0 | X42: 0 | Y42: 0 | Z42: =SUM(V42:Y42) -> 0 | AA42: 0 | AB42: 0 | AC42: 0 | AD42: 0 | AE42: =SUM(AA42:AD42) -> 0 | AF42: 0 | AG42: 0 | AH42: 57 | AI42: 0 | AJ42: =SUM(AF42:AI42) -> 57 | AK42: 0 | AL42: 0 | AM42: 0 | AN42: =SUM(AK42:AM42) -> 0 | AO42: 0 | AP42: 0 | AQ42: 0 | AR42: =SUM(AO42:AQ42) -> 0 | AS42: 0 | AT42: 0 | AU42: 0 | AV42: 0 | AW42: =SUM(AS42:AV42) -> 0 | AX42: =SUM(AY42:AZ42) -> 57 | AY42: =SUM(AV42,AT42,AS42,AP42,AO42,AL42,AK42,AI42,AG42,AF42,AD42,AB42,AA42,Y42,W42,V42) -> 0 | AZ42: =SUM(AU42,AQ42,AM42,AH42,AC42,X42) -> 57 | BA42: 0 | BB42: =SUM(AX42+BA42) -> 57 | BC42: A DEFINIR | BD42: CEMIT | BE42: PROFISSIONAL | BG42: 1179046 | BI42: 2 | BJ42: PADRÃO ANTIGO | BK42: =Y42+AD42+AI42+AV42 -> 0 | BL42: =V42+W42+AA42+AB42+AF42+AG42+AK42+AL42+AO42+AP42+AS42+AT42 -> 0 | BM42: =IFERROR(__xludf.DUMMYFUNCTION("IFERROR(VLOOKUP(BG42,IMPORTRANGE(""https://docs.google.com/spreadsheets/d/1juPI-Fb8LD0YtltB2mlGEnp_R3UVu1t3wSFPzgCyHXE/edit?gid=0#gid=0"",""GERAL!A2:C""),3,0),""-"")"),"-") -> -
A43: NTE 01 - IRECÊ | B43: ITAGUACU DA BAHIA | C43: ANEXO | D43: 1179281 | E43: 1178799 | F43: 29459141 | G43: ANEXO - CEMIT - IRECÊ - POVOADO FAZENDA ALMAS | H43: POV. FAZ. ALMAS - SN(00009) | I43: CENTRO | J43: 27KM | K43: CEDIDO | L43: PEQUENO | M43: =IFERROR(__xludf.DUMMYFUNCTION("IFERROR(VLOOKUP(D43, IMPORTRANGE(""https://docs.google.com/spreadsheets/d/1MjHtlUikwobi2MaWJgy7tfLeBmhj1u-dRFRs_8GwSoA/edit#gid=0"",""Gestores Escolares!D7:J""),3,0),""VERIFICAR CÓD SEC"")"),"MARCOS PAULO DA SILVA ALMEIDA") -> MARCOS PAULO DA SILVA ALMEIDA | N43: =IFERROR(__xludf.DUMMYFUNCTION("IFERROR(VLOOKUP(D43, IMPORTRANGE(""https://docs.google.com/spreadsheets/d/1MjHtlUikwobi2MaWJgy7tfLeBmhj1u-dRFRs_8GwSoA/edit#gid=0"",""Gestores Escolares!D7:J""),4,0),""VERIFICAR CÓD SEC"")"),"(74) 9 9998-8112") -> (74) 9 9998-8112 | O43: =IFERROR(__xludf.DUMMYFUNCTION("IFERROR(VLOOKUP(D43, IMPORTRANGE(""https://docs.google.com/spreadsheets/d/1MjHtlUikwobi2MaWJgy7tfLeBmhj1u-dRFRs_8GwSoA/edit#gid=0"",""Gestores Escolares!D7:J""),6,0),""VERIFICAR CÓD SEC"")"),"FERNANDA MIRANDA CAMPOS") -> FERNANDA MIRANDA CAMPOS | P43: =IFERROR(__xludf.DUMMYFUNCTION("IFERROR(VLOOKUP(D43, IMPORTRANGE(""https://docs.google.com/spreadsheets/d/1MjHtlUikwobi2MaWJgy7tfLeBmhj1u-dRFRs_8GwSoA/edit#gid=0"",""Gestores Escolares!D7:J""),7,0),""VERIFICAR CÓD SEC"")"),"(74) 9 9963-4717") -> (74) 9 9963-4717 | Q43: =IFERROR(__xludf.DUMMYFUNCTION("IFERROR(VLOOKUP(D43, IMPORTRANGE(""https://docs.google.com/spreadsheets/d/1MjHtlUikwobi2MaWJgy7tfLeBmhj1u-dRFRs_8GwSoA/edit#gid=0"",""Gestores Escolares!D7:m""),9,0),""VERIFICAR CÓD SEC"")"),"") | R43: =IFERROR(__xludf.DUMMYFUNCTION("IFERROR(VLOOKUP(D43, IMPORTRANGE(""https://docs.google.com/spreadsheets/d/1MjHtlUikwobi2MaWJgy7tfLeBmhj1u-dRFRs_8GwSoA/edit#gid=0"",""Gestores Escolares!D7:m""),10,0),""VERIFICAR CÓD SEC"")"),"") | T43: 1 | U43: 3 | V43: 0 | W43: 0 | X43: 0 | Y43: 0 | Z43: =SUM(V43:Y43) -> 0 | AA43: 0 | AB43: 0 | AC43: 0 | AD43: 0 | AE43: =SUM(AA43:AD43) -> 0 | AF43: 11 | AG43: 34 | AH43: 40 | AI43: 0 | AJ43: =SUM(AF43:AI43) -> 85 | AK43: 0 | AL43: 0 | AM43: 0 | AN43: =SUM(AK43:AM43) -> 0 | AO43: 0 | AP43: 0 | AQ43: 0 | AR43: =SUM(AO43:AQ43) -> 0 | AS43: 0 | AT43: 0 | AU43: 0 | AV43: 0 | AW43: =SUM(AS43:AV43) -> 0 | AX43: =SUM(AY43:AZ43) -> 85 | AY43: =SUM(AV43,AT43,AS43,AP43,AO43,AL43,AK43,AI43,AG43,AF43,AD43,AB43,AA43,Y43,W43,V43) -> 45 | AZ43: =SUM(AU43,AQ43,AM43,AH43,AC43,X43) -> 40 | BA43: 0 | BB43: =SUM(AX43+BA43) -> 85 | BC43: A DEFINIR | BD43: CEMIT | BE43: PROFISSIONAL | BG43: 1178799 | BI43: 3 | BJ43: PADRÃO ANTIGO | BK43: =Y43+AD43+AI43+AV43 -> 0 | BL43: =V43+W43+AA43+AB43+AF43+AG43+AK43+AL43+AO43+AP43+AS43+AT43 -> 45 | BM43: =IFERROR(__xludf.DUMMYFUNCTION("IFERROR(VLOOKUP(BG43,IMPORTRANGE(""https://docs.google.com/spreadsheets/d/1juPI-Fb8LD0YtltB2mlGEnp_R3UVu1t3wSFPzgCyHXE/edit?gid=0#gid=0"",""GERAL!A2:C""),3,0),""-"")"),"-") -> -
A44: NTE 01 - IRECÊ | B44: ITAGUACU DA BAHIA | C44: ANEXO | D44: 1179281 | E44: 1178956 | F44: 29459141 | G44: ANEXO - CEMIT - IRECÊ - POVOADO BARREIROS - COMUNIDADE QUILOMBOLA | H44: BARREIROS - SN(00028) | I44: CENTRO | J44: 18KM | K44: CEDIDO | L44: PEQUENO | M44: =IFERROR(__xludf.DUMMYFUNCTION("IFERROR(VLOOKUP(D44, IMPORTRANGE(""https://docs.google.com/spreadsheets/d/1MjHtlUikwobi2MaWJgy7tfLeBmhj1u-dRFRs_8GwSoA/edit#gid=0"",""Gestores Escolares!D7:J""),3,0),""VERIFICAR CÓD SEC"")"),"MARCOS PAULO DA SILVA ALMEIDA") -> MARCOS PAULO DA SILVA ALMEIDA | N44: =IFERROR(__xludf.DUMMYFUNCTION("IFERROR(VLOOKUP(D44, IMPORTRANGE(""https://docs.google.com/spreadsheets/d/1MjHtlUikwobi2MaWJgy7tfLeBmhj1u-dRFRs_8GwSoA/edit#gid=0"",""Gestores Escolares!D7:J""),4,0),""VERIFICAR CÓD SEC"")"),"(74) 9 9998-8112") -> (74) 9 9998-8112 | O44: =IFERROR(__xludf.DUMMYFUNCTION("IFERROR(VLOOKUP(D44, IMPORTRANGE(""https://docs.google.com/spreadsheets/d/1MjHtlUikwobi2MaWJgy7tfLeBmhj1u-dRFRs_8GwSoA/edit#gid=0"",""Gestores Escolares!D7:J""),6,0),""VERIFICAR CÓD SEC"")"),"FERNANDA MIRANDA CAMPOS") -> FERNANDA MIRANDA CAMPOS | P44: =IFERROR(__xludf.DUMMYFUNCTION("IFERROR(VLOOKUP(D44, IMPORTRANGE(""https://docs.google.com/spreadsheets/d/1MjHtlUikwobi2MaWJgy7tfLeBmhj1u-dRFRs_8GwSoA/edit#gid=0"",""Gestores Escolares!D7:J""),7,0),""VERIFICAR CÓD SEC"")"),"(74) 9 9963-4717") -> (74) 9 9963-4717 | Q44: =IFERROR(__xludf.DUMMYFUNCTION("IFERROR(VLOOKUP(D44, IMPORTRANGE(""https://docs.google.com/spreadsheets/d/1MjHtlUikwobi2MaWJgy7tfLeBmhj1u-dRFRs_8GwSoA/edit#gid=0"",""Gestores Escolares!D7:m""),9,0),""VERIFICAR CÓD SEC"")"),"") | R44: =IFERROR(__xludf.DUMMYFUNCTION("IFERROR(VLOOKUP(D44, IMPORTRANGE(""https://docs.google.com/spreadsheets/d/1MjHtlUikwobi2MaWJgy7tfLeBmhj1u-dRFRs_8GwSoA/edit#gid=0"",""Gestores Escolares!D7:m""),10,0),""VERIFICAR CÓD SEC"")"),"") | T44: 1 | U44: 3 | V44: 0 | W44: 0 | X44: 0 | Y44: 0 | Z44: =SUM(V44:Y44) -> 0 | AA44: 0 | AB44: 0 | AC44: 0 | AD44: 0 | AE44: =SUM(AA44:AD44) -> 0 | AF44: 10 | AG44: 13 | AH44: 23 | AI44: 0 | AJ44: =SUM(AF44:AI44) -> 46 | AK44: 0 | AL44: 0 | AM44: 0 | AN44: =SUM(AK44:AM44) -> 0 | AO44: 0 | AP44: 0 | AQ44: 0 | AR44: =SUM(AO44:AQ44) -> 0 | AS44: 0 | AT44: 0 | AU44: 0 | AV44: 0 | AW44: =SUM(AS44:AV44) -> 0 | AX44: =SUM(AY44:AZ44) -> 46 | AY44: =SUM(AV44,AT44,AS44,AP44,AO44,AL44,AK44,AI44,AG44,AF44,AD44,AB44,AA44,Y44,W44,V44) -> 23 | AZ44: =SUM(AU44,AQ44,AM44,AH44,AC44,X44) -> 23 | BA44: 0 | BB44: =SUM(AX44+BA44) -> 46 | BC44: QUILOMBOLA | BD44: CEMIT | BE44: A DEFINIR | BG44: 1178956 | BI44: 3 | BJ44: PADRÃO ANTIGO | BK44: =Y44+AD44+AI44+AV44 -> 0 | BL44: =V44+W44+AA44+AB44+AF44+AG44+AK44+AL44+AO44+AP44+AS44+AT44 -> 23 | BM44: =IFERROR(__xludf.DUMMYFUNCTION("IFERROR(VLOOKUP(BG44,IMPORTRANGE(""https://docs.google.com/spreadsheets/d/1juPI-Fb8LD0YtltB2mlGEnp_R3UVu1t3wSFPzgCyHXE/edit?gid=0#gid=0"",""GERAL!A2:C""),3,0),""-"")"),"QUILOMBOLAS") -> QUILOMBOLAS
A45: NTE 01 - IRECÊ | B45: ITAGUACU DA BAHIA | C45: ANEXO | D45: 1179281 | E45: 1179161 | F45: 29459141 | G45: ANEXO - CEMIT - IRECÊ - DISTRITO VÁRZEA GRANDE | H45: VARZEA GRANDE - SN(00084) | I45: CENTRO | J45: 25KM | K45: CEDIDO | L45: PEQUENO | M45: =IFERROR(__xludf.DUMMYFUNCTION("IFERROR(VLOOKUP(D45, IMPORTRANGE(""https://docs.google.com/spreadsheets/d/1MjHtlUikwobi2MaWJgy7tfLeBmhj1u-dRFRs_8GwSoA/edit#gid=0"",""Gestores Escolares!D7:J""),3,0),""VERIFICAR CÓD SEC"")"),"MARCOS PAULO DA SILVA ALMEIDA") -> MARCOS PAULO DA SILVA ALMEIDA | N45: =IFERROR(__xludf.DUMMYFUNCTION("IFERROR(VLOOKUP(D45, IMPORTRANGE(""https://docs.google.com/spreadsheets/d/1MjHtlUikwobi2MaWJgy7tfLeBmhj1u-dRFRs_8GwSoA/edit#gid=0"",""Gestores Escolares!D7:J""),4,0),""VERIFICAR CÓD SEC"")"),"(74) 9 9998-8112") -> (74) 9 9998-8112 | O45: =IFERROR(__xludf.DUMMYFUNCTION("IFERROR(VLOOKUP(D45, IMPORTRANGE(""https://docs.google.com/spreadsheets/d/1MjHtlUikwobi2MaWJgy7tfLeBmhj1u-dRFRs_8GwSoA/edit#gid=0"",""Gestores Escolares!D7:J""),6,0),""VERIFICAR CÓD SEC"")"),"FERNANDA MIRANDA CAMPOS") -> FERNANDA MIRANDA CAMPOS | P45: =IFERROR(__xludf.DUMMYFUNCTION("IFERROR(VLOOKUP(D45, IMPORTRANGE(""https://docs.google.com/spreadsheets/d/1MjHtlUikwobi2MaWJgy7tfLeBmhj1u-dRFRs_8GwSoA/edit#gid=0"",""Gestores Escolares!D7:J""),7,0),""VERIFICAR CÓD SEC"")"),"(74) 9 9963-4717") -> (74) 9 9963-4717 | Q45: =IFERROR(__xludf.DUMMYFUNCTION("IFERROR(VLOOKUP(D45, IMPORTRANGE(""https://docs.google.com/spreadsheets/d/1MjHtlUikwobi2MaWJgy7tfLeBmhj1u-dRFRs_8GwSoA/edit#gid=0"",""Gestores Escolares!D7:m""),9,0),""VERIFICAR CÓD SEC"")"),"") | R45: =IFERROR(__xludf.DUMMYFUNCTION("IFERROR(VLOOKUP(D45, IMPORTRANGE(""https://docs.google.com/spreadsheets/d/1MjHtlUikwobi2MaWJgy7tfLeBmhj1u-dRFRs_8GwSoA/edit#gid=0"",""Gestores Escolares!D7:m""),10,0),""VERIFICAR CÓD SEC"")"),"") | T45: 1 | U45: 3 | V45: 0 | W45: 0 | X45: 0 | Y45: 0 | Z45: =SUM(V45:Y45) -> 0 | AA45: 0 | AB45: 0 | AC45: 0 | AD45: 0 | AE45: =SUM(AA45:AD45) -> 0 | AF45: 27 | AG45: 0 | AH45: 0 | AI45: 0 | AJ45: =SUM(AF45:AI45) -> 27 | AK45: 0 | AL45: 0 | AM45: 0 | AN45: =SUM(AK45:AM45) -> 0 | AO45: 0 | AP45: 0 | AQ45: 0 | AR45: =SUM(AO45:AQ45) -> 0 | AS45: 0 | AT45: 0 | AU45: 0 | AV45: 0 | AW45: =SUM(AS45:AV45) -> 0 | AX45: =SUM(AY45:AZ45) -> 27 | AY45: =SUM(AV45,AT45,AS45,AP45,AO45,AL45,AK45,AI45,AG45,AF45,AD45,AB45,AA45,Y45,W45,V45) -> 27 | AZ45: =SUM(AU45,AQ45,AM45,AH45,AC45,X45) -> 0 | BA45: 0 | BB45: =SUM(AX45+BA45) -> 27 | BC45: A DEFINIR | BD45: CEMIT | BE45: PROFISSIONAL | BG45: 1179161 | BI45: 3 | BJ45: PADRÃO ANTIGO | BK45: =Y45+AD45+AI45+AV45 -> 0 | BL45: =V45+W45+AA45+AB45+AF45+AG45+AK45+AL45+AO45+AP45+AS45+AT45 -> 27 | BM45: =IFERROR(__xludf.DUMMYFUNCTION("IFERROR(VLOOKUP(BG45,IMPORTRANGE(""https://docs.google.com/spreadsheets/d/1juPI-Fb8LD0YtltB2mlGEnp_R3UVu1t3wSFPzgCyHXE/edit?gid=0#gid=0"",""GERAL!A2:C""),3,0),""-"")"),"-") -> -
A46: NTE 01 - IRECÊ | B46: ITAGUACU DA BAHIA | C46: ANEXO | D46: 1179281 | E46: 1179146 | F46: 29459141 | G46: ANEXO - CEMIT - IRECÊ - ASSENTAMENTO CALIFÓRNIA II | H46: CALIFORNIA II - SN(00002) | I46: CENTRO | J46: 87KM | K46: CEDIDO | L46: PEQUENO | M46: =IFERROR(__xludf.DUMMYFUNCTION("IFERROR(VLOOKUP(D46, IMPORTRANGE(""https://docs.google.com/spreadsheets/d/1MjHtlUikwobi2MaWJgy7tfLeBmhj1u-dRFRs_8GwSoA/edit#gid=0"",""Gestores Escolares!D7:J""),3,0),""VERIFICAR CÓD SEC"")"),"MARCOS PAULO DA SILVA ALMEIDA") -> MARCOS PAULO DA SILVA ALMEIDA | N46: =IFERROR(__xludf.DUMMYFUNCTION("IFERROR(VLOOKUP(D46, IMPORTRANGE(""https://docs.google.com/spreadsheets/d/1MjHtlUikwobi2MaWJgy7tfLeBmhj1u-dRFRs_8GwSoA/edit#gid=0"",""Gestores Escolares!D7:J""),4,0),""VERIFICAR CÓD SEC"")"),"(74) 9 9998-8112") -> (74) 9 9998-8112 | O46: =IFERROR(__xludf.DUMMYFUNCTION("IFERROR(VLOOKUP(D46, IMPORTRANGE(""https://docs.google.com/spreadsheets/d/1MjHtlUikwobi2MaWJgy7tfLeBmhj1u-dRFRs_8GwSoA/edit#gid=0"",""Gestores Escolares!D7:J""),6,0),""VERIFICAR CÓD SEC"")"),"FERNANDA MIRANDA CAMPOS") -> FERNANDA MIRANDA CAMPOS | P46: =IFERROR(__xludf.DUMMYFUNCTION("IFERROR(VLOOKUP(D46, IMPORTRANGE(""https://docs.google.com/spreadsheets/d/1MjHtlUikwobi2MaWJgy7tfLeBmhj1u-dRFRs_8GwSoA/edit#gid=0"",""Gestores Escolares!D7:J""),7,0),""VERIFICAR CÓD SEC"")"),"(74) 9 9963-4717") -> (74) 9 9963-4717 | Q46: =IFERROR(__xludf.DUMMYFUNCTION("IFERROR(VLOOKUP(D46, IMPORTRANGE(""https://docs.google.com/spreadsheets/d/1MjHtlUikwobi2MaWJgy7tfLeBmhj1u-dRFRs_8GwSoA/edit#gid=0"",""Gestores Escolares!D7:m""),9,0),""VERIFICAR CÓD SEC"")"),"") | R46: =IFERROR(__xludf.DUMMYFUNCTION("IFERROR(VLOOKUP(D46, IMPORTRANGE(""https://docs.google.com/spreadsheets/d/1MjHtlUikwobi2MaWJgy7tfLeBmhj1u-dRFRs_8GwSoA/edit#gid=0"",""Gestores Escolares!D7:m""),10,0),""VERIFICAR CÓD SEC"")"),"") | T46: 1 | U46: 2 | V46: 0 | W46: 0 | X46: 0 | Y46: 0 | Z46: =SUM(V46:Y46) -> 0 | AA46: 0 | AB46: 0 | AC46: 0 | AD46: 0 | AE46: =SUM(AA46:AD46) -> 0 | AF46: 6 | AG46: 5 | AH46: 3 | AI46: 0 | AJ46: =SUM(AF46:AI46) -> 14 | AK46: 0 | AL46: 0 | AM46: 0 | AN46: =SUM(AK46:AM46) -> 0 | AO46: 0 | AP46: 0 | AQ46: 0 | AR46: =SUM(AO46:AQ46) -> 0 | AS46: 0 | AT46: 0 | AU46: 0 | AV46: 0 | AW46: =SUM(AS46:AV46) -> 0 | AX46: =SUM(AY46:AZ46) -> 14 | AY46: =SUM(AV46,AT46,AS46,AP46,AO46,AL46,AK46,AI46,AG46,AF46,AD46,AB46,AA46,Y46,W46,V46) -> 11 | AZ46: =SUM(AU46,AQ46,AM46,AH46,AC46,X46) -> 3 | BA46: 0 | BB46: =SUM(AX46+BA46) -> 14 | BC46: ASSENTAMENTO | BD46: CEMIT | BE46: A DEFINIR | BF46: Anexo - Alunos serão matriculados | BG46: 1179146 | BI46: 2 | BJ46: PADRÃO ANTIGO | BK46: =Y46+AD46+AI46+AV46 -> 0 | BL46: =V46+W46+AA46+AB46+AF46+AG46+AK46+AL46+AO46+AP46+AS46+AT46 -> 11 | BM46: =IFERROR(__xludf.DUMMYFUNCTION("IFERROR(VLOOKUP(BG46,IMPORTRANGE(""https://docs.google.com/spreadsheets/d/1juPI-Fb8LD0YtltB2mlGEnp_R3UVu1t3wSFPzgCyHXE/edit?gid=0#gid=0"",""GERAL!A2:C""),3,0),""-"")"),"ASSENTAMENTOS") -> ASSENTAMENTOS
A47: NTE 01 - IRECÊ | B47: JOAO DOURADO | C47: ESCOLA | D47: 1162502 | F47: 29064392 | G47: COLÉGIO ESTADUAL DE TEMPO INTEGRAL IDALINA DA SILVA DOURADO | H47: JOAQUIM AUGUSTO DOURADO - SN(00021) | I47: CENTRO | J47: SEDE | K47: PRÓPRIO | L47: GRANDE | M47: =IFERROR(__xludf.DUMMYFUNCTION("IFERROR(VLOOKUP(D47, IMPORTRANGE(""https://docs.google.com/spreadsheets/d/1MjHtlUikwobi2MaWJgy7tfLeBmhj1u-dRFRs_8GwSoA/edit#gid=0"",""Gestores Escolares!D7:J""),3,0),""VERIFICAR CÓD SEC"")"),"RAQUEL VASCONCELOS DOS SANTOS NETA") -> RAQUEL VASCONCELOS DOS SANTOS NETA | N47: =IFERROR(__xludf.DUMMYFUNCTION("IFERROR(VLOOKUP(D47, IMPORTRANGE(""https://docs.google.com/spreadsheets/d/1MjHtlUikwobi2MaWJgy7tfLeBmhj1u-dRFRs_8GwSoA/edit#gid=0"",""Gestores Escolares!D7:J""),4,0),""VERIFICAR CÓD SEC"")"),"(74) 9 9978-8773") -> (74) 9 9978-8773 | O47: =IFERROR(__xludf.DUMMYFUNCTION("IFERROR(VLOOKUP(D47, IMPORTRANGE(""https://docs.google.com/spreadsheets/d/1MjHtlUikwobi2MaWJgy7tfLeBmhj1u-dRFRs_8GwSoA/edit#gid=0"",""Gestores Escolares!D7:J""),6,0),""VERIFICAR CÓD SEC"")"),"LUCIANE MORAIS ROSENDO DA SILVA") -> LUCIANE MORAIS ROSENDO DA SILVA | P47: =IFERROR(__xludf.DUMMYFUNCTION("IFERROR(VLOOKUP(D47, IMPORTRANGE(""https://docs.google.com/spreadsheets/d/1MjHtlUikwobi2MaWJgy7tfLeBmhj1u-dRFRs_8GwSoA/edit#gid=0"",""Gestores Escolares!D7:J""),7,0),""VERIFICAR CÓD SEC"")"),"(74) 9 9971-8183/ 9 9971-8113") -> (74) 9 9971-8183/ 9 9971-8113 | Q47: =IFERROR(__xludf.DUMMYFUNCTION("IFERROR(VLOOKUP(D47, IMPORTRANGE(""https://docs.google.com/spreadsheets/d/1MjHtlUikwobi2MaWJgy7tfLeBmhj1u-dRFRs_8GwSoA/edit#gid=0"",""Gestores Escolares!D7:m""),9,0),""VERIFICAR CÓD SEC"")"),"DAMARES FERREIRA DE SOUZA LOULA") -> DAMARES FERREIRA DE SOUZA LOULA | R47: =IFERROR(__xludf.DUMMYFUNCTION("IFERROR(VLOOKUP(D47, IMPORTRANGE(""https://docs.google.com/spreadsheets/d/1MjHtlUikwobi2MaWJgy7tfLeBmhj1u-dRFRs_8GwSoA/edit#gid=0"",""Gestores Escolares!D7:m""),10,0),""VERIFICAR CÓD SEC"")"),"(74) 9 9945-4599") -> (74) 9 9945-4599 | T47: 9 | U47: 08 + 02 adapt. | V47: 0 | W47: 0 | X47: 0 | Y47: 0 | Z47: =SUM(V47:Y47) -> 0 | AA47: 0 | AB47: 0 | AC47: 0 | AD47: 0 | AE47: =SUM(AA47:AD47) -> 0 | AF47: 403 | AG47: 293 | AH47: 0 | AI47: 0 | AJ47: =SUM(AF47:AI47) -> 696 | AK47: 0 | AL47: 0 | AM47: 0 | AN47: =SUM(AK47:AM47) -> 0 | AO47: 0 | AP47: 0 | AQ47: 118 | AR47: =SUM(AO47:AQ47) -> 118 | AS47: 0 | AT47: 59 | AU47: 10 | AV47: 0 | AW47: =SUM(AS47:AV47) -> 69 | AX47: =SUM(AY47:AZ47) -> 883 | AY47: =SUM(AV47,AT47,AS47,AP47,AO47,AL47,AK47,AI47,AG47,AF47,AD47,AB47,AA47,Y47,W47,V47) -> 755 | AZ47: =SUM(AU47,AQ47,AM47,AH47,AC47,X47) -> 128 | BA47: 0 | BB47: =SUM(AX47+BA47) -> 883 | BC47: A DEFINIR | BD47: A DEFINIR | BE47: A DEFINIR | BG47: 1162502 | BH47: -11.343506453429942, -41.65595640872485 | BI47: 8 | BJ47: NOVO PADRÃO (MODERNIZAÇÃO) | BK47: =Y47+AD47+AI47+AV47 -> 0 | BL47: =V47+W47+AA47+AB47+AF47+AG47+AK47+AL47+AO47+AP47+AS47+AT47 -> 755 | BM47: =IFERROR(__xludf.DUMMYFUNCTION("IFERROR(VLOOKUP(BG47,IMPORTRANGE(""https://docs.google.com/spreadsheets/d/1juPI-Fb8LD0YtltB2mlGEnp_R3UVu1t3wSFPzgCyHXE/edit?gid=0#gid=0"",""GERAL!A2:C""),3,0),""-"")"),"-") -> -
A48: NTE 01 - IRECÊ | B48: JOAO DOURADO | C48: ANEXO | D48: 1179281 | E48: 1179345 | F48: 29459141 | G48: ANEXO - CEMIT - IRECÊ - POVOADO CALDEIRÃO DO JACO | H48: RUA DIVINO ESPIRITO SANTO - SN(00003) | I48: POVOADO CALDEIRÃO DO JACO | J48: 9KM | K48: CEDIDO | L48: PEQUENO | M48: =IFERROR(__xludf.DUMMYFUNCTION("IFERROR(VLOOKUP(D48, IMPORTRANGE(""https://docs.google.com/spreadsheets/d/1MjHtlUikwobi2MaWJgy7tfLeBmhj1u-dRFRs_8GwSoA/edit#gid=0"",""Gestores Escolares!D7:J""),3,0),""VERIFICAR CÓD SEC"")"),"MARCOS PAULO DA SILVA ALMEIDA") -> MARCOS PAULO DA SILVA ALMEIDA | N48: =IFERROR(__xludf.DUMMYFUNCTION("IFERROR(VLOOKUP(D48, IMPORTRANGE(""https://docs.google.com/spreadsheets/d/1MjHtlUikwobi2MaWJgy7tfLeBmhj1u-dRFRs_8GwSoA/edit#gid=0"",""Gestores Escolares!D7:J""),4,0),""VERIFICAR CÓD SEC"")"),"(74) 9 9998-8112") -> (74) 9 9998-8112 | O48: =IFERROR(__xludf.DUMMYFUNCTION("IFERROR(VLOOKUP(D48, IMPORTRANGE(""https://docs.google.com/spreadsheets/d/1MjHtlUikwobi2MaWJgy7tfLeBmhj1u-dRFRs_8GwSoA/edit#gid=0"",""Gestores Escolares!D7:J""),6,0),""VERIFICAR CÓD SEC"")"),"FERNANDA MIRANDA CAMPOS") -> FERNANDA MIRANDA CAMPOS | P48: =IFERROR(__xludf.DUMMYFUNCTION("IFERROR(VLOOKUP(D48, IMPORTRANGE(""https://docs.google.com/spreadsheets/d/1MjHtlUikwobi2MaWJgy7tfLeBmhj1u-dRFRs_8GwSoA/edit#gid=0"",""Gestores Escolares!D7:J""),7,0),""VERIFICAR CÓD SEC"")"),"(74) 9 9963-4717") -> (74) 9 9963-4717 | Q48: =IFERROR(__xludf.DUMMYFUNCTION("IFERROR(VLOOKUP(D48, IMPORTRANGE(""https://docs.google.com/spreadsheets/d/1MjHtlUikwobi2MaWJgy7tfLeBmhj1u-dRFRs_8GwSoA/edit#gid=0"",""Gestores Escolares!D7:m""),9,0),""VERIFICAR CÓD SEC"")"),"") | R48: =IFERROR(__xludf.DUMMYFUNCTION("IFERROR(VLOOKUP(D48, IMPORTRANGE(""https://docs.google.com/spreadsheets/d/1MjHtlUikwobi2MaWJgy7tfLeBmhj1u-dRFRs_8GwSoA/edit#gid=0"",""Gestores Escolares!D7:m""),10,0),""VERIFICAR CÓD SEC"")"),"") | T48: 2 | U48: 2 | V48: 0 | W48: 0 | X48: 0 | Y48: 0 | Z48: =SUM(V48:Y48) -> 0 | AA48: 0 | AB48: 0 | AC48: 0 | AD48: 0 | AE48: =SUM(AA48:AD48) -> 0 | AF48: 0 | AG48: 0 | AH48: 47 | AI48: 0 | AJ48: =SUM(AF48:AI48) -> 47 | AK48: 0 | AL48: 0 | AM48: 0 | AN48: =SUM(AK48:AM48) -> 0 | AO48: 0 | AP48: 0 | AQ48: 0 | AR48: =SUM(AO48:AQ48) -> 0 | AS48: 0 | AT48: 0 | AU48: 0 | AV48: 0 | AW48: =SUM(AS48:AV48) -> 0 | AX48: =SUM(AY48:AZ48) -> 47 | AY48: =SUM(AV48,AT48,AS48,AP48,AO48,AL48,AK48,AI48,AG48,AF48,AD48,AB48,AA48,Y48,W48,V48) -> 0 | AZ48: =SUM(AU48,AQ48,AM48,AH48,AC48,X48) -> 47 | BA48: 0 | BB48: =SUM(AX48+BA48) -> 47 | BC48: A DEFINIR | BD48: CEMIT | BE48: PROFISSIONAL | BG48: 1179345 | BI48: 2 | BJ48: PADRÃO ANTIGO | BK48: =Y48+AD48+AI48+AV48 -> 0 | BL48: =V48+W48+AA48+AB48+AF48+AG48+AK48+AL48+AO48+AP48+AS48+AT48 -> 0 | BM48: =IFERROR(__xludf.DUMMYFUNCTION("IFERROR(VLOOKUP(BG48,IMPORTRANGE(""https://docs.google.com/spreadsheets/d/1juPI-Fb8LD0YtltB2mlGEnp_R3UVu1t3wSFPzgCyHXE/edit?gid=0#gid=0"",""GERAL!A2:C""),3,0),""-"")"),"-") -> -
A49: NTE 01 - IRECÊ | B49: JOAO DOURADO | C49: ANEXO | D49: 1179281 | E49: 1178802 | F49: 29459141 | G49: ANEXO - CEMIT - IRECÊ - DISTRITO RIACHO DE JOÃO DOURADO | H49: DISTRITO DE RIACHO DE JOAO DOURADO - SN(00005) | I49: CENTRO | J49: 42KM | K49: CEDIDO | L49: PEQUENO | M49: =IFERROR(__xludf.DUMMYFUNCTION("IFERROR(VLOOKUP(D49, IMPORTRANGE(""https://docs.google.com/spreadsheets/d/1MjHtlUikwobi2MaWJgy7tfLeBmhj1u-dRFRs_8GwSoA/edit#gid=0"",""Gestores Escolares!D7:J""),3,0),""VERIFICAR CÓD SEC"")"),"MARCOS PAULO DA SILVA ALMEIDA") -> MARCOS PAULO DA SILVA ALMEIDA | N49: =IFERROR(__xludf.DUMMYFUNCTION("IFERROR(VLOOKUP(D49, IMPORTRANGE(""https://docs.google.com/spreadsheets/d/1MjHtlUikwobi2MaWJgy7tfLeBmhj1u-dRFRs_8GwSoA/edit#gid=0"",""Gestores Escolares!D7:J""),4,0),""VERIFICAR CÓD SEC"")"),"(74) 9 9998-8112") -> (74) 9 9998-8112 | O49: =IFERROR(__xludf.DUMMYFUNCTION("IFERROR(VLOOKUP(D49, IMPORTRANGE(""https://docs.google.com/spreadsheets/d/1MjHtlUikwobi2MaWJgy7tfLeBmhj1u-dRFRs_8GwSoA/edit#gid=0"",""Gestores Escolares!D7:J""),6,0),""VERIFICAR CÓD SEC"")"),"FERNANDA MIRANDA CAMPOS") -> FERNANDA MIRANDA CAMPOS | P49: =IFERROR(__xludf.DUMMYFUNCTION("IFERROR(VLOOKUP(D49, IMPORTRANGE(""https://docs.google.com/spreadsheets/d/1MjHtlUikwobi2MaWJgy7tfLeBmhj1u-dRFRs_8GwSoA/edit#gid=0"",""Gestores Escolares!D7:J""),7,0),""VERIFICAR CÓD SEC"")"),"(74) 9 9963-4717") -> (74) 9 9963-4717 | Q49: =IFERROR(__xludf.DUMMYFUNCTION("IFERROR(VLOOKUP(D49, IMPORTRANGE(""https://docs.google.com/spreadsheets/d/1MjHtlUikwobi2MaWJgy7tfLeBmhj1u-dRFRs_8GwSoA/edit#gid=0"",""Gestores Escolares!D7:m""),9,0),""VERIFICAR CÓD SEC"")"),"") | R49: =IFERROR(__xludf.DUMMYFUNCTION("IFERROR(VLOOKUP(D49, IMPORTRANGE(""https://docs.google.com/spreadsheets/d/1MjHtlUikwobi2MaWJgy7tfLeBmhj1u-dRFRs_8GwSoA/edit#gid=0"",""Gestores Escolares!D7:m""),10,0),""VERIFICAR CÓD SEC"")"),"") | T49: 3 | U49: 3 | V49: 0 | W49: 0 | X49: 0 | Y49: 0 | Z49: =SUM(V49:Y49) -> 0 | AA49: 0 | AB49: 0 | AC49: 0 | AD49: 0 | AE49: =SUM(AA49:AD49) -> 0 | AF49: 0 | AG49: 0 | AH49: 48 | AI49: 0 | AJ49: =SUM(AF49:AI49) -> 48 | AK49: 0 | AL49: 0 | AM49: 0 | AN49: =SUM(AK49:AM49) -> 0 | AO49: 0 | AP49: 0 | AQ49: 0 | AR49: =SUM(AO49:AQ49) -> 0 | AS49: 0 | AT49: 0 | AU49: 0 | AV49: 0 | AW49: =SUM(AS49:AV49) -> 0 | AX49: =SUM(AY49:AZ49) -> 48 | AY49: =SUM(AV49,AT49,AS49,AP49,AO49,AL49,AK49,AI49,AG49,AF49,AD49,AB49,AA49,Y49,W49,V49) -> 0 | AZ49: =SUM(AU49,AQ49,AM49,AH49,AC49,X49) -> 48 | BA49: 0 | BB49: =SUM(AX49+BA49) -> 48 | BC49: A DEFINIR | BD49: CEMIT | BE49: PROFISSIONAL | BG49: 1178802 | BI49: 3 | BJ49: PADRÃO ANTIGO | BK49: =Y49+AD49+AI49+AV49 -> 0 | BL49: =V49+W49+AA49+AB49+AF49+AG49+AK49+AL49+AO49+AP49+AS49+AT49 -> 0 | BM49: =IFERROR(__xludf.DUMMYFUNCTION("IFERROR(VLOOKUP(BG49,IMPORTRANGE(""https://docs.google.com/spreadsheets/d/1juPI-Fb8LD0YtltB2mlGEnp_R3UVu1t3wSFPzgCyHXE/edit?gid=0#gid=0"",""GERAL!A2:C""),3,0),""-"")"),"-") -> -
A50: NTE 01 - IRECÊ | B50: JOAO DOURADO | C50: ANEXO | D50: 1179281 | E50: 1178801 | F50: 29459141 | G50: ANEXO - CEMIT - IRECÊ - DISTRITO DE MATA DO MILHO - COMUNIDADE QUILOMBOLA | H50: DISTRITO DE MATA DO MILHO - SN(00007) | I50: CENTRO | J50: 43KM | K50: CEDIDO | L50: PEQUENO | M50: =IFERROR(__xludf.DUMMYFUNCTION("IFERROR(VLOOKUP(D50, IMPORTRANGE(""https://docs.google.com/spreadsheets/d/1MjHtlUikwobi2MaWJgy7tfLeBmhj1u-dRFRs_8GwSoA/edit#gid=0"",""Gestores Escolares!D7:J""),3,0),""VERIFICAR CÓD SEC"")"),"MARCOS PAULO DA SILVA ALMEIDA") -> MARCOS PAULO DA SILVA ALMEIDA | N50: =IFERROR(__xludf.DUMMYFUNCTION("IFERROR(VLOOKUP(D50, IMPORTRANGE(""https://docs.google.com/spreadsheets/d/1MjHtlUikwobi2MaWJgy7tfLeBmhj1u-dRFRs_8GwSoA/edit#gid=0"",""Gestores Escolares!D7:J""),4,0),""VERIFICAR CÓD SEC"")"),"(74) 9 9998-8112") -> (74) 9 9998-8112 | O50: =IFERROR(__xludf.DUMMYFUNCTION("IFERROR(VLOOKUP(D50, IMPORTRANGE(""https://docs.google.com/spreadsheets/d/1MjHtlUikwobi2MaWJgy7tfLeBmhj1u-dRFRs_8GwSoA/edit#gid=0"",""Gestores Escolares!D7:J""),6,0),""VERIFICAR CÓD SEC"")"),"FERNANDA MIRANDA CAMPOS") -> FERNANDA MIRANDA CAMPOS | P50: =IFERROR(__xludf.DUMMYFUNCTION("IFERROR(VLOOKUP(D50, IMPORTRANGE(""https://docs.google.com/spreadsheets/d/1MjHtlUikwobi2MaWJgy7tfLeBmhj1u-dRFRs_8GwSoA/edit#gid=0"",""Gestores Escolares!D7:J""),7,0),""VERIFICAR CÓD SEC"")"),"(74) 9 9963-4717") -> (74) 9 9963-4717 | Q50: =IFERROR(__xludf.DUMMYFUNCTION("IFERROR(VLOOKUP(D50, IMPORTRANGE(""https://docs.google.com/spreadsheets/d/1MjHtlUikwobi2MaWJgy7tfLeBmhj1u-dRFRs_8GwSoA/edit#gid=0"",""Gestores Escolares!D7:m""),9,0),""VERIFICAR CÓD SEC"")"),"") | R50: =IFERROR(__xludf.DUMMYFUNCTION("IFERROR(VLOOKUP(D50, IMPORTRANGE(""https://docs.google.com/spreadsheets/d/1MjHtlUikwobi2MaWJgy7tfLeBmhj1u-dRFRs_8GwSoA/edit#gid=0"",""Gestores Escolares!D7:m""),10,0),""VERIFICAR CÓD SEC"")"),"") | T50: 3 | U50: 3 | V50: 0 | W50: 0 | X50: 0 | Y50: 0 | Z50: =SUM(V50:Y50) -> 0 | AA50: 0 | AB50: 0 | AC50: 0 | AD50: 0 | AE50: =SUM(AA50:AD50) -> 0 | AF50: 0 | AG50: 0 | AH50: 21 | AI50: 0 | AJ50: =SUM(AF50:AI50) -> 21 | AK50: 0 | AL50: 0 | AM50: 0 | AN50: =SUM(AK50:AM50) -> 0 | AO50: 0 | AP50: 0 | AQ50: 0 | AR50: =SUM(AO50:AQ50) -> 0 | AS50: 0 | AT50: 0 | AU50: 0 | AV50: 0 | AW50: =SUM(AS50:AV50) -> 0 | AX50: =SUM(AY50:AZ50) -> 21 | AY50: =SUM(AV50,AT50,AS50,AP50,AO50,AL50,AK50,AI50,AG50,AF50,AD50,AB50,AA50,Y50,W50,V50) -> 0 | AZ50: =SUM(AU50,AQ50,AM50,AH50,AC50,X50) -> 21 | BA50: 0 | BB50: =SUM(AX50+BA50) -> 21 | BC50: QUILOMBOLA | BD50: CEMIT | BE50: A DEFINIR | BG50: 1178801 | BI50: 3 | BJ50: PADRÃO ANTIGO | BK50: =Y50+AD50+AI50+AV50 -> 0 | BL50: =V50+W50+AA50+AB50+AF50+AG50+AK50+AL50+AO50+AP50+AS50+AT50 -> 0 | BM50: =IFERROR(__xludf.DUMMYFUNCTION("IFERROR(VLOOKUP(BG50,IMPORTRANGE(""https://docs.google.com/spreadsheets/d/1juPI-Fb8LD0YtltB2mlGEnp_R3UVu1t3wSFPzgCyHXE/edit?gid=0#gid=0"",""GERAL!A2:C""),3,0),""-"")"),"QUILOMBOLAS") -> QUILOMBOLAS
A51: NTE 01 - IRECÊ | B51: JOAO DOURADO | C51: ANEXO | D51: 1179281 | E51: 1178800 | F51: 29459141 | G51: ANEXO - CEMIT - IRECÊ - DISTRITO DE FLORESTA | H51: FLORESTA - SN(00079) | I51: CENTRO | J51: 32,6KM | K51: PRÓPRIO | L51: PEQUENO | M51: =IFERROR(__xludf.DUMMYFUNCTION("IFERROR(VLOOKUP(D51, IMPORTRANGE(""https://docs.google.com/spreadsheets/d/1MjHtlUikwobi2MaWJgy7tfLeBmhj1u-dRFRs_8GwSoA/edit#gid=0"",""Gestores Escolares!D7:J""),3,0),""VERIFICAR CÓD SEC"")"),"MARCOS PAULO DA SILVA ALMEIDA") -> MARCOS PAULO DA SILVA ALMEIDA | N51: =IFERROR(__xludf.DUMMYFUNCTION("IFERROR(VLOOKUP(D51, IMPORTRANGE(""https://docs.google.com/spreadsheets/d/1MjHtlUikwobi2MaWJgy7tfLeBmhj1u-dRFRs_8GwSoA/edit#gid=0"",""Gestores Escolares!D7:J""),4,0),""VERIFICAR CÓD SEC"")"),"(74) 9 9998-8112") -> (74) 9 9998-8112 | O51: =IFERROR(__xludf.DUMMYFUNCTION("IFERROR(VLOOKUP(D51, IMPORTRANGE(""https://docs.google.com/spreadsheets/d/1MjHtlUikwobi2MaWJgy7tfLeBmhj1u-dRFRs_8GwSoA/edit#gid=0"",""Gestores Escolares!D7:J""),6,0),""VERIFICAR CÓD SEC"")"),"FERNANDA MIRANDA CAMPOS") -> FERNANDA MIRANDA CAMPOS | P51: =IFERROR(__xludf.DUMMYFUNCTION("IFERROR(VLOOKUP(D51, IMPORTRANGE(""https://docs.google.com/spreadsheets/d/1MjHtlUikwobi2MaWJgy7tfLeBmhj1u-dRFRs_8GwSoA/edit#gid=0"",""Gestores Escolares!D7:J""),7,0),""VERIFICAR CÓD SEC"")"),"(74) 9 9963-4717") -> (74) 9 9963-4717 | Q51: =IFERROR(__xludf.DUMMYFUNCTION("IFERROR(VLOOKUP(D51, IMPORTRANGE(""https://docs.google.com/spreadsheets/d/1MjHtlUikwobi2MaWJgy7tfLeBmhj1u-dRFRs_8GwSoA/edit#gid=0"",""Gestores Escolares!D7:m""),9,0),""VERIFICAR CÓD SEC"")"),"") | R51: =IFERROR(__xludf.DUMMYFUNCTION("IFERROR(VLOOKUP(D51, IMPORTRANGE(""https://docs.google.com/spreadsheets/d/1MjHtlUikwobi2MaWJgy7tfLeBmhj1u-dRFRs_8GwSoA/edit#gid=0"",""Gestores Escolares!D7:m""),10,0),""VERIFICAR CÓD SEC"")"),"") | T51: 3 | U51: 3 | V51: 0 | W51: 0 | X51: 0 | Y51: 0 | Z51: =SUM(V51:Y51) -> 0 | AA51: 0 | AB51: 0 | AC51: 0 | AD51: 0 | AE51: =SUM(AA51:AD51) -> 0 | AF51: 0 | AG51: 0 | AH51: 11 | AI51: 0 | AJ51: =SUM(AF51:AI51) -> 11 | AK51: 0 | AL51: 0 | AM51: 0 | AN51: =SUM(AK51:AM51) -> 0 | AO51: 0 | AP51: 0 | AQ51: 0 | AR51: =SUM(AO51:AQ51) -> 0 | AS51: 0 | AT51: 0 | AU51: 0 | AV51: 0 | AW51: =SUM(AS51:AV51) -> 0 | AX51: =SUM(AY51:AZ51) -> 11 | AY51: =SUM(AV51,AT51,AS51,AP51,AO51,AL51,AK51,AI51,AG51,AF51,AD51,AB51,AA51,Y51,W51,V51) -> 0 | AZ51: =SUM(AU51,AQ51,AM51,AH51,AC51,X51) -> 11 | BA51: 0 | BB51: =SUM(AX51+BA51) -> 11 | BC51: A DEFINIR | BD51: CEMIT | BE51: PROFISSIONAL | BG51: 1178800 | BI51: 3 | BJ51: PADRÃO ANTIGO | BK51: =Y51+AD51+AI51+AV51 -> 0 | BL51: =V51+W51+AA51+AB51+AF51+AG51+AK51+AL51+AO51+AP51+AS51+AT51 -> 0 | BM51: =IFERROR(__xludf.DUMMYFUNCTION("IFERROR(VLOOKUP(BG51,IMPORTRANGE(""https://docs.google.com/spreadsheets/d/1juPI-Fb8LD0YtltB2mlGEnp_R3UVu1t3wSFPzgCyHXE/edit?gid=0#gid=0"",""GERAL!A2:C""),3,0),""-"")"),"-") -> -
A52: NTE 01 - IRECÊ | B52: JUSSARA | C52: ESCOLA | D52: 1178040 | F52: 29428726 | G52: COLÉGIO ESTADUAL DE TEMPO INTEGRAL PROFESSOR ETEVALDO MARTINIANO DA ROCHA (ANTIGO - COLÉGIO ESTADUAL CAROLINA ALMEIDA LOPES) | H52: RUA JOSÉ DE ANCHIETA - S/N | I52: CENTRO | J52: SEDE | K52: PRÓPRIO | L52: GRANDE | M52: =IFERROR(__xludf.DUMMYFUNCTION("IFERROR(VLOOKUP(D52, IMPORTRANGE(""https://docs.google.com/spreadsheets/d/1MjHtlUikwobi2MaWJgy7tfLeBmhj1u-dRFRs_8GwSoA/edit#gid=0"",""Gestores Escolares!D7:J""),3,0),""VERIFICAR CÓD SEC"")"),"LUCIEL RODRIGUES DA SILVA") -> LUCIEL RODRIGUES DA SILVA | N52: =IFERROR(__xludf.DUMMYFUNCTION("IFERROR(VLOOKUP(D52, IMPORTRANGE(""https://docs.google.com/spreadsheets/d/1MjHtlUikwobi2MaWJgy7tfLeBmhj1u-dRFRs_8GwSoA/edit#gid=0"",""Gestores Escolares!D7:J""),4,0),""VERIFICAR CÓD SEC"")"),"(74) 9 8147-1052") -> (74) 9 8147-1052 | O52: =IFERROR(__xludf.DUMMYFUNCTION("IFERROR(VLOOKUP(D52, IMPORTRANGE(""https://docs.google.com/spreadsheets/d/1MjHtlUikwobi2MaWJgy7tfLeBmhj1u-dRFRs_8GwSoA/edit#gid=0"",""Gestores Escolares!D7:J""),6,0),""VERIFICAR CÓD SEC"")"),"ARTÊNIA RIBEIRO DA MOTA") -> ARTÊNIA RIBEIRO DA MOTA | P52: =IFERROR(__xludf.DUMMYFUNCTION("IFERROR(VLOOKUP(D52, IMPORTRANGE(""https://docs.google.com/spreadsheets/d/1MjHtlUikwobi2MaWJgy7tfLeBmhj1u-dRFRs_8GwSoA/edit#gid=0"",""Gestores Escolares!D7:J""),7,0),""VERIFICAR CÓD SEC"")"),"(74) 9 9997-6753") -> (74) 9 9997-6753 | Q52: =IFERROR(__xludf.DUMMYFUNCTION("IFERROR(VLOOKUP(D52, IMPORTRANGE(""https://docs.google.com/spreadsheets/d/1MjHtlUikwobi2MaWJgy7tfLeBmhj1u-dRFRs_8GwSoA/edit#gid=0"",""Gestores Escolares!D7:m""),9,0),""VERIFICAR CÓD SEC"")"),"FRANCISCO DE SOUZA NUNES NETO") -> FRANCISCO DE SOUZA NUNES NETO | R52: =IFERROR(__xludf.DUMMYFUNCTION("IFERROR(VLOOKUP(D52, IMPORTRANGE(""https://docs.google.com/spreadsheets/d/1MjHtlUikwobi2MaWJgy7tfLeBmhj1u-dRFRs_8GwSoA/edit#gid=0"",""Gestores Escolares!D7:m""),10,0),""VERIFICAR CÓD SEC"")"),"(74) 9 8124-4545") -> (74) 9 8124-4545 | T52: 8 | U52: 17 | V52: 0 | W52: 0 | X52: 0 | Y52: 0 | Z52: =SUM(V52:Y52) -> 0 | AA52: 0 | AB52: 0 | AC52: 0 | AD52: 0 | AE52: =SUM(AA52:AD52) -> 0 | AF52: 0 | AG52: 0 | AH52: 0 | AI52: 476 | AJ52: =SUM(AF52:AI52) -> 476 | AK52: 0 | AL52: 0 | AM52: 0 | AN52: =SUM(AK52:AM52) -> 0 | AO52: 0 | AP52: 0 | AQ52: 56 | AR52: =SUM(AO52:AQ52) -> 56 | AS52: 0 | AT52: 0 | AU52: 0 | AV52: 98 | AW52: =SUM(AS52:AV52) -> 98 | AX52: =SUM(AY52:AZ52) -> 630 | AY52: =SUM(AV52,AT52,AS52,AP52,AO52,AL52,AK52,AI52,AG52,AF52,AD52,AB52,AA52,Y52,W52,V52) -> 574 | AZ52: =SUM(AU52,AQ52,AM52,AH52,AC52,X52) -> 56 | BA52: 0 | BB52: =SUM(AX52+BA52) -> 630 | BC52: A DEFINIR | BD52: A DEFINIR | BE52: A DEFINIR | BG52: 1178040 | BH52: -11.050364545223243, -41.96966928954358 | BI52: 8 | BJ52: NOVO PADRÃO (NOVA ESCOLA) | BK52: =Y52+AD52+AI52+AV52 -> 574 | BL52: =V52+W52+AA52+AB52+AF52+AG52+AK52+AL52+AO52+AP52+AS52+AT52 -> 0 | BM52: =IFERROR(__xludf.DUMMYFUNCTION("IFERROR(VLOOKUP(BG52,IMPORTRANGE(""https://docs.google.com/spreadsheets/d/1juPI-Fb8LD0YtltB2mlGEnp_R3UVu1t3wSFPzgCyHXE/edit?gid=0#gid=0"",""GERAL!A2:C""),3,0),""-"")"),"-") -> -
A53: NTE 01 - IRECÊ | B53: LAPAO | C53: ESCOLA | D53: 1178257 | F53: 29536200 | G53: COLÉGIO ESTADUAL DO CAMPO DE AGUADA NOVA - DISTRITO DE AGUADA NOVA | H53: RUA DO BARRO VERMELHO - S/N | I53: CENTRO | J53: 9KM | K53: PRÓPRIO | L53: PEQUENO | M53: =IFERROR(__xludf.DUMMYFUNCTION("IFERROR(VLOOKUP(D53, IMPORTRANGE(""https://docs.google.com/spreadsheets/d/1MjHtlUikwobi2MaWJgy7tfLeBmhj1u-dRFRs_8GwSoA/edit#gid=0"",""Gestores Escolares!D7:J""),3,0),""VERIFICAR CÓD SEC"")"),"HELDER TORRES DE OLIVEIRA") -> HELDER TORRES DE OLIVEIRA | N53: =IFERROR(__xludf.DUMMYFUNCTION("IFERROR(VLOOKUP(D53, IMPORTRANGE(""https://docs.google.com/spreadsheets/d/1MjHtlUikwobi2MaWJgy7tfLeBmhj1u-dRFRs_8GwSoA/edit#gid=0"",""Gestores Escolares!D7:J""),4,0),""VERIFICAR CÓD SEC"")"),"(74) 9 9985-9402") -> (74) 9 9985-9402 | O53: =IFERROR(__xludf.DUMMYFUNCTION("IFERROR(VLOOKUP(D53, IMPORTRANGE(""https://docs.google.com/spreadsheets/d/1MjHtlUikwobi2MaWJgy7tfLeBmhj1u-dRFRs_8GwSoA/edit#gid=0"",""Gestores Escolares!D7:J""),6,0),""VERIFICAR CÓD SEC"")"),"") | P53: =IFERROR(__xludf.DUMMYFUNCTION("IFERROR(VLOOKUP(D53, IMPORTRANGE(""https://docs.google.com/spreadsheets/d/1MjHtlUikwobi2MaWJgy7tfLeBmhj1u-dRFRs_8GwSoA/edit#gid=0"",""Gestores Escolares!D7:J""),7,0),""VERIFICAR CÓD SEC"")"),"") | Q53: =IFERROR(__xludf.DUMMYFUNCTION("IFERROR(VLOOKUP(D53, IMPORTRANGE(""https://docs.google.com/spreadsheets/d/1MjHtlUikwobi2MaWJgy7tfLeBmhj1u-dRFRs_8GwSoA/edit#gid=0"",""Gestores Escolares!D7:m""),9,0),""VERIFICAR CÓD SEC"")"),"") | R53: =IFERROR(__xludf.DUMMYFUNCTION("IFERROR(VLOOKUP(D53, IMPORTRANGE(""https://docs.google.com/spreadsheets/d/1MjHtlUikwobi2MaWJgy7tfLeBmhj1u-dRFRs_8GwSoA/edit#gid=0"",""Gestores Escolares!D7:m""),10,0),""VERIFICAR CÓD SEC"")"),"") | T53: 8 | U53: 06 + 03 Adapt. | V53: 0 | W53: 0 | X53: 0 | Y53: 0 | Z53: =SUM(V53:Y53) -> 0 | AA53: 0 | AB53: 0 | AC53: 0 | AD53: 0 | AE53: =SUM(AA53:AD53) -> 0 | AF53: 275 | AG53: 0 | AH53: 0 | AI53: 0 | AJ53: =SUM(AF53:AI53) -> 275 | AK53: 0 | AL53: 0 | AM53: 0 | AN53: =SUM(AK53:AM53) -> 0 | AO53: 0 | AP53: 0 | AQ53: 37 | AR53: =SUM(AO53:AQ53) -> 37 | AS53: 0 | AT53: 0 | AU53: 0 | AV53: 0 | AW53: =SUM(AS53:AV53) -> 0 | AX53: =SUM(AY53:AZ53) -> 312 | AY53: =SUM(AV53,AT53,AS53,AP53,AO53,AL53,AK53,AI53,AG53,AF53,AD53,AB53,AA53,Y53,W53,V53) -> 275 | AZ53: =SUM(AU53,AQ53,AM53,AH53,AC53,X53) -> 37 | BA53: 0 | BB53: =SUM(AX53+BA53) -> 312 | BC53: DO CAMPO | BD53: A DEFINIR | BE53: A DEFINIR | BG53: 1178257 | BH53: -11.459584054928188, -41.807448881500136 | BI53: 8 | BJ53: PADRÃO ANTIGO | BK53: =Y53+AD53+AI53+AV53 -> 0 | BL53: =V53+W53+AA53+AB53+AF53+AG53+AK53+AL53+AO53+AP53+AS53+AT53 -> 275 | BM53: =IFERROR(__xludf.DUMMYFUNCTION("IFERROR(VLOOKUP(BG53,IMPORTRANGE(""https://docs.google.com/spreadsheets/d/1juPI-Fb8LD0YtltB2mlGEnp_R3UVu1t3wSFPzgCyHXE/edit?gid=0#gid=0"",""GERAL!A2:C""),3,0),""-"")"),"CAMPO") -> CAMPO
A54: NTE 01 - IRECÊ | B54: LAPAO | C54: ESCOLA | D54: 1162480 | F54: 29065356 | G54: COLÉGIO ESTADUAL DE TEMPO INTEGRAL JUSTINIANO DE CASTRO DOURADO | H54: ESTR. IRECE-LAPÃO,S/N | I54: CENTRO | J54: SEDE | K54: PRÓPRIO | L54: ESPECIAL | M54: =IFERROR(__xludf.DUMMYFUNCTION("IFERROR(VLOOKUP(D54, IMPORTRANGE(""https://docs.google.com/spreadsheets/d/1MjHtlUikwobi2MaWJgy7tfLeBmhj1u-dRFRs_8GwSoA/edit#gid=0"",""Gestores Escolares!D7:J""),3,0),""VERIFICAR CÓD SEC"")")," KALINE CASTRO CAMPOS NEVES MORAIS") -> KALINE CASTRO CAMPOS NEVES MORAIS | N54: =IFERROR(__xludf.DUMMYFUNCTION("IFERROR(VLOOKUP(D54, IMPORTRANGE(""https://docs.google.com/spreadsheets/d/1MjHtlUikwobi2MaWJgy7tfLeBmhj1u-dRFRs_8GwSoA/edit#gid=0"",""Gestores Escolares!D7:J""),4,0),""VERIFICAR CÓD SEC"")"),"(74) 9 9978-4377") -> (74) 9 9978-4377 | O54: =IFERROR(__xludf.DUMMYFUNCTION("IFERROR(VLOOKUP(D54, IMPORTRANGE(""https://docs.google.com/spreadsheets/d/1MjHtlUikwobi2MaWJgy7tfLeBmhj1u-dRFRs_8GwSoA/edit#gid=0"",""Gestores Escolares!D7:J""),6,0),""VERIFICAR CÓD SEC"")"),"ARIEVANDRO CARDOSO NUNES") -> ARIEVANDRO CARDOSO NUNES | P54: =IFERROR(__xludf.DUMMYFUNCTION("IFERROR(VLOOKUP(D54, IMPORTRANGE(""https://docs.google.com/spreadsheets/d/1MjHtlUikwobi2MaWJgy7tfLeBmhj1u-dRFRs_8GwSoA/edit#gid=0"",""Gestores Escolares!D7:J""),7,0),""VERIFICAR CÓD SEC"")"),"(74) 9 9973-8723") -> (74) 9 9973-8723 | Q54: =IFERROR(__xludf.DUMMYFUNCTION("IFERROR(VLOOKUP(D54, IMPORTRANGE(""https://docs.google.com/spreadsheets/d/1MjHtlUikwobi2MaWJgy7tfLeBmhj1u-dRFRs_8GwSoA/edit#gid=0"",""Gestores Escolares!D7:m""),9,0),""VERIFICAR CÓD SEC"")"),"BRUNO GOMES DE ARAUJO") -> BRUNO GOMES DE ARAUJO | R54: =IFERROR(__xludf.DUMMYFUNCTION("IFERROR(VLOOKUP(D54, IMPORTRANGE(""https://docs.google.com/spreadsheets/d/1MjHtlUikwobi2MaWJgy7tfLeBmhj1u-dRFRs_8GwSoA/edit#gid=0"",""Gestores Escolares!D7:m""),10,0),""VERIFICAR CÓD SEC"")"),"(75) 9 9188-3053") -> (75) 9 9188-3053 | T54: 15 | U54: 24 Salas, sendo 20 como salas de aula e 04 adaptadas: 01 para almoxarifado, 01 sala de artes, 01 sala de atendimento de psicologia e 01 sala de esportes. | V54: 0 | W54: 0 | X54: 0 | Y54: 0 | Z54: =SUM(V54:Y54) -> 0 | AA54: 0 | AB54: 0 | AC54: 0 | AD54: 0 | AE54: =SUM(AA54:AD54) -> 0 | AF54: 54 | AG54: 0 | AH54: 0 | AI54: 438 | AJ54: =SUM(AF54:AI54) -> 492 | AK54: 0 | AL54: 0 | AM54: 0 | AN54: =SUM(AK54:AM54) -> 0 | AO54: 0 | AP54: 0 | AQ54: 68 | AR54: =SUM(AO54:AQ54) -> 68 | AS54: 0 | AT54: 0 | AU54: 18 | AV54: 110 | AW54: =SUM(AS54:AV54) -> 128 | AX54: =SUM(AY54:AZ54) -> 688 | AY54: =SUM(AV54,AT54,AS54,AP54,AO54,AL54,AK54,AI54,AG54,AF54,AD54,AB54,AA54,Y54,W54,V54) -> 602 | AZ54: =SUM(AU54,AQ54,AM54,AH54,AC54,X54) -> 86 | BA54: 0 | BB54: =SUM(AX54+BA54) -> 688 | BC54: A DEFINIR | BD54: A DEFINIR | BE54: A DEFINIR | BG54: 1162480 | BH54: -11.37583292184791, -41.84159439232399 | BI54: 24 | BJ54: NOVO PADRÃO (NOVA ESCOLA) | BK54: =Y54+AD54+AI54+AV54 -> 548 | BL54: =V54+W54+AA54+AB54+AF54+AG54+AK54+AL54+AO54+AP54+AS54+AT54 -> 54 | BM54: =IFERROR(__xludf.DUMMYFUNCTION("IFERROR(VLOOKUP(BG54,IMPORTRANGE(""https://docs.google.com/spreadsheets/d/1juPI-Fb8LD0YtltB2mlGEnp_R3UVu1t3wSFPzgCyHXE/edit?gid=0#gid=0"",""GERAL!A2:C""),3,0),""-"")"),"-") -> -
A55: NTE 01 - IRECÊ | B55: MULUNGU DO MORRO | C55: ESCOLA | D55: 1178146 | F55: 29445400 | G55: COLÉGIO ESTADUAL DE TEMPO INTEGRAL DE MULUNGU DO MORRO | H55: BENEDITO NOGUEIRA - SN(00048) | I55: CENTRO | J55: SEDE | K55: PRÓPRIO | L55: MÉDIO | M55: =IFERROR(__xludf.DUMMYFUNCTION("IFERROR(VLOOKUP(D55, IMPORTRANGE(""https://docs.google.com/spreadsheets/d/1MjHtlUikwobi2MaWJgy7tfLeBmhj1u-dRFRs_8GwSoA/edit#gid=0"",""Gestores Escolares!D7:J""),3,0),""VERIFICAR CÓD SEC"")"),"FABIANA PACHECO ARAUJO") -> FABIANA PACHECO ARAUJO | N55: =IFERROR(__xludf.DUMMYFUNCTION("IFERROR(VLOOKUP(D55, IMPORTRANGE(""https://docs.google.com/spreadsheets/d/1MjHtlUikwobi2MaWJgy7tfLeBmhj1u-dRFRs_8GwSoA/edit#gid=0"",""Gestores Escolares!D7:J""),4,0),""VERIFICAR CÓD SEC"")"),"(63) 9 9137-0469") -> (63) 9 9137-0469 | O55: =IFERROR(__xludf.DUMMYFUNCTION("IFERROR(VLOOKUP(D55, IMPORTRANGE(""https://docs.google.com/spreadsheets/d/1MjHtlUikwobi2MaWJgy7tfLeBmhj1u-dRFRs_8GwSoA/edit#gid=0"",""Gestores Escolares!D7:J""),6,0),""VERIFICAR CÓD SEC"")"),"ADAIR SILVA MACHADO ") -> ADAIR SILVA MACHADO | P55: =IFERROR(__xludf.DUMMYFUNCTION("IFERROR(VLOOKUP(D55, IMPORTRANGE(""https://docs.google.com/spreadsheets/d/1MjHtlUikwobi2MaWJgy7tfLeBmhj1u-dRFRs_8GwSoA/edit#gid=0"",""Gestores Escolares!D7:J""),7,0),""VERIFICAR CÓD SEC"")"),"(75) 9 9228-6198") -> (75) 9 9228-6198 | Q55: =IFERROR(__xludf.DUMMYFUNCTION("IFERROR(VLOOKUP(D55, IMPORTRANGE(""https://docs.google.com/spreadsheets/d/1MjHtlUikwobi2MaWJgy7tfLeBmhj1u-dRFRs_8GwSoA/edit#gid=0"",""Gestores Escolares!D7:m""),9,0),""VERIFICAR CÓD SEC"")"),"") | R55: =IFERROR(__xludf.DUMMYFUNCTION("IFERROR(VLOOKUP(D55, IMPORTRANGE(""https://docs.google.com/spreadsheets/d/1MjHtlUikwobi2MaWJgy7tfLeBmhj1u-dRFRs_8GwSoA/edit#gid=0"",""Gestores Escolares!D7:m""),10,0),""VERIFICAR CÓD SEC"")"),"") | T55: 8 | U55: 6 + 2 (Adapt) | V55: 0 | W55: 0 | X55: 0 | Y55: 0 | Z55: =SUM(V55:Y55) -> 0 | AA55: 0 | AB55: 0 | AC55: 0 | AD55: 0 | AE55: =SUM(AA55:AD55) -> 0 | AF55: 173 | AG55: 177 | AH55: 0 | AI55: 0 | AJ55: =SUM(AF55:AI55) -> 350 | AK55: 0 | AL55: 0 | AM55: 0 | AN55: =SUM(AK55:AM55) -> 0 | AO55: 0 | AP55: 0 | AQ55: 93 | AR55: =SUM(AO55:AQ55) -> 93 | AS55: 83 | AT55: 29 | AU55: 0 | AV55: 0 | AW55: =SUM(AS55:AV55) -> 112 | AX55: =SUM(AY55:AZ55) -> 555 | AY55: =SUM(AV55,AT55,AS55,AP55,AO55,AL55,AK55,AI55,AG55,AF55,AD55,AB55,AA55,Y55,W55,V55) -> 462 | AZ55: =SUM(AU55,AQ55,AM55,AH55,AC55,X55) -> 93 | BA55: 0 | BB55: =SUM(AX55+BA55) -> 555 | BC55: A DEFINIR | BD55: A DEFINIR | BE55: A DEFINIR | BG55: 1178146 | BH55: -11.967223522622936, -41.64585240430931 | BI55: 8 | BJ55: PADRÃO ANTIGO | BK55: =Y55+AD55+AI55+AV55 -> 0 | BL55: =V55+W55+AA55+AB55+AF55+AG55+AK55+AL55+AO55+AP55+AS55+AT55 -> 462 | BM55: =IFERROR(__xludf.DUMMYFUNCTION("IFERROR(VLOOKUP(BG55,IMPORTRANGE(""https://docs.google.com/spreadsheets/d/1juPI-Fb8LD0YtltB2mlGEnp_R3UVu1t3wSFPzgCyHXE/edit?gid=0#gid=0"",""GERAL!A2:C""),3,0),""-"")"),"-") -> -
A56: NTE 01 - IRECÊ | B56: MULUNGU DO MORRO | C56: ANEXO | D56: 1179281 | E56: 1178803 | F56: 29459141 | G56: ANEXO - CEMIT - IRECÊ - DISTRITO DE VÁRZEA DO CERCO | H56: DIST. DE VARZEA DO CERCO - S/N | I56: DISTRITO DE VARZEA DO CERCO | J56: 30KM | K56: CEDIDO | L56: PEQUENO | M56: =IFERROR(__xludf.DUMMYFUNCTION("IFERROR(VLOOKUP(D56, IMPORTRANGE(""https://docs.google.com/spreadsheets/d/1MjHtlUikwobi2MaWJgy7tfLeBmhj1u-dRFRs_8GwSoA/edit#gid=0"",""Gestores Escolares!D7:J""),3,0),""VERIFICAR CÓD SEC"")"),"MARCOS PAULO DA SILVA ALMEIDA") -> MARCOS PAULO DA SILVA ALMEIDA | N56: =IFERROR(__xludf.DUMMYFUNCTION("IFERROR(VLOOKUP(D56, IMPORTRANGE(""https://docs.google.com/spreadsheets/d/1MjHtlUikwobi2MaWJgy7tfLeBmhj1u-dRFRs_8GwSoA/edit#gid=0"",""Gestores Escolares!D7:J""),4,0),""VERIFICAR CÓD SEC"")"),"(74) 9 9998-8112") -> (74) 9 9998-8112 | O56: =IFERROR(__xludf.DUMMYFUNCTION("IFERROR(VLOOKUP(D56, IMPORTRANGE(""https://docs.google.com/spreadsheets/d/1MjHtlUikwobi2MaWJgy7tfLeBmhj1u-dRFRs_8GwSoA/edit#gid=0"",""Gestores Escolares!D7:J""),6,0),""VERIFICAR CÓD SEC"")"),"FERNANDA MIRANDA CAMPOS") -> FERNANDA MIRANDA CAMPOS | P56: =IFERROR(__xludf.DUMMYFUNCTION("IFERROR(VLOOKUP(D56, IMPORTRANGE(""https://docs.google.com/spreadsheets/d/1MjHtlUikwobi2MaWJgy7tfLeBmhj1u-dRFRs_8GwSoA/edit#gid=0"",""Gestores Escolares!D7:J""),7,0),""VERIFICAR CÓD SEC"")"),"(74) 9 9963-4717") -> (74) 9 9963-4717 | Q56: =IFERROR(__xludf.DUMMYFUNCTION("IFERROR(VLOOKUP(D56, IMPORTRANGE(""https://docs.google.com/spreadsheets/d/1MjHtlUikwobi2MaWJgy7tfLeBmhj1u-dRFRs_8GwSoA/edit#gid=0"",""Gestores Escolares!D7:m""),9,0),""VERIFICAR CÓD SEC"")"),"") | R56: =IFERROR(__xludf.DUMMYFUNCTION("IFERROR(VLOOKUP(D56, IMPORTRANGE(""https://docs.google.com/spreadsheets/d/1MjHtlUikwobi2MaWJgy7tfLeBmhj1u-dRFRs_8GwSoA/edit#gid=0"",""Gestores Escolares!D7:m""),10,0),""VERIFICAR CÓD SEC"")"),"") | T56: 3 | U56: 3 | V56: 0 | W56: 0 | X56: 0 | Y56: 0 | Z56: =SUM(V56:Y56) -> 0 | AA56: 0 | AB56: 0 | AC56: 0 | AD56: 0 | AE56: =SUM(AA56:AD56) -> 0 | AF56: 0 | AG56: 0 | AH56: 63 | AI56: 0 | AJ56: =SUM(AF56:AI56) -> 63 | AK56: 0 | AL56: 0 | AM56: 0 | AN56: =SUM(AK56:AM56) -> 0 | AO56: 0 | AP56: 0 | AQ56: 0 | AR56: =SUM(AO56:AQ56) -> 0 | AS56: 0 | AT56: 0 | AU56: 0 | AV56: 0 | AW56: =SUM(AS56:AV56) -> 0 | AX56: =SUM(AY56:AZ56) -> 63 | AY56: =SUM(AV56,AT56,AS56,AP56,AO56,AL56,AK56,AI56,AG56,AF56,AD56,AB56,AA56,Y56,W56,V56) -> 0 | AZ56: =SUM(AU56,AQ56,AM56,AH56,AC56,X56) -> 63 | BA56: 0 | BB56: =SUM(AX56+BA56) -> 63 | BC56: A DEFINIR | BD56: CEMIT | BE56: PROFISSIONAL | BG56: 1178803 | BI56: 3 | BJ56: PADRÃO ANTIGO | BK56: =Y56+AD56+AI56+AV56 -> 0 | BL56: =V56+W56+AA56+AB56+AF56+AG56+AK56+AL56+AO56+AP56+AS56+AT56 -> 0 | BM56: =IFERROR(__xludf.DUMMYFUNCTION("IFERROR(VLOOKUP(BG56,IMPORTRANGE(""https://docs.google.com/spreadsheets/d/1juPI-Fb8LD0YtltB2mlGEnp_R3UVu1t3wSFPzgCyHXE/edit?gid=0#gid=0"",""GERAL!A2:C""),3,0),""-"")"),"-") -> -
A57: NTE 01 - IRECÊ | B57: PRESIDENTE DUTRA | C57: ESCOLA | D57: 1127154 | F57: 29066395 | G57: COLÉGIO ESTADUAL DE TEMPO INTEGRAL LEILA JANAINA BRITO GONÇALVES (ANTIGO C.E DOUTOR ANTONIO CARLOS MAGALHAES) | H57: RUA PROJETADA, S/N 44.930-000 CENTRO | I57: CENTRO | J57: SEDE | K57: PRÓPRIO | L57: ESPECIAL | M57: =IFERROR(__xludf.DUMMYFUNCTION("IFERROR(VLOOKUP(D57, IMPORTRANGE(""https://docs.google.com/spreadsheets/d/1MjHtlUikwobi2MaWJgy7tfLeBmhj1u-dRFRs_8GwSoA/edit#gid=0"",""Gestores Escolares!D7:J""),3,0),""VERIFICAR CÓD SEC"")"),"INDIRA NEIVA SOUZA") -> INDIRA NEIVA SOUZA | N57: =IFERROR(__xludf.DUMMYFUNCTION("IFERROR(VLOOKUP(D57, IMPORTRANGE(""https://docs.google.com/spreadsheets/d/1MjHtlUikwobi2MaWJgy7tfLeBmhj1u-dRFRs_8GwSoA/edit#gid=0"",""Gestores Escolares!D7:J""),4,0),""VERIFICAR CÓD SEC"")"),"(74) 9 9998-1299") -> (74) 9 9998-1299 | O57: =IFERROR(__xludf.DUMMYFUNCTION("IFERROR(VLOOKUP(D57, IMPORTRANGE(""https://docs.google.com/spreadsheets/d/1MjHtlUikwobi2MaWJgy7tfLeBmhj1u-dRFRs_8GwSoA/edit#gid=0"",""Gestores Escolares!D7:J""),6,0),""VERIFICAR CÓD SEC"")"),"NEUZETE GONÇALVES MACHADO") -> NEUZETE GONÇALVES MACHADO | P57: =IFERROR(__xludf.DUMMYFUNCTION("IFERROR(VLOOKUP(D57, IMPORTRANGE(""https://docs.google.com/spreadsheets/d/1MjHtlUikwobi2MaWJgy7tfLeBmhj1u-dRFRs_8GwSoA/edit#gid=0"",""Gestores Escolares!D7:J""),7,0),""VERIFICAR CÓD SEC"")"),"(74) 9 8822-4448") -> (74) 9 8822-4448 | Q57: =IFERROR(__xludf.DUMMYFUNCTION("IFERROR(VLOOKUP(D57, IMPORTRANGE(""https://docs.google.com/spreadsheets/d/1MjHtlUikwobi2MaWJgy7tfLeBmhj1u-dRFRs_8GwSoA/edit#gid=0"",""Gestores Escolares!D7:m""),9,0),""VERIFICAR CÓD SEC"")"),"MAGALI CARVALHO DE SOUZA") -> MAGALI CARVALHO DE SOUZA | R57: =IFERROR(__xludf.DUMMYFUNCTION("IFERROR(VLOOKUP(D57, IMPORTRANGE(""https://docs.google.com/spreadsheets/d/1MjHtlUikwobi2MaWJgy7tfLeBmhj1u-dRFRs_8GwSoA/edit#gid=0"",""Gestores Escolares!D7:m""),10,0),""VERIFICAR CÓD SEC"")"),"(74) 9 8128-5683") -> (74) 9 8128-5683 | T57: 8 | U57: 10 | V57: 0 | W57: 0 | X57: 0 | Y57: 0 | Z57: =SUM(V57:Y57) -> 0 | AA57: 0 | AB57: 0 | AC57: 0 | AD57: 0 | AE57: =SUM(AA57:AD57) -> 0 | AF57: 0 | AG57: 0 | AH57: 0 | AI57: 316 | AJ57: =SUM(AF57:AI57) -> 316 | AK57: 0 | AL57: 0 | AM57: 0 | AN57: =SUM(AK57:AM57) -> 0 | AO57: 0 | AP57: 0 | AQ57: 78 | AR57: =SUM(AO57:AQ57) -> 78 | AS57: 0 | AT57: 0 | AU57: 33 | AV57: 62 | AW57: =SUM(AS57:AV57) -> 95 | AX57: =SUM(AY57:AZ57) -> 489 | AY57: =SUM(AV57,AT57,AS57,AP57,AO57,AL57,AK57,AI57,AG57,AF57,AD57,AB57,AA57,Y57,W57,V57) -> 378 | AZ57: =SUM(AU57,AQ57,AM57,AH57,AC57,X57) -> 111 | BA57: 0 | BB57: =SUM(AX57+BA57) -> 489 | BC57: A DEFINIR | BD57: A DEFINIR | BE57: A DEFINIR | BG57: 1127154 | BH57: -11.29115446805411, -41.993385086993364 | BI57: 10 | BJ57: NOVO PADRÃO (NOVA ESCOLA) | BK57: =Y57+AD57+AI57+AV57 -> 378 | BL57: =V57+W57+AA57+AB57+AF57+AG57+AK57+AL57+AO57+AP57+AS57+AT57 -> 0 | BM57: =IFERROR(__xludf.DUMMYFUNCTION("IFERROR(VLOOKUP(BG57,IMPORTRANGE(""https://docs.google.com/spreadsheets/d/1juPI-Fb8LD0YtltB2mlGEnp_R3UVu1t3wSFPzgCyHXE/edit?gid=0#gid=0"",""GERAL!A2:C""),3,0),""-"")"),"-") -> -
A58: NTE 01 - IRECÊ | B58: SAO GABRIEL | C58: ESCOLA | D58: 1162618 | F58: 29067332 | G58: COLÉGIO ESTADUAL DE TEMPO INTEGRAL PROFESSORA ROSÁLIA PEREIRA DA ROCHA | H58: JOÃO DURVAL - 127 | I58: CENTRO | J58: SEDE | K58: PRÓPRIO | L58: GRANDE | M58: =IFERROR(__xludf.DUMMYFUNCTION("IFERROR(VLOOKUP(D58, IMPORTRANGE(""https://docs.google.com/spreadsheets/d/1MjHtlUikwobi2MaWJgy7tfLeBmhj1u-dRFRs_8GwSoA/edit#gid=0"",""Gestores Escolares!D7:J""),3,0),""VERIFICAR CÓD SEC"")"),"CECILIA MACHADO DE OLIVEIRA") -> CECILIA MACHADO DE OLIVEIRA | N58: =IFERROR(__xludf.DUMMYFUNCTION("IFERROR(VLOOKUP(D58, IMPORTRANGE(""https://docs.google.com/spreadsheets/d/1MjHtlUikwobi2MaWJgy7tfLeBmhj1u-dRFRs_8GwSoA/edit#gid=0"",""Gestores Escolares!D7:J""),4,0),""VERIFICAR CÓD SEC"")"),"(74) 9 9937-8438") -> (74) 9 9937-8438 | O58: =IFERROR(__xludf.DUMMYFUNCTION("IFERROR(VLOOKUP(D58, IMPORTRANGE(""https://docs.google.com/spreadsheets/d/1MjHtlUikwobi2MaWJgy7tfLeBmhj1u-dRFRs_8GwSoA/edit#gid=0"",""Gestores Escolares!D7:J""),6,0),""VERIFICAR CÓD SEC"")"),"CARLOS AUGUSTO DOURADO MOITINHO") -> CARLOS AUGUSTO DOURADO MOITINHO | P58: =IFERROR(__xludf.DUMMYFUNCTION("IFERROR(VLOOKUP(D58, IMPORTRANGE(""https://docs.google.com/spreadsheets/d/1MjHtlUikwobi2MaWJgy7tfLeBmhj1u-dRFRs_8GwSoA/edit#gid=0"",""Gestores Escolares!D7:J""),7,0),""VERIFICAR CÓD SEC"")"),"(74) 9 9927-1323") -> (74) 9 9927-1323 | Q58: =IFERROR(__xludf.DUMMYFUNCTION("IFERROR(VLOOKUP(D58, IMPORTRANGE(""https://docs.google.com/spreadsheets/d/1MjHtlUikwobi2MaWJgy7tfLeBmhj1u-dRFRs_8GwSoA/edit#gid=0"",""Gestores Escolares!D7:m""),9,0),""VERIFICAR CÓD SEC"")"),"MARILVA BATISTA CAVALCANTE") -> MARILVA BATISTA CAVALCANTE | R58: =IFERROR(__xludf.DUMMYFUNCTION("IFERROR(VLOOKUP(D58, IMPORTRANGE(""https://docs.google.com/spreadsheets/d/1MjHtlUikwobi2MaWJgy7tfLeBmhj1u-dRFRs_8GwSoA/edit#gid=0"",""Gestores Escolares!D7:m""),10,0),""VERIFICAR CÓD SEC"")"),"(74) 9 9934-9647") -> (74) 9 9934-9647 | T58: 9 | U58: 12 salas, sendo 09 salas de aula, 02 para multifuncional, 01 para sala de oficinas, 01 para sala de professores. | V58: 0 | W58: 0 | X58: 0 | Y58: 0 | Z58: =SUM(V58:Y58) -> 0 | AA58: 0 | AB58: 0 | AC58: 0 | AD58: 0 | AE58: =SUM(AA58:AD58) -> 0 | AF58: 0 | AG58: 0 | AH58: 0 | AI58: 157 | AJ58: =SUM(AF58:AI58) -> 157 | AK58: 0 | AL58: 0 | AM58: 0 | AN58: =SUM(AK58:AM58) -> 0 | AO58: 0 | AP58: 0 | AQ58: 85 | AR58: =SUM(AO58:AQ58) -> 85 | AS58: 0 | AT58: 0 | AU58: 74 | AV58: 122 | AW58: =SUM(AS58:AV58) -> 196 | AX58: =SUM(AY58:AZ58) -> 438 | AY58: =SUM(AV58,AT58,AS58,AP58,AO58,AL58,AK58,AI58,AG58,AF58,AD58,AB58,AA58,Y58,W58,V58) -> 279 | AZ58: =SUM(AU58,AQ58,AM58,AH58,AC58,X58) -> 159 | BA58: 0 | BB58: =SUM(AX58+BA58) -> 438 | BC58: A DEFINIR | BD58: A DEFINIR | BE58: A DEFINIR | BG58: 1162618 | BH58: -11.231179604058674, -41.8789779928961 | BI58: 6 | BJ58: NOVO PADRÃO (AMPLIAÇÃO COM MODERNIZAÇÃO) | BK58: =Y58+AD58+AI58+AV58 -> 279 | BL58: =V58+W58+AA58+AB58+AF58+AG58+AK58+AL58+AO58+AP58+AS58+AT58 -> 0 | BM58: =IFERROR(__xludf.DUMMYFUNCTION("IFERROR(VLOOKUP(BG58,IMPORTRANGE(""https://docs.google.com/spreadsheets/d/1juPI-Fb8LD0YtltB2mlGEnp_R3UVu1t3wSFPzgCyHXE/edit?gid=0#gid=0"",""GERAL!A2:C""),3,0),""-"")"),"-") -> -
A59: NTE 01 - IRECÊ | B59: SAO GABRIEL | C59: ESCOLA | D59: 1179655 | F59: 29473365 | G59: COLÉGIO ESTADUAL ALMERINDA ALMEIDA - DISTRITO DE GAMELEIRA DO JACARÉ | H59: TRAVESSA DUQUE DE CAXIAS - 01 | I59: CENTRO | J59: 35KM | K59: PRÓPRIO | L59: PEQUENO | M59: =IFERROR(__xludf.DUMMYFUNCTION("IFERROR(VLOOKUP(D59, IMPORTRANGE(""https://docs.google.com/spreadsheets/d/1MjHtlUikwobi2MaWJgy7tfLeBmhj1u-dRFRs_8GwSoA/edit#gid=0"",""Gestores Escolares!D7:J""),3,0),""VERIFICAR CÓD SEC"")"),"HUGO MACHADO HONORATO SOUSA") -> HUGO MACHADO HONORATO SOUSA | N59: =IFERROR(__xludf.DUMMYFUNCTION("IFERROR(VLOOKUP(D59, IMPORTRANGE(""https://docs.google.com/spreadsheets/d/1MjHtlUikwobi2MaWJgy7tfLeBmhj1u-dRFRs_8GwSoA/edit#gid=0"",""Gestores Escolares!D7:J""),4,0),""VERIFICAR CÓD SEC"")"),"(74) 9 8130-7150") -> (74) 9 8130-7150 | O59: =IFERROR(__xludf.DUMMYFUNCTION("IFERROR(VLOOKUP(D59, IMPORTRANGE(""https://docs.google.com/spreadsheets/d/1MjHtlUikwobi2MaWJgy7tfLeBmhj1u-dRFRs_8GwSoA/edit#gid=0"",""Gestores Escolares!D7:J""),6,0),""VERIFICAR CÓD SEC"")"),"") | P59: =IFERROR(__xludf.DUMMYFUNCTION("IFERROR(VLOOKUP(D59, IMPORTRANGE(""https://docs.google.com/spreadsheets/d/1MjHtlUikwobi2MaWJgy7tfLeBmhj1u-dRFRs_8GwSoA/edit#gid=0"",""Gestores Escolares!D7:J""),7,0),""VERIFICAR CÓD SEC"")"),"") | Q59: =IFERROR(__xludf.DUMMYFUNCTION("IFERROR(VLOOKUP(D59, IMPORTRANGE(""https://docs.google.com/spreadsheets/d/1MjHtlUikwobi2MaWJgy7tfLeBmhj1u-dRFRs_8GwSoA/edit#gid=0"",""Gestores Escolares!D7:m""),9,0),""VERIFICAR CÓD SEC"")"),"") | R59: =IFERROR(__xludf.DUMMYFUNCTION("IFERROR(VLOOKUP(D59, IMPORTRANGE(""https://docs.google.com/spreadsheets/d/1MjHtlUikwobi2MaWJgy7tfLeBmhj1u-dRFRs_8GwSoA/edit#gid=0"",""Gestores Escolares!D7:m""),10,0),""VERIFICAR CÓD SEC"")"),"") | T59: 4 | U59: 4 | V59: 0 | W59: 0 | X59: 0 | Y59: 0 | Z59: =SUM(V59:Y59) -> 0 | AA59: 0 | AB59: 0 | AC59: 0 | AD59: 0 | AE59: =SUM(AA59:AD59) -> 0 | AF59: 125 | AG59: 110 | AH59: 0 | AI59: 0 | AJ59: =SUM(AF59:AI59) -> 235 | AK59: 0 | AL59: 0 | AM59: 0 | AN59: =SUM(AK59:AM59) -> 0 | AO59: 0 | AP59: 0 | AQ59: 40 | AR59: =SUM(AO59:AQ59) -> 40 | AS59: 0 | AT59: 0 | AU59: 0 | AV59: 0 | AW59: =SUM(AS59:AV59) -> 0 | AX59: =SUM(AY59:AZ59) -> 275 | AY59: =SUM(AV59,AT59,AS59,AP59,AO59,AL59,AK59,AI59,AG59,AF59,AD59,AB59,AA59,Y59,W59,V59) -> 235 | AZ59: =SUM(AU59,AQ59,AM59,AH59,AC59,X59) -> 40 | BA59: 0 | BB59: =SUM(AX59+BA59) -> 275 | BC59: DO CAMPO | BD59: A DEFINIR | BE59: A DEFINIR | BG59: 1179655 | BH59: -11.225375962960939, -41.86878029942797 | BI59: 4 | BJ59: PADRÃO ANTIGO | BK59: =Y59+AD59+AI59+AV59 -> 0 | BL59: =V59+W59+AA59+AB59+AF59+AG59+AK59+AL59+AO59+AP59+AS59+AT59 -> 235 | BM59: =IFERROR(__xludf.DUMMYFUNCTION("IFERROR(VLOOKUP(BG59,IMPORTRANGE(""https://docs.google.com/spreadsheets/d/1juPI-Fb8LD0YtltB2mlGEnp_R3UVu1t3wSFPzgCyHXE/edit?gid=0#gid=0"",""GERAL!A2:C""),3,0),""-"")"),"CAMPO") -> CAMPO
A60: NTE 01 - IRECÊ | B60: UIBAI | C60: ESCOLA | D60: 1178038 | F60: 29425328 | G60: COLÉGIO ESTADUAL MANOEL LEVI - TEMPO INTEGRAL | H60: RUA ABILIO MACHADO - S/N | I60: CENTRO | J60: SEDE | K60: PRÓPRIO | L60: GRANDE | M60: =IFERROR(__xludf.DUMMYFUNCTION("IFERROR(VLOOKUP(D60, IMPORTRANGE(""https://docs.google.com/spreadsheets/d/1MjHtlUikwobi2MaWJgy7tfLeBmhj1u-dRFRs_8GwSoA/edit#gid=0"",""Gestores Escolares!D7:J""),3,0),""VERIFICAR CÓD SEC"")"),"NATÉRCIA SILVA MATOS") -> NATÉRCIA SILVA MATOS | N60: =IFERROR(__xludf.DUMMYFUNCTION("IFERROR(VLOOKUP(D60, IMPORTRANGE(""https://docs.google.com/spreadsheets/d/1MjHtlUikwobi2MaWJgy7tfLeBmhj1u-dRFRs_8GwSoA/edit#gid=0"",""Gestores Escolares!D7:J""),4,0),""VERIFICAR CÓD SEC"")"),"(74) 9 9909-8948") -> (74) 9 9909-8948 | O60: =IFERROR(__xludf.DUMMYFUNCTION("IFERROR(VLOOKUP(D60, IMPORTRANGE(""https://docs.google.com/spreadsheets/d/1MjHtlUikwobi2MaWJgy7tfLeBmhj1u-dRFRs_8GwSoA/edit#gid=0"",""Gestores Escolares!D7:J""),6,0),""VERIFICAR CÓD SEC"")"),"JARIETE MACHADO") -> JARIETE MACHADO | P60: =IFERROR(__xludf.DUMMYFUNCTION("IFERROR(VLOOKUP(D60, IMPORTRANGE(""https://docs.google.com/spreadsheets/d/1MjHtlUikwobi2MaWJgy7tfLeBmhj1u-dRFRs_8GwSoA/edit#gid=0"",""Gestores Escolares!D7:J""),7,0),""VERIFICAR CÓD SEC"")"),"(74) 9 8808-0273") -> (74) 9 8808-0273 | Q60: =IFERROR(__xludf.DUMMYFUNCTION("IFERROR(VLOOKUP(D60, IMPORTRANGE(""https://docs.google.com/spreadsheets/d/1MjHtlUikwobi2MaWJgy7tfLeBmhj1u-dRFRs_8GwSoA/edit#gid=0"",""Gestores Escolares!D7:m""),9,0),""VERIFICAR CÓD SEC"")"),"VALDINEA MENDES LEVI") -> VALDINEA MENDES LEVI | R60: =IFERROR(__xludf.DUMMYFUNCTION("IFERROR(VLOOKUP(D60, IMPORTRANGE(""https://docs.google.com/spreadsheets/d/1MjHtlUikwobi2MaWJgy7tfLeBmhj1u-dRFRs_8GwSoA/edit#gid=0"",""Gestores Escolares!D7:m""),10,0),""VERIFICAR CÓD SEC"")"),"(74) 9 8828-6024") -> (74) 9 8828-6024 | T60: 12 | U60: 14 salas, sendo 12 salas de aula e 02 adaptadas para sala de vídeo. | V60: 0 | W60: 0 | X60: 0 | Y60: 0 | Z60: =SUM(V60:Y60) -> 0 | AA60: 0 | AB60: 0 | AC60: 0 | AD60: 0 | AE60: =SUM(AA60:AD60) -> 0 | AF60: 0 | AG60: 39 | AH60: 0 | AI60: 284 | AJ60: =SUM(AF60:AI60) -> 323 | AK60: 0 | AL60: 0 | AM60: 0 | AN60: =SUM(AK60:AM60) -> 0 | AO60: 0 | AP60: 0 | AQ60: 38 | AR60: =SUM(AO60:AQ60) -> 38 | AS60: 0 | AT60: 0 | AU60: 18 | AV60: 59 | AW60: =SUM(AS60:AV60) -> 77 | AX60: =SUM(AY60:AZ60) -> 438 | AY60: =SUM(AV60,AT60,AS60,AP60,AO60,AL60,AK60,AI60,AG60,AF60,AD60,AB60,AA60,Y60,W60,V60) -> 382 | AZ60: =SUM(AU60,AQ60,AM60,AH60,AC60,X60) -> 56 | BA60: 0 | BB60: =SUM(AX60+BA60) -> 438 | BC60: A DEFINIR | BD60: A DEFINIR | BE60: A DEFINIR | BG60: 1178038 | BH60: -11.335750546103549, -42.13098928417718 | BI60: 14 | BJ60: NOVO PADRÃO (AMPLIAÇÃO COM MODERNIZAÇÃO) | BK60: =Y60+AD60+AI60+AV60 -> 343 | BL60: =V60+W60+AA60+AB60+AF60+AG60+AK60+AL60+AO60+AP60+AS60+AT60 -> 39 | BM60: =IFERROR(__xludf.DUMMYFUNCTION("IFERROR(VLOOKUP(BG60,IMPORTRANGE(""https://docs.google.com/spreadsheets/d/1juPI-Fb8LD0YtltB2mlGEnp_R3UVu1t3wSFPzgCyHXE/edit?gid=0#gid=0"",""GERAL!A2:C""),3,0),""-"")"),"-") -> -
A61: NTE 01 - IRECÊ | B61: XIQUE-XIQUE | C61: ESCOLA | D61: 1176432 | F61: 29395321 | G61: COLÉGIO ESTADUAL PROFESSORA GILDETE DE SOUZA VIANA | H61: ANTIGO AEROPORTO - SN(00097) | I61: CENTRO | J61: SEDE | K61: PRÓPRIO | L61: ESPECIAL | M61: =IFERROR(__xludf.DUMMYFUNCTION("IFERROR(VLOOKUP(D61, IMPORTRANGE(""https://docs.google.com/spreadsheets/d/1MjHtlUikwobi2MaWJgy7tfLeBmhj1u-dRFRs_8GwSoA/edit#gid=0"",""Gestores Escolares!D7:J""),3,0),""VERIFICAR CÓD SEC"")"),"EDINALVA DA CONCEICAO OLIVEIRA") -> EDINALVA DA CONCEICAO OLIVEIRA | N61: =IFERROR(__xludf.DUMMYFUNCTION("IFERROR(VLOOKUP(D61, IMPORTRANGE(""https://docs.google.com/spreadsheets/d/1MjHtlUikwobi2MaWJgy7tfLeBmhj1u-dRFRs_8GwSoA/edit#gid=0"",""Gestores Escolares!D7:J""),4,0),""VERIFICAR CÓD SEC"")"),"(74) 9 9818-2525") -> (74) 9 9818-2525 | O61: =IFERROR(__xludf.DUMMYFUNCTION("IFERROR(VLOOKUP(D61, IMPORTRANGE(""https://docs.google.com/spreadsheets/d/1MjHtlUikwobi2MaWJgy7tfLeBmhj1u-dRFRs_8GwSoA/edit#gid=0"",""Gestores Escolares!D7:J""),6,0),""VERIFICAR CÓD SEC"")"),"JOSEILTON RIBEIRO DO BONFIM") -> JOSEILTON RIBEIRO DO BONFIM | P61: =IFERROR(__xludf.DUMMYFUNCTION("IFERROR(VLOOKUP(D61, IMPORTRANGE(""https://docs.google.com/spreadsheets/d/1MjHtlUikwobi2MaWJgy7tfLeBmhj1u-dRFRs_8GwSoA/edit#gid=0"",""Gestores Escolares!D7:J""),7,0),""VERIFICAR CÓD SEC"")"),"(74) 9 9959-3152/ (71) 9 9185-8027") -> (74) 9 9959-3152/ (71) 9 9185-8027 | Q61: =IFERROR(__xludf.DUMMYFUNCTION("IFERROR(VLOOKUP(D61, IMPORTRANGE(""https://docs.google.com/spreadsheets/d/1MjHtlUikwobi2MaWJgy7tfLeBmhj1u-dRFRs_8GwSoA/edit#gid=0"",""Gestores Escolares!D7:m""),9,0),""VERIFICAR CÓD SEC"")"),"") | R61: =IFERROR(__xludf.DUMMYFUNCTION("IFERROR(VLOOKUP(D61, IMPORTRANGE(""https://docs.google.com/spreadsheets/d/1MjHtlUikwobi2MaWJgy7tfLeBmhj1u-dRFRs_8GwSoA/edit#gid=0"",""Gestores Escolares!D7:m""),10,0),""VERIFICAR CÓD SEC"")"),"") | T61: 12 | U61: 12 | V61: 0 | W61: 0 | X61: 0 | Y61: 0 | Z61: =SUM(V61:Y61) -> 0 | AA61: 0 | AB61: 0 | AC61: 0 | AD61: 0 | AE61: =SUM(AA61:AD61) -> 0 | AF61: 288 | AG61: 213 | AH61: 0 | AI61: 11 | AJ61: =SUM(AF61:AI61) -> 512 | AK61: 0 | AL61: 0 | AM61: 0 | AN61: =SUM(AK61:AM61) -> 0 | AO61: 0 | AP61: 0 | AQ61: 174 | AR61: =SUM(AO61:AQ61) -> 174 | AS61: 0 | AT61: 0 | AU61: 0 | AV61: 0 | AW61: =SUM(AS61:AV61) -> 0 | AX61: =SUM(AY61:AZ61) -> 686 | AY61: =SUM(AV61,AT61,AS61,AP61,AO61,AL61,AK61,AI61,AG61,AF61,AD61,AB61,AA61,Y61,W61,V61) -> 512 | AZ61: =SUM(AU61,AQ61,AM61,AH61,AC61,X61) -> 174 | BA61: 0 | BB61: =SUM(AX61+BA61) -> 686 | BC61: A DEFINIR | BD61: A DEFINIR | BE61: A DEFINIR | BG61: 1176432 | BH61: -10.822998357483721, -42.723402900748546 | BI61: 12 | BJ61: PADRÃO ANTIGO | BK61: =Y61+AD61+AI61+AV61 -> 11 | BL61: =V61+W61+AA61+AB61+AF61+AG61+AK61+AL61+AO61+AP61+AS61+AT61 -> 501 | BM61: =IFERROR(__xludf.DUMMYFUNCTION("IFERROR(VLOOKUP(BG61,IMPORTRANGE(""https://docs.google.com/spreadsheets/d/1juPI-Fb8LD0YtltB2mlGEnp_R3UVu1t3wSFPzgCyHXE/edit?gid=0#gid=0"",""GERAL!A2:C""),3,0),""-"")"),"-") -> -
A62: NTE 01 - IRECÊ | B62: XIQUE-XIQUE | C62: ESCOLA | D62: 1126808 | F62: 29041333 | G62: CENTRO ESTADUAL DE EDUCAÇÃO PROFISSIONAL EM RECURSOS NATURAIS DO CENTRO BAIANO | H62: PRACA POLIVALENTE - SN(00584) | I62: CENTRO | J62: SEDE | K62: PRÓPRIO | L62: ESPECIAL | M62: =IFERROR(__xludf.DUMMYFUNCTION("IFERROR(VLOOKUP(D62, IMPORTRANGE(""https://docs.google.com/spreadsheets/d/1MjHtlUikwobi2MaWJgy7tfLeBmhj1u-dRFRs_8GwSoA/edit#gid=0"",""Gestores Escolares!D7:J""),3,0),""VERIFICAR CÓD SEC"")"),"MARIA GORETE DE MIRANDA ALVES") -> MARIA GORETE DE MIRANDA ALVES | N62: =IFERROR(__xludf.DUMMYFUNCTION("IFERROR(VLOOKUP(D62, IMPORTRANGE(""https://docs.google.com/spreadsheets/d/1MjHtlUikwobi2MaWJgy7tfLeBmhj1u-dRFRs_8GwSoA/edit#gid=0"",""Gestores Escolares!D7:J""),4,0),""VERIFICAR CÓD SEC"")"),"(74) 9 9144-6072") -> (74) 9 9144-6072 | O62: =IFERROR(__xludf.DUMMYFUNCTION("IFERROR(VLOOKUP(D62, IMPORTRANGE(""https://docs.google.com/spreadsheets/d/1MjHtlUikwobi2MaWJgy7tfLeBmhj1u-dRFRs_8GwSoA/edit#gid=0"",""Gestores Escolares!D7:J""),6,0),""VERIFICAR CÓD SEC"")"),"EDNA PINHEIRO BASTOS") -> EDNA PINHEIRO BASTOS | P62: =IFERROR(__xludf.DUMMYFUNCTION("IFERROR(VLOOKUP(D62, IMPORTRANGE(""https://docs.google.com/spreadsheets/d/1MjHtlUikwobi2MaWJgy7tfLeBmhj1u-dRFRs_8GwSoA/edit#gid=0"",""Gestores Escolares!D7:J""),7,0),""VERIFICAR CÓD SEC"")"),"(71) 9 8771-5105") -> (71) 9 8771-5105 | Q62: =IFERROR(__xludf.DUMMYFUNCTION("IFERROR(VLOOKUP(D62, IMPORTRANGE(""https://docs.google.com/spreadsheets/d/1MjHtlUikwobi2MaWJgy7tfLeBmhj1u-dRFRs_8GwSoA/edit#gid=0"",""Gestores Escolares!D7:m""),9,0),""VERIFICAR CÓD SEC"")"),"") | R62: =IFERROR(__xludf.DUMMYFUNCTION("IFERROR(VLOOKUP(D62, IMPORTRANGE(""https://docs.google.com/spreadsheets/d/1MjHtlUikwobi2MaWJgy7tfLeBmhj1u-dRFRs_8GwSoA/edit#gid=0"",""Gestores Escolares!D7:m""),10,0),""VERIFICAR CÓD SEC"")"),"") | T62: 15 | U62: 24 | V62: 0 | W62: 0 | X62: 0 | Y62: 0 | Z62: =SUM(V62:Y62) -> 0 | AA62: 0 | AB62: 0 | AC62: 0 | AD62: 0 | AE62: =SUM(AA62:AD62) -> 0 | AF62: 0 | AG62: 0 | AH62: 0 | AI62: 0 | AJ62: =SUM(AF62:AI62) -> 0 | AK62: 0 | AL62: 0 | AM62: 0 | AN62: =SUM(AK62:AM62) -> 0 | AO62: 0 | AP62: 0 | AQ62: 0 | AR62: =SUM(AO62:AQ62) -> 0 | AS62: 462 | AT62: 353 | AU62: 226 | AV62: 0 | AW62: =SUM(AS62:AV62) -> 1041 | AX62: =SUM(AY62:AZ62) -> 1041 | AY62: =SUM(AV62,AT62,AS62,AP62,AO62,AL62,AK62,AI62,AG62,AF62,AD62,AB62,AA62,Y62,W62,V62) -> 815 | AZ62: =SUM(AU62,AQ62,AM62,AH62,AC62,X62) -> 226 | BA62: 0 | BB62: =SUM(AX62+BA62) -> 1041 | BC62: A DEFINIR | BD62: CEEP | BE62: PROFISSIONAL | BG62: 1126808 | BH62: -10.82791301403092, -42.72619543619899 | BI62: 11 | BJ62: NOVO PADRÃO (AMPLIAÇÃO COM MODERNIZAÇÃO) | BK62: =Y62+AD62+AI62+AV62 -> 0 | BL62: =V62+W62+AA62+AB62+AF62+AG62+AK62+AL62+AO62+AP62+AS62+AT62 -> 815 | BM62: =IFERROR(__xludf.DUMMYFUNCTION("IFERROR(VLOOKUP(BG62,IMPORTRANGE(""https://docs.google.com/spreadsheets/d/1juPI-Fb8LD0YtltB2mlGEnp_R3UVu1t3wSFPzgCyHXE/edit?gid=0#gid=0"",""GERAL!A2:C""),3,0),""-"")"),"-") -> -
A63: NTE 02 - VELHO CHICO | B63: BARRA | C63: ESCOLA | D63: 1127502 | F63: 29036143 | G63: COLÉGIO ESTADUAL DE TEMPO INTEGRAL DE BARRA | H63: RUA DOM PEDRO II - S/N | I63: CENTRO | J63: SEDE | K63: PRÓPRIO | L63: ESPECIAL | M63: =IFERROR(__xludf.DUMMYFUNCTION("IFERROR(VLOOKUP(D63, IMPORTRANGE(""https://docs.google.com/spreadsheets/d/1MjHtlUikwobi2MaWJgy7tfLeBmhj1u-dRFRs_8GwSoA/edit#gid=0"",""Gestores Escolares!D7:J""),3,0),""VERIFICAR CÓD SEC"")"),"ANDRE RICARDO NUNES NASCIMENTO") -> ANDRE RICARDO NUNES NASCIMENTO | N63: =IFERROR(__xludf.DUMMYFUNCTION("IFERROR(VLOOKUP(D63, IMPORTRANGE(""https://docs.google.com/spreadsheets/d/1MjHtlUikwobi2MaWJgy7tfLeBmhj1u-dRFRs_8GwSoA/edit#gid=0"",""Gestores Escolares!D7:J""),4,0),""VERIFICAR CÓD SEC"")"),"(74) 9 8824-9168") -> (74) 9 8824-9168 | O63: =IFERROR(__xludf.DUMMYFUNCTION("IFERROR(VLOOKUP(D63, IMPORTRANGE(""https://docs.google.com/spreadsheets/d/1MjHtlUikwobi2MaWJgy7tfLeBmhj1u-dRFRs_8GwSoA/edit#gid=0"",""Gestores Escolares!D7:J""),6,0),""VERIFICAR CÓD SEC"")"),"LISA MARINA DA SILVA MIGUEL") -> LISA MARINA DA SILVA MIGUEL | P63: =IFERROR(__xludf.DUMMYFUNCTION("IFERROR(VLOOKUP(D63, IMPORTRANGE(""https://docs.google.com/spreadsheets/d/1MjHtlUikwobi2MaWJgy7tfLeBmhj1u-dRFRs_8GwSoA/edit#gid=0"",""Gestores Escolares!D7:J""),7,0),""VERIFICAR CÓD SEC"")"),"(74) 9 9914-2789") -> (74) 9 9914-2789 | Q63: =IFERROR(__xludf.DUMMYFUNCTION("IFERROR(VLOOKUP(D63, IMPORTRANGE(""https://docs.google.com/spreadsheets/d/1MjHtlUikwobi2MaWJgy7tfLeBmhj1u-dRFRs_8GwSoA/edit#gid=0"",""Gestores Escolares!D7:m""),9,0),""VERIFICAR CÓD SEC"")"),"VANESSA DA CONCEICAO BARBOSA DOS ANJOS") -> VANESSA DA CONCEICAO BARBOSA DOS ANJOS | R63: =IFERROR(__xludf.DUMMYFUNCTION("IFERROR(VLOOKUP(D63, IMPORTRANGE(""https://docs.google.com/spreadsheets/d/1MjHtlUikwobi2MaWJgy7tfLeBmhj1u-dRFRs_8GwSoA/edit#gid=0"",""Gestores Escolares!D7:m""),10,0),""VERIFICAR CÓD SEC"")"),"(75) 9 9232-0785") -> (75) 9 9232-0785 | T63: 9 | U63: 36 | V63: 0 | W63: 0 | X63: 0 | Y63: 0 | Z63: =SUM(V63:Y63) -> 0 | AA63: 0 | AB63: 0 | AC63: 0 | AD63: 0 | AE63: =SUM(AA63:AD63) -> 0 | AF63: 459 | AG63: 423 | AH63: 0 | AI63: 200 | AJ63: =SUM(AF63:AI63) -> 1082 | AK63: 0 | AL63: 0 | AM63: 0 | AN63: =SUM(AK63:AM63) -> 0 | AO63: 0 | AP63: 0 | AQ63: 126 | AR63: =SUM(AO63:AQ63) -> 126 | AS63: 0 | AT63: 0 | AU63: 0 | AV63: 0 | AW63: =SUM(AS63:AV63) -> 0 | AX63: =SUM(AY63:AZ63) -> 1208 | AY63: =SUM(AV63,AT63,AS63,AP63,AO63,AL63,AK63,AI63,AG63,AF63,AD63,AB63,AA63,Y63,W63,V63) -> 1082 | AZ63: =SUM(AU63,AQ63,AM63,AH63,AC63,X63) -> 126 | BA63: 0 | BB63: =SUM(AX63+BA63) -> 1208 | BC63: A DEFINIR | BD63: A DEFINIR | BE63: A DEFINIR | BG63: 1127502 | BH63: -11.087653249093082, -43.155823459240736 | BI63: 8 | BJ63: NOVO PADRÃO (NOVA ESCOLA) | BK63: =Y63+AD63+AI63+AV63 -> 200 | BL63: =V63+W63+AA63+AB63+AF63+AG63+AK63+AL63+AO63+AP63+AS63+AT63 -> 882 | BM63: =IFERROR(__xludf.DUMMYFUNCTION("IFERROR(VLOOKUP(BG63,IMPORTRANGE(""https://docs.google.com/spreadsheets/d/1juPI-Fb8LD0YtltB2mlGEnp_R3UVu1t3wSFPzgCyHXE/edit?gid=0#gid=0"",""GERAL!A2:C""),3,0),""-"")"),"-") -> -
A64: NTE 02 - VELHO CHICO | B64: BARRA | C64: ESCOLA | D64: 1179431 | F64: 29464374 | G64: CENTRO REG DE ENS MEDIO COM INTERMEDIACAO TEC-CEMIT VELHO CHICO-BARRA | H64: RUA N 02 N SN(00006) 47100970 | I64: SANTA CLARA CEP: | J64: SEDE | K64: PRÓPRIO | L64: ESPECIAL | M64: =IFERROR(__xludf.DUMMYFUNCTION("IFERROR(VLOOKUP(D64, IMPORTRANGE(""https://docs.google.com/spreadsheets/d/1MjHtlUikwobi2MaWJgy7tfLeBmhj1u-dRFRs_8GwSoA/edit#gid=0"",""Gestores Escolares!D7:J""),3,0),""VERIFICAR CÓD SEC"")"),"NEIDE RAFAEL DE SOUZA ROCHA") -> NEIDE RAFAEL DE SOUZA ROCHA | N64: =IFERROR(__xludf.DUMMYFUNCTION("IFERROR(VLOOKUP(D64, IMPORTRANGE(""https://docs.google.com/spreadsheets/d/1MjHtlUikwobi2MaWJgy7tfLeBmhj1u-dRFRs_8GwSoA/edit#gid=0"",""Gestores Escolares!D7:J""),4,0),""VERIFICAR CÓD SEC"")"),"(74) 9 9807-3175") -> (74) 9 9807-3175 | O64: =IFERROR(__xludf.DUMMYFUNCTION("IFERROR(VLOOKUP(D64, IMPORTRANGE(""https://docs.google.com/spreadsheets/d/1MjHtlUikwobi2MaWJgy7tfLeBmhj1u-dRFRs_8GwSoA/edit#gid=0"",""Gestores Escolares!D7:J""),6,0),""VERIFICAR CÓD SEC"")"),"FRANCISCO DE ARAUJO LEAL") -> FRANCISCO DE ARAUJO LEAL | P64: =IFERROR(__xludf.DUMMYFUNCTION("IFERROR(VLOOKUP(D64, IMPORTRANGE(""https://docs.google.com/spreadsheets/d/1MjHtlUikwobi2MaWJgy7tfLeBmhj1u-dRFRs_8GwSoA/edit#gid=0"",""Gestores Escolares!D7:J""),7,0),""VERIFICAR CÓD SEC"")"),"(74) 9 8836-8463") -> (74) 9 8836-8463 | Q64: =IFERROR(__xludf.DUMMYFUNCTION("IFERROR(VLOOKUP(D64, IMPORTRANGE(""https://docs.google.com/spreadsheets/d/1MjHtlUikwobi2MaWJgy7tfLeBmhj1u-dRFRs_8GwSoA/edit#gid=0"",""Gestores Escolares!D7:m""),9,0),""VERIFICAR CÓD SEC"")"),"CLAUDEMIR CELSO LIMA") -> CLAUDEMIR CELSO LIMA | R64: =IFERROR(__xludf.DUMMYFUNCTION("IFERROR(VLOOKUP(D64, IMPORTRANGE(""https://docs.google.com/spreadsheets/d/1MjHtlUikwobi2MaWJgy7tfLeBmhj1u-dRFRs_8GwSoA/edit#gid=0"",""Gestores Escolares!D7:m""),10,0),""VERIFICAR CÓD SEC"")"),"(74) 9 9952-3072") -> (74) 9 9952-3072 | T64: - | U64: 1 | V64: 0 | W64: 0 | X64: 0 | Y64: 0 | Z64: =SUM(V64:Y64) -> 0 | AA64: 0 | AB64: 0 | AC64: 0 | AD64: 0 | AE64: =SUM(AA64:AD64) -> 0 | AF64: 0 | AG64: 0 | AH64: 0 | AI64: 0 | AJ64: =SUM(AF64:AI64) -> 0 | AK64: 0 | AL64: 0 | AM64: 0 | AN64: =SUM(AK64:AM64) -> 0 | AO64: 0 | AP64: 0 | AQ64: 0 | AR64: =SUM(AO64:AQ64) -> 0 | AS64: 0 | AT64: 0 | AU64: 0 | AV64: 0 | AW64: =SUM(AS64:AV64) -> 0 | AX64: =SUM(AY64:AZ64) -> 0 | AY64: =SUM(AV64,AT64,AS64,AP64,AO64,AL64,AK64,AI64,AG64,AF64,AD64,AB64,AA64,Y64,W64,V64) -> 0 | AZ64: =SUM(AU64,AQ64,AM64,AH64,AC64,X64) -> 0 | BA64: 0 | BB64: =SUM(AX64+BA64) -> 0 | BC64: A DEFINIR | BD64: CEMIT | BE64: PROFISSIONAL | BF64: UEE ADMINISTRATIVA CEMIT | BG64: 1179431 | BI64: 1 | BJ64: PADRÃO ANTIGO | BK64: =Y64+AD64+AI64+AV64 -> 0 | BL64: =V64+W64+AA64+AB64+AF64+AG64+AK64+AL64+AO64+AP64+AS64+AT64 -> 0 | BM64: =IFERROR(__xludf.DUMMYFUNCTION("IFERROR(VLOOKUP(BG64,IMPORTRANGE(""https://docs.google.com/spreadsheets/d/1juPI-Fb8LD0YtltB2mlGEnp_R3UVu1t3wSFPzgCyHXE/edit?gid=0#gid=0"",""GERAL!A2:C""),3,0),""-"")"),"-") -> -
A65: NTE 02 - VELHO CHICO | B65: BARRA | C65: ESCOLA | D65: 1178324 | F65: 29863724 | G65: CENTRO ESTADUAL DE EDUCACAO PROFISSIONAL AGUAS - TEMPO INTEGRAL | H65: ANTIGA FAZENDA BALI HAI, BR 161 - S/N | I65: CENTRO | J65: SEDE | K65: PRÓPRIO | L65: ESPECIAL | M65: =IFERROR(__xludf.DUMMYFUNCTION("IFERROR(VLOOKUP(D65, IMPORTRANGE(""https://docs.google.com/spreadsheets/d/1MjHtlUikwobi2MaWJgy7tfLeBmhj1u-dRFRs_8GwSoA/edit#gid=0"",""Gestores Escolares!D7:J""),3,0),""VERIFICAR CÓD SEC"")"),"ANA PAULA SANTOS GONCALVES") -> ANA PAULA SANTOS GONCALVES | N65: =IFERROR(__xludf.DUMMYFUNCTION("IFERROR(VLOOKUP(D65, IMPORTRANGE(""https://docs.google.com/spreadsheets/d/1MjHtlUikwobi2MaWJgy7tfLeBmhj1u-dRFRs_8GwSoA/edit#gid=0"",""Gestores Escolares!D7:J""),4,0),""VERIFICAR CÓD SEC"")"),"(74) 9 9973-8960") -> (74) 9 9973-8960 | O65: =IFERROR(__xludf.DUMMYFUNCTION("IFERROR(VLOOKUP(D65, IMPORTRANGE(""https://docs.google.com/spreadsheets/d/1MjHtlUikwobi2MaWJgy7tfLeBmhj1u-dRFRs_8GwSoA/edit#gid=0"",""Gestores Escolares!D7:J""),6,0),""VERIFICAR CÓD SEC"")")," MARILEIDE RAMOS DE CARVALHO") -> MARILEIDE RAMOS DE CARVALHO | P65: =IFERROR(__xludf.DUMMYFUNCTION("IFERROR(VLOOKUP(D65, IMPORTRANGE(""https://docs.google.com/spreadsheets/d/1MjHtlUikwobi2MaWJgy7tfLeBmhj1u-dRFRs_8GwSoA/edit#gid=0"",""Gestores Escolares!D7:J""),7,0),""VERIFICAR CÓD SEC"")"),"(74) 9 9994-1397") -> (74) 9 9994-1397 | Q65: =IFERROR(__xludf.DUMMYFUNCTION("IFERROR(VLOOKUP(D65, IMPORTRANGE(""https://docs.google.com/spreadsheets/d/1MjHtlUikwobi2MaWJgy7tfLeBmhj1u-dRFRs_8GwSoA/edit#gid=0"",""Gestores Escolares!D7:m""),9,0),""VERIFICAR CÓD SEC"")"),"NATA BENICIO DE SOUZA") -> NATA BENICIO DE SOUZA | R65: =IFERROR(__xludf.DUMMYFUNCTION("IFERROR(VLOOKUP(D65, IMPORTRANGE(""https://docs.google.com/spreadsheets/d/1MjHtlUikwobi2MaWJgy7tfLeBmhj1u-dRFRs_8GwSoA/edit#gid=0"",""Gestores Escolares!D7:m""),10,0),""VERIFICAR CÓD SEC"")"),"(74) 9 8123-3246") -> (74) 9 8123-3246 | T65: 8 | U65: 06 + 06 (Adapt) | V65: 0 | W65: 0 | X65: 0 | Y65: 0 | Z65: =SUM(V65:Y65) -> 0 | AA65: 0 | AB65: 0 | AC65: 0 | AD65: 0 | AE65: =SUM(AA65:AD65) -> 0 | AF65: 0 | AG65: 0 | AH65: 0 | AI65: 0 | AJ65: =SUM(AF65:AI65) -> 0 | AK65: 0 | AL65: 0 | AM65: 0 | AN65: =SUM(AK65:AM65) -> 0 | AO65: 0 | AP65: 0 | AQ65: 0 | AR65: =SUM(AO65:AQ65) -> 0 | AS65: 0 | AT65: 0 | AU65: 95 | AV65: 223 | AW65: =SUM(AS65:AV65) -> 318 | AX65: =SUM(AY65:AZ65) -> 318 | AY65: =SUM(AV65,AT65,AS65,AP65,AO65,AL65,AK65,AI65,AG65,AF65,AD65,AB65,AA65,Y65,W65,V65) -> 223 | AZ65: =SUM(AU65,AQ65,AM65,AH65,AC65,X65) -> 95 | BA65: 0 | BB65: =SUM(AX65+BA65) -> 318 | BC65: A DEFINIR | BD65: CEEP | BE65: PROFISSIONAL | BG65: 1178324 | BH65: -11.095358822403696, -43.21548188537059 | BI65: 8 | BJ65: PADRÃO ANTIGO | BK65: =Y65+AD65+AI65+AV65 -> 223 | BL65: =V65+W65+AA65+AB65+AF65+AG65+AK65+AL65+AO65+AP65+AS65+AT65 -> 0 | BM65: =IFERROR(__xludf.DUMMYFUNCTION("IFERROR(VLOOKUP(BG65,IMPORTRANGE(""https://docs.google.com/spreadsheets/d/1juPI-Fb8LD0YtltB2mlGEnp_R3UVu1t3wSFPzgCyHXE/edit?gid=0#gid=0"",""GERAL!A2:C""),3,0),""-"")"),"-") -> -
A66: NTE 02 - VELHO CHICO | B66: BARRA | C66: ANEXO | D66: 1179431 | E66: 1178812 | F66: 29464374 | G66: ANEXO - CEMIT - VELHO CHICO-BARRA- CURRALINHO - COMUNIDADE QUILOMBOLA | H66: CURRALINHO - SN(00042) | I66: CENTRO | J66: 48KM | K66: CEDIDO | L66: PEQUENO | M66: =IFERROR(__xludf.DUMMYFUNCTION("IFERROR(VLOOKUP(D66, IMPORTRANGE(""https://docs.google.com/spreadsheets/d/1MjHtlUikwobi2MaWJgy7tfLeBmhj1u-dRFRs_8GwSoA/edit#gid=0"",""Gestores Escolares!D7:J""),3,0),""VERIFICAR CÓD SEC"")"),"NEIDE RAFAEL DE SOUZA ROCHA") -> NEIDE RAFAEL DE SOUZA ROCHA | N66: =IFERROR(__xludf.DUMMYFUNCTION("IFERROR(VLOOKUP(D66, IMPORTRANGE(""https://docs.google.com/spreadsheets/d/1MjHtlUikwobi2MaWJgy7tfLeBmhj1u-dRFRs_8GwSoA/edit#gid=0"",""Gestores Escolares!D7:J""),4,0),""VERIFICAR CÓD SEC"")"),"(74) 9 9807-3175") -> (74) 9 9807-3175 | O66: =IFERROR(__xludf.DUMMYFUNCTION("IFERROR(VLOOKUP(D66, IMPORTRANGE(""https://docs.google.com/spreadsheets/d/1MjHtlUikwobi2MaWJgy7tfLeBmhj1u-dRFRs_8GwSoA/edit#gid=0"",""Gestores Escolares!D7:J""),6,0),""VERIFICAR CÓD SEC"")"),"FRANCISCO DE ARAUJO LEAL") -> FRANCISCO DE ARAUJO LEAL | P66: =IFERROR(__xludf.DUMMYFUNCTION("IFERROR(VLOOKUP(D66, IMPORTRANGE(""https://docs.google.com/spreadsheets/d/1MjHtlUikwobi2MaWJgy7tfLeBmhj1u-dRFRs_8GwSoA/edit#gid=0"",""Gestores Escolares!D7:J""),7,0),""VERIFICAR CÓD SEC"")"),"(74) 9 8836-8463") -> (74) 9 8836-8463 | Q66: =IFERROR(__xludf.DUMMYFUNCTION("IFERROR(VLOOKUP(D66, IMPORTRANGE(""https://docs.google.com/spreadsheets/d/1MjHtlUikwobi2MaWJgy7tfLeBmhj1u-dRFRs_8GwSoA/edit#gid=0"",""Gestores Escolares!D7:m""),9,0),""VERIFICAR CÓD SEC"")"),"CLAUDEMIR CELSO LIMA") -> CLAUDEMIR CELSO LIMA | R66: =IFERROR(__xludf.DUMMYFUNCTION("IFERROR(VLOOKUP(D66, IMPORTRANGE(""https://docs.google.com/spreadsheets/d/1MjHtlUikwobi2MaWJgy7tfLeBmhj1u-dRFRs_8GwSoA/edit#gid=0"",""Gestores Escolares!D7:m""),10,0),""VERIFICAR CÓD SEC"")"),"(74) 9 9952-3072") -> (74) 9 9952-3072 | T66: 2 | U66: 2 | V66: 0 | W66: 0 | X66: 0 | Y66: 0 | Z66: =SUM(V66:Y66) -> 0 | AA66: 0 | AB66: 0 | AC66: 0 | AD66: 0 | AE66: =SUM(AA66:AD66) -> 0 | AF66: 21 | AG66: 10 | AH66: 0 | AI66: 0 | AJ66: =SUM(AF66:AI66) -> 31 | AK66: 0 | AL66: 0 | AM66: 0 | AN66: =SUM(AK66:AM66) -> 0 | AO66: 0 | AP66: 0 | AQ66: 0 | AR66: =SUM(AO66:AQ66) -> 0 | AS66: 0 | AT66: 0 | AU66: 0 | AV66: 0 | AW66: =SUM(AS66:AV66) -> 0 | AX66: =SUM(AY66:AZ66) -> 31 | AY66: =SUM(AV66,AT66,AS66,AP66,AO66,AL66,AK66,AI66,AG66,AF66,AD66,AB66,AA66,Y66,W66,V66) -> 31 | AZ66: =SUM(AU66,AQ66,AM66,AH66,AC66,X66) -> 0 | BA66: 0 | BB66: =SUM(AX66+BA66) -> 31 | BC66: QUILOMBOLA | BD66: CEMIT | BE66: A DEFINIR | BG66: 1178812 | BI66: 2 | BJ66: PADRÃO ANTIGO | BK66: =Y66+AD66+AI66+AV66 -> 0 | BL66: =V66+W66+AA66+AB66+AF66+AG66+AK66+AL66+AO66+AP66+AS66+AT66 -> 31 | BM66: =IFERROR(__xludf.DUMMYFUNCTION("IFERROR(VLOOKUP(BG66,IMPORTRANGE(""https://docs.google.com/spreadsheets/d/1juPI-Fb8LD0YtltB2mlGEnp_R3UVu1t3wSFPzgCyHXE/edit?gid=0#gid=0"",""GERAL!A2:C""),3,0),""-"")"),"QUILOMBOLAS") -> QUILOMBOLAS
A67: NTE 02 - VELHO CHICO | B67: BARRA | C67: ANEXO | D67: 1179431 | E67: 1178814 | F67: 29464374 | G67: ANEXO - CEMIT - VELHO CHICO-BARRA - WANDERLEY | H67: WANDERLEY - SN(00037) | I67: CENTRO | J67: 34KM | K67: CEDIDO | L67: PEQUENO | M67: =IFERROR(__xludf.DUMMYFUNCTION("IFERROR(VLOOKUP(D67, IMPORTRANGE(""https://docs.google.com/spreadsheets/d/1MjHtlUikwobi2MaWJgy7tfLeBmhj1u-dRFRs_8GwSoA/edit#gid=0"",""Gestores Escolares!D7:J""),3,0),""VERIFICAR CÓD SEC"")"),"NEIDE RAFAEL DE SOUZA ROCHA") -> NEIDE RAFAEL DE SOUZA ROCHA | N67: =IFERROR(__xludf.DUMMYFUNCTION("IFERROR(VLOOKUP(D67, IMPORTRANGE(""https://docs.google.com/spreadsheets/d/1MjHtlUikwobi2MaWJgy7tfLeBmhj1u-dRFRs_8GwSoA/edit#gid=0"",""Gestores Escolares!D7:J""),4,0),""VERIFICAR CÓD SEC"")"),"(74) 9 9807-3175") -> (74) 9 9807-3175 | O67: =IFERROR(__xludf.DUMMYFUNCTION("IFERROR(VLOOKUP(D67, IMPORTRANGE(""https://docs.google.com/spreadsheets/d/1MjHtlUikwobi2MaWJgy7tfLeBmhj1u-dRFRs_8GwSoA/edit#gid=0"",""Gestores Escolares!D7:J""),6,0),""VERIFICAR CÓD SEC"")"),"FRANCISCO DE ARAUJO LEAL") -> FRANCISCO DE ARAUJO LEAL | P67: =IFERROR(__xludf.DUMMYFUNCTION("IFERROR(VLOOKUP(D67, IMPORTRANGE(""https://docs.google.com/spreadsheets/d/1MjHtlUikwobi2MaWJgy7tfLeBmhj1u-dRFRs_8GwSoA/edit#gid=0"",""Gestores Escolares!D7:J""),7,0),""VERIFICAR CÓD SEC"")"),"(74) 9 8836-8463") -> (74) 9 8836-8463 | Q67: =IFERROR(__xludf.DUMMYFUNCTION("IFERROR(VLOOKUP(D67, IMPORTRANGE(""https://docs.google.com/spreadsheets/d/1MjHtlUikwobi2MaWJgy7tfLeBmhj1u-dRFRs_8GwSoA/edit#gid=0"",""Gestores Escolares!D7:m""),9,0),""VERIFICAR CÓD SEC"")"),"CLAUDEMIR CELSO LIMA") -> CLAUDEMIR CELSO LIMA | R67: =IFERROR(__xludf.DUMMYFUNCTION("IFERROR(VLOOKUP(D67, IMPORTRANGE(""https://docs.google.com/spreadsheets/d/1MjHtlUikwobi2MaWJgy7tfLeBmhj1u-dRFRs_8GwSoA/edit#gid=0"",""Gestores Escolares!D7:m""),10,0),""VERIFICAR CÓD SEC"")"),"(74) 9 9952-3072") -> (74) 9 9952-3072 | T67: 3 | U67: 2 | V67: 0 | W67: 0 | X67: 0 | Y67: 0 | Z67: =SUM(V67:Y67) -> 0 | AA67: 0 | AB67: 0 | AC67: 0 | AD67: 0 | AE67: =SUM(AA67:AD67) -> 0 | AF67: 57 | AG67: 0 | AH67: 52 | AI67: 0 | AJ67: =SUM(AF67:AI67) -> 109 | AK67: 0 | AL67: 0 | AM67: 0 | AN67: =SUM(AK67:AM67) -> 0 | AO67: 0 | AP67: 0 | AQ67: 0 | AR67: =SUM(AO67:AQ67) -> 0 | AS67: 0 | AT67: 0 | AU67: 0 | AV67: 0 | AW67: =SUM(AS67:AV67) -> 0 | AX67: =SUM(AY67:AZ67) -> 109 | AY67: =SUM(AV67,AT67,AS67,AP67,AO67,AL67,AK67,AI67,AG67,AF67,AD67,AB67,AA67,Y67,W67,V67) -> 57 | AZ67: =SUM(AU67,AQ67,AM67,AH67,AC67,X67) -> 52 | BA67: 0 | BB67: =SUM(AX67+BA67) -> 109 | BC67: A DEFINIR | BD67: CEMIT | BE67: PROFISSIONAL | BG67: 1178814 | BI67: 3 | BJ67: PADRÃO ANTIGO | BK67: =Y67+AD67+AI67+AV67 -> 0 | BL67: =V67+W67+AA67+AB67+AF67+AG67+AK67+AL67+AO67+AP67+AS67+AT67 -> 57 | BM67: =IFERROR(__xludf.DUMMYFUNCTION("IFERROR(VLOOKUP(BG67,IMPORTRANGE(""https://docs.google.com/spreadsheets/d/1juPI-Fb8LD0YtltB2mlGEnp_R3UVu1t3wSFPzgCyHXE/edit?gid=0#gid=0"",""GERAL!A2:C""),3,0),""-"")"),"-") -> -
A68: NTE 02 - VELHO CHICO | B68: BARRA | C68: ANEXO | D68: 1179431 | E68: 1178816 | F68: 29464374 | G68: ANEXO - CEMIT - VELHO CHICO-BARRA - POVOADO PRIMAVERA | H68: PRIMAVERA - SN(00016) | I68: CENTRO | J68: 50KM | K68: CEDIDO | L68: PEQUENO | M68: =IFERROR(__xludf.DUMMYFUNCTION("IFERROR(VLOOKUP(D68, IMPORTRANGE(""https://docs.google.com/spreadsheets/d/1MjHtlUikwobi2MaWJgy7tfLeBmhj1u-dRFRs_8GwSoA/edit#gid=0"",""Gestores Escolares!D7:J""),3,0),""VERIFICAR CÓD SEC"")"),"NEIDE RAFAEL DE SOUZA ROCHA") -> NEIDE RAFAEL DE SOUZA ROCHA | N68: =IFERROR(__xludf.DUMMYFUNCTION("IFERROR(VLOOKUP(D68, IMPORTRANGE(""https://docs.google.com/spreadsheets/d/1MjHtlUikwobi2MaWJgy7tfLeBmhj1u-dRFRs_8GwSoA/edit#gid=0"",""Gestores Escolares!D7:J""),4,0),""VERIFICAR CÓD SEC"")"),"(74) 9 9807-3175") -> (74) 9 9807-3175 | O68: =IFERROR(__xludf.DUMMYFUNCTION("IFERROR(VLOOKUP(D68, IMPORTRANGE(""https://docs.google.com/spreadsheets/d/1MjHtlUikwobi2MaWJgy7tfLeBmhj1u-dRFRs_8GwSoA/edit#gid=0"",""Gestores Escolares!D7:J""),6,0),""VERIFICAR CÓD SEC"")"),"FRANCISCO DE ARAUJO LEAL") -> FRANCISCO DE ARAUJO LEAL | P68: =IFERROR(__xludf.DUMMYFUNCTION("IFERROR(VLOOKUP(D68, IMPORTRANGE(""https://docs.google.com/spreadsheets/d/1MjHtlUikwobi2MaWJgy7tfLeBmhj1u-dRFRs_8GwSoA/edit#gid=0"",""Gestores Escolares!D7:J""),7,0),""VERIFICAR CÓD SEC"")"),"(74) 9 8836-8463") -> (74) 9 8836-8463 | Q68: =IFERROR(__xludf.DUMMYFUNCTION("IFERROR(VLOOKUP(D68, IMPORTRANGE(""https://docs.google.com/spreadsheets/d/1MjHtlUikwobi2MaWJgy7tfLeBmhj1u-dRFRs_8GwSoA/edit#gid=0"",""Gestores Escolares!D7:m""),9,0),""VERIFICAR CÓD SEC"")"),"CLAUDEMIR CELSO LIMA") -> CLAUDEMIR CELSO LIMA | R68: =IFERROR(__xludf.DUMMYFUNCTION("IFERROR(VLOOKUP(D68, IMPORTRANGE(""https://docs.google.com/spreadsheets/d/1MjHtlUikwobi2MaWJgy7tfLeBmhj1u-dRFRs_8GwSoA/edit#gid=0"",""Gestores Escolares!D7:m""),10,0),""VERIFICAR CÓD SEC"")"),"(74) 9 9952-3072") -> (74) 9 9952-3072 | T68: 2 | U68: 2 | V68: 0 | W68: 0 | X68: 0 | Y68: 0 | Z68: =SUM(V68:Y68) -> 0 | AA68: 0 | AB68: 0 | AC68: 0 | AD68: 0 | AE68: =SUM(AA68:AD68) -> 0 | AF68: 15 | AG68: 22 | AH68: 0 | AI68: 0 | AJ68: =SUM(AF68:AI68) -> 37 | AK68: 0 | AL68: 0 | AM68: 0 | AN68: =SUM(AK68:AM68) -> 0 | AO68: 0 | AP68: 0 | AQ68: 0 | AR68: =SUM(AO68:AQ68) -> 0 | AS68: 0 | AT68: 0 | AU68: 0 | AV68: 0 | AW68: =SUM(AS68:AV68) -> 0 | AX68: =SUM(AY68:AZ68) -> 37 | AY68: =SUM(AV68,AT68,AS68,AP68,AO68,AL68,AK68,AI68,AG68,AF68,AD68,AB68,AA68,Y68,W68,V68) -> 37 | AZ68: =SUM(AU68,AQ68,AM68,AH68,AC68,X68) -> 0 | BA68: 0 | BB68: =SUM(AX68+BA68) -> 37 | BC68: A DEFINIR | BD68: CEMIT | BE68: PROFISSIONAL | BG68: 1178816 | BI68: 2 | BJ68: PADRÃO ANTIGO | BK68: =Y68+AD68+AI68+AV68 -> 0 | BL68: =V68+W68+AA68+AB68+AF68+AG68+AK68+AL68+AO68+AP68+AS68+AT68 -> 37 | BM68: =IFERROR(__xludf.DUMMYFUNCTION("IFERROR(VLOOKUP(BG68,IMPORTRANGE(""https://docs.google.com/spreadsheets/d/1juPI-Fb8LD0YtltB2mlGEnp_R3UVu1t3wSFPzgCyHXE/edit?gid=0#gid=0"",""GERAL!A2:C""),3,0),""-"")"),"-") -> -
A69: NTE 02 - VELHO CHICO | B69: BARRA | C69: ANEXO | D69: 1179431 | E69: 1179212 | F69: 29464374 | G69: ANEXO - CEMIT - VELHO CHICO-BARRA - POVOADO ITACOATIARA | H69: POVOADO DE ITACOATIARA - SN(00006) | I69: CENTRO | J69: 50KM | K69: CEDIDO | L69: PEQUENO | M69: =IFERROR(__xludf.DUMMYFUNCTION("IFERROR(VLOOKUP(D69, IMPORTRANGE(""https://docs.google.com/spreadsheets/d/1MjHtlUikwobi2MaWJgy7tfLeBmhj1u-dRFRs_8GwSoA/edit#gid=0"",""Gestores Escolares!D7:J""),3,0),""VERIFICAR CÓD SEC"")"),"NEIDE RAFAEL DE SOUZA ROCHA") -> NEIDE RAFAEL DE SOUZA ROCHA | N69: =IFERROR(__xludf.DUMMYFUNCTION("IFERROR(VLOOKUP(D69, IMPORTRANGE(""https://docs.google.com/spreadsheets/d/1MjHtlUikwobi2MaWJgy7tfLeBmhj1u-dRFRs_8GwSoA/edit#gid=0"",""Gestores Escolares!D7:J""),4,0),""VERIFICAR CÓD SEC"")"),"(74) 9 9807-3175") -> (74) 9 9807-3175 | O69: =IFERROR(__xludf.DUMMYFUNCTION("IFERROR(VLOOKUP(D69, IMPORTRANGE(""https://docs.google.com/spreadsheets/d/1MjHtlUikwobi2MaWJgy7tfLeBmhj1u-dRFRs_8GwSoA/edit#gid=0"",""Gestores Escolares!D7:J""),6,0),""VERIFICAR CÓD SEC"")"),"FRANCISCO DE ARAUJO LEAL") -> FRANCISCO DE ARAUJO LEAL | P69: =IFERROR(__xludf.DUMMYFUNCTION("IFERROR(VLOOKUP(D69, IMPORTRANGE(""https://docs.google.com/spreadsheets/d/1MjHtlUikwobi2MaWJgy7tfLeBmhj1u-dRFRs_8GwSoA/edit#gid=0"",""Gestores Escolares!D7:J""),7,0),""VERIFICAR CÓD SEC"")"),"(74) 9 8836-8463") -> (74) 9 8836-8463 | Q69: =IFERROR(__xludf.DUMMYFUNCTION("IFERROR(VLOOKUP(D69, IMPORTRANGE(""https://docs.google.com/spreadsheets/d/1MjHtlUikwobi2MaWJgy7tfLeBmhj1u-dRFRs_8GwSoA/edit#gid=0"",""Gestores Escolares!D7:m""),9,0),""VERIFICAR CÓD SEC"")"),"CLAUDEMIR CELSO LIMA") -> CLAUDEMIR CELSO LIMA | R69: =IFERROR(__xludf.DUMMYFUNCTION("IFERROR(VLOOKUP(D69, IMPORTRANGE(""https://docs.google.com/spreadsheets/d/1MjHtlUikwobi2MaWJgy7tfLeBmhj1u-dRFRs_8GwSoA/edit#gid=0"",""Gestores Escolares!D7:m""),10,0),""VERIFICAR CÓD SEC"")"),"(74) 9 9952-3072") -> (74) 9 9952-3072 | T69: 1 | U69: 2 | V69: 0 | W69: 0 | X69: 0 | Y69: 0 | Z69: =SUM(V69:Y69) -> 0 | AA69: 0 | AB69: 0 | AC69: 0 | AD69: 0 | AE69: =SUM(AA69:AD69) -> 0 | AF69: 14 | AG69: 26 | AH69: 21 | AI69: 0 | AJ69: =SUM(AF69:AI69) -> 61 | AK69: 0 | AL69: 0 | AM69: 0 | AN69: =SUM(AK69:AM69) -> 0 | AO69: 0 | AP69: 0 | AQ69: 0 | AR69: =SUM(AO69:AQ69) -> 0 | AS69: 0 | AT69: 0 | AU69: 0 | AV69: 0 | AW69: =SUM(AS69:AV69) -> 0 | AX69: =SUM(AY69:AZ69) -> 61 | AY69: =SUM(AV69,AT69,AS69,AP69,AO69,AL69,AK69,AI69,AG69,AF69,AD69,AB69,AA69,Y69,W69,V69) -> 40 | AZ69: =SUM(AU69,AQ69,AM69,AH69,AC69,X69) -> 21 | BA69: 0 | BB69: =SUM(AX69+BA69) -> 61 | BC69: A DEFINIR | BD69: CEMIT | BE69: PROFISSIONAL | BG69: 1179212 | BI69: 1 | BJ69: PADRÃO ANTIGO | BK69: =Y69+AD69+AI69+AV69 -> 0 | BL69: =V69+W69+AA69+AB69+AF69+AG69+AK69+AL69+AO69+AP69+AS69+AT69 -> 40 | BM69: =IFERROR(__xludf.DUMMYFUNCTION("IFERROR(VLOOKUP(BG69,IMPORTRANGE(""https://docs.google.com/spreadsheets/d/1juPI-Fb8LD0YtltB2mlGEnp_R3UVu1t3wSFPzgCyHXE/edit?gid=0#gid=0"",""GERAL!A2:C""),3,0),""-"")"),"-") -> -
A70: NTE 02 - VELHO CHICO | B70: BARRA | C70: ANEXO | D70: 1179431 | E70: 1178813 | F70: 29464374 | G70: ANEXO - CEMIT - VELHO CHICO-BARRA - LIMOEIRO | H70: LIMOEIRO - SN(00043) | I70: CENTRO | J70: 96KM | K70: CEDIDO | L70: PEQUENO | M70: =IFERROR(__xludf.DUMMYFUNCTION("IFERROR(VLOOKUP(D70, IMPORTRANGE(""https://docs.google.com/spreadsheets/d/1MjHtlUikwobi2MaWJgy7tfLeBmhj1u-dRFRs_8GwSoA/edit#gid=0"",""Gestores Escolares!D7:J""),3,0),""VERIFICAR CÓD SEC"")"),"NEIDE RAFAEL DE SOUZA ROCHA") -> NEIDE RAFAEL DE SOUZA ROCHA | N70: =IFERROR(__xludf.DUMMYFUNCTION("IFERROR(VLOOKUP(D70, IMPORTRANGE(""https://docs.google.com/spreadsheets/d/1MjHtlUikwobi2MaWJgy7tfLeBmhj1u-dRFRs_8GwSoA/edit#gid=0"",""Gestores Escolares!D7:J""),4,0),""VERIFICAR CÓD SEC"")"),"(74) 9 9807-3175") -> (74) 9 9807-3175 | O70: =IFERROR(__xludf.DUMMYFUNCTION("IFERROR(VLOOKUP(D70, IMPORTRANGE(""https://docs.google.com/spreadsheets/d/1MjHtlUikwobi2MaWJgy7tfLeBmhj1u-dRFRs_8GwSoA/edit#gid=0"",""Gestores Escolares!D7:J""),6,0),""VERIFICAR CÓD SEC"")"),"FRANCISCO DE ARAUJO LEAL") -> FRANCISCO DE ARAUJO LEAL | P70: =IFERROR(__xludf.DUMMYFUNCTION("IFERROR(VLOOKUP(D70, IMPORTRANGE(""https://docs.google.com/spreadsheets/d/1MjHtlUikwobi2MaWJgy7tfLeBmhj1u-dRFRs_8GwSoA/edit#gid=0"",""Gestores Escolares!D7:J""),7,0),""VERIFICAR CÓD SEC"")"),"(74) 9 8836-8463") -> (74) 9 8836-8463 | Q70: =IFERROR(__xludf.DUMMYFUNCTION("IFERROR(VLOOKUP(D70, IMPORTRANGE(""https://docs.google.com/spreadsheets/d/1MjHtlUikwobi2MaWJgy7tfLeBmhj1u-dRFRs_8GwSoA/edit#gid=0"",""Gestores Escolares!D7:m""),9,0),""VERIFICAR CÓD SEC"")"),"CLAUDEMIR CELSO LIMA") -> CLAUDEMIR CELSO LIMA | R70: =IFERROR(__xludf.DUMMYFUNCTION("IFERROR(VLOOKUP(D70, IMPORTRANGE(""https://docs.google.com/spreadsheets/d/1MjHtlUikwobi2MaWJgy7tfLeBmhj1u-dRFRs_8GwSoA/edit#gid=0"",""Gestores Escolares!D7:m""),10,0),""VERIFICAR CÓD SEC"")"),"(74) 9 9952-3072") -> (74) 9 9952-3072 | T70: 3 | U70: 2 | V70: 0 | W70: 0 | X70: 0 | Y70: 0 | Z70: =SUM(V70:Y70) -> 0 | AA70: 0 | AB70: 0 | AC70: 0 | AD70: 0 | AE70: =SUM(AA70:AD70) -> 0 | AF70: 0 | AG70: 53 | AH70: 71 | AI70: 0 | AJ70: =SUM(AF70:AI70) -> 124 | AK70: 0 | AL70: 0 | AM70: 0 | AN70: =SUM(AK70:AM70) -> 0 | AO70: 0 | AP70: 0 | AQ70: 0 | AR70: =SUM(AO70:AQ70) -> 0 | AS70: 0 | AT70: 0 | AU70: 0 | AV70: 0 | AW70: =SUM(AS70:AV70) -> 0 | AX70: =SUM(AY70:AZ70) -> 124 | AY70: =SUM(AV70,AT70,AS70,AP70,AO70,AL70,AK70,AI70,AG70,AF70,AD70,AB70,AA70,Y70,W70,V70) -> 53 | AZ70: =SUM(AU70,AQ70,AM70,AH70,AC70,X70) -> 71 | BA70: 0 | BB70: =SUM(AX70+BA70) -> 124 | BC70: A DEFINIR | BD70: CEMIT | BE70: PROFISSIONAL | BG70: 1178813 | BI70: 3 | BJ70: PADRÃO ANTIGO | BK70: =Y70+AD70+AI70+AV70 -> 0 | BL70: =V70+W70+AA70+AB70+AF70+AG70+AK70+AL70+AO70+AP70+AS70+AT70 -> 53 | BM70: =IFERROR(__xludf.DUMMYFUNCTION("IFERROR(VLOOKUP(BG70,IMPORTRANGE(""https://docs.google.com/spreadsheets/d/1juPI-Fb8LD0YtltB2mlGEnp_R3UVu1t3wSFPzgCyHXE/edit?gid=0#gid=0"",""GERAL!A2:C""),3,0),""-"")"),"-") -> -
A71: NTE 02 - VELHO CHICO | B71: BARRA | C71: ANEXO | D71: 1179431 | E71: 1178815 | F71: 29464374 | G71: ANEXO - CEMIT - VELHO CHICO-BARRA - DISTRITO DE IGARITE - COMUNIDADE QUILOMBOLA | H71: DISTRITO DE IGARITE - S/N | I71: CENTRO | J71: 87KM | K71: PRÓPRIO | L71: PEQUENO | M71: =IFERROR(__xludf.DUMMYFUNCTION("IFERROR(VLOOKUP(D71, IMPORTRANGE(""https://docs.google.com/spreadsheets/d/1MjHtlUikwobi2MaWJgy7tfLeBmhj1u-dRFRs_8GwSoA/edit#gid=0"",""Gestores Escolares!D7:J""),3,0),""VERIFICAR CÓD SEC"")"),"NEIDE RAFAEL DE SOUZA ROCHA") -> NEIDE RAFAEL DE SOUZA ROCHA | N71: =IFERROR(__xludf.DUMMYFUNCTION("IFERROR(VLOOKUP(D71, IMPORTRANGE(""https://docs.google.com/spreadsheets/d/1MjHtlUikwobi2MaWJgy7tfLeBmhj1u-dRFRs_8GwSoA/edit#gid=0"",""Gestores Escolares!D7:J""),4,0),""VERIFICAR CÓD SEC"")"),"(74) 9 9807-3175") -> (74) 9 9807-3175 | O71: =IFERROR(__xludf.DUMMYFUNCTION("IFERROR(VLOOKUP(D71, IMPORTRANGE(""https://docs.google.com/spreadsheets/d/1MjHtlUikwobi2MaWJgy7tfLeBmhj1u-dRFRs_8GwSoA/edit#gid=0"",""Gestores Escolares!D7:J""),6,0),""VERIFICAR CÓD SEC"")"),"FRANCISCO DE ARAUJO LEAL") -> FRANCISCO DE ARAUJO LEAL | P71: =IFERROR(__xludf.DUMMYFUNCTION("IFERROR(VLOOKUP(D71, IMPORTRANGE(""https://docs.google.com/spreadsheets/d/1MjHtlUikwobi2MaWJgy7tfLeBmhj1u-dRFRs_8GwSoA/edit#gid=0"",""Gestores Escolares!D7:J""),7,0),""VERIFICAR CÓD SEC"")"),"(74) 9 8836-8463") -> (74) 9 8836-8463 | Q71: =IFERROR(__xludf.DUMMYFUNCTION("IFERROR(VLOOKUP(D71, IMPORTRANGE(""https://docs.google.com/spreadsheets/d/1MjHtlUikwobi2MaWJgy7tfLeBmhj1u-dRFRs_8GwSoA/edit#gid=0"",""Gestores Escolares!D7:m""),9,0),""VERIFICAR CÓD SEC"")"),"CLAUDEMIR CELSO LIMA") -> CLAUDEMIR CELSO LIMA | R71: =IFERROR(__xludf.DUMMYFUNCTION("IFERROR(VLOOKUP(D71, IMPORTRANGE(""https://docs.google.com/spreadsheets/d/1MjHtlUikwobi2MaWJgy7tfLeBmhj1u-dRFRs_8GwSoA/edit#gid=0"",""Gestores Escolares!D7:m""),10,0),""VERIFICAR CÓD SEC"")"),"(74) 9 9952-3072") -> (74) 9 9952-3072 | T71: 1 | U71: 2 | V71: 0 | W71: 0 | X71: 0 | Y71: 0 | Z71: =SUM(V71:Y71) -> 0 | AA71: 0 | AB71: 0 | AC71: 0 | AD71: 0 | AE71: =SUM(AA71:AD71) -> 0 | AF71: 22 | AG71: 16 | AH71: 17 | AI71: 0 | AJ71: =SUM(AF71:AI71) -> 55 | AK71: 0 | AL71: 0 | AM71: 0 | AN71: =SUM(AK71:AM71) -> 0 | AO71: 0 | AP71: 0 | AQ71: 0 | AR71: =SUM(AO71:AQ71) -> 0 | AS71: 0 | AT71: 0 | AU71: 0 | AV71: 0 | AW71: =SUM(AS71:AV71) -> 0 | AX71: =SUM(AY71:AZ71) -> 55 | AY71: =SUM(AV71,AT71,AS71,AP71,AO71,AL71,AK71,AI71,AG71,AF71,AD71,AB71,AA71,Y71,W71,V71) -> 38 | AZ71: =SUM(AU71,AQ71,AM71,AH71,AC71,X71) -> 17 | BA71: 0 | BB71: =SUM(AX71+BA71) -> 55 | BC71: QUILOMBOLA | BD71: CEMIT | BE71: A DEFINIR | BG71: 1178815 | BI71: 1 | BJ71: PADRÃO ANTIGO | BK71: =Y71+AD71+AI71+AV71 -> 0 | BL71: =V71+W71+AA71+AB71+AF71+AG71+AK71+AL71+AO71+AP71+AS71+AT71 -> 38 | BM71: =IFERROR(__xludf.DUMMYFUNCTION("IFERROR(VLOOKUP(BG71,IMPORTRANGE(""https://docs.google.com/spreadsheets/d/1juPI-Fb8LD0YtltB2mlGEnp_R3UVu1t3wSFPzgCyHXE/edit?gid=0#gid=0"",""GERAL!A2:C""),3,0),""-"")"),"QUILOMBOLAS") -> QUILOMBOLAS
A72: NTE 02 - VELHO CHICO | B72: BARRA | C72: ANEXO | D72: 1179431 | E72: 1178818 | F72: 29464374 | G72: ANEXO - CEMIT - VELHO CHICO-BARRA - DISTRITO DE IBIRABA | H72: DISTRITO DE IBIRABA - S/N | I72: CENTRO | J72: 54KM | K72: CEDIDO | L72: PEQUENO | M72: =IFERROR(__xludf.DUMMYFUNCTION("IFERROR(VLOOKUP(D72, IMPORTRANGE(""https://docs.google.com/spreadsheets/d/1MjHtlUikwobi2MaWJgy7tfLeBmhj1u-dRFRs_8GwSoA/edit#gid=0"",""Gestores Escolares!D7:J""),3,0),""VERIFICAR CÓD SEC"")"),"NEIDE RAFAEL DE SOUZA ROCHA") -> NEIDE RAFAEL DE SOUZA ROCHA | N72: =IFERROR(__xludf.DUMMYFUNCTION("IFERROR(VLOOKUP(D72, IMPORTRANGE(""https://docs.google.com/spreadsheets/d/1MjHtlUikwobi2MaWJgy7tfLeBmhj1u-dRFRs_8GwSoA/edit#gid=0"",""Gestores Escolares!D7:J""),4,0),""VERIFICAR CÓD SEC"")"),"(74) 9 9807-3175") -> (74) 9 9807-3175 | O72: =IFERROR(__xludf.DUMMYFUNCTION("IFERROR(VLOOKUP(D72, IMPORTRANGE(""https://docs.google.com/spreadsheets/d/1MjHtlUikwobi2MaWJgy7tfLeBmhj1u-dRFRs_8GwSoA/edit#gid=0"",""Gestores Escolares!D7:J""),6,0),""VERIFICAR CÓD SEC"")"),"FRANCISCO DE ARAUJO LEAL") -> FRANCISCO DE ARAUJO LEAL | P72: =IFERROR(__xludf.DUMMYFUNCTION("IFERROR(VLOOKUP(D72, IMPORTRANGE(""https://docs.google.com/spreadsheets/d/1MjHtlUikwobi2MaWJgy7tfLeBmhj1u-dRFRs_8GwSoA/edit#gid=0"",""Gestores Escolares!D7:J""),7,0),""VERIFICAR CÓD SEC"")"),"(74) 9 8836-8463") -> (74) 9 8836-8463 | Q72: =IFERROR(__xludf.DUMMYFUNCTION("IFERROR(VLOOKUP(D72, IMPORTRANGE(""https://docs.google.com/spreadsheets/d/1MjHtlUikwobi2MaWJgy7tfLeBmhj1u-dRFRs_8GwSoA/edit#gid=0"",""Gestores Escolares!D7:m""),9,0),""VERIFICAR CÓD SEC"")"),"CLAUDEMIR CELSO LIMA") -> CLAUDEMIR CELSO LIMA | R72: =IFERROR(__xludf.DUMMYFUNCTION("IFERROR(VLOOKUP(D72, IMPORTRANGE(""https://docs.google.com/spreadsheets/d/1MjHtlUikwobi2MaWJgy7tfLeBmhj1u-dRFRs_8GwSoA/edit#gid=0"",""Gestores Escolares!D7:m""),10,0),""VERIFICAR CÓD SEC"")"),"(74) 9 9952-3072") -> (74) 9 9952-3072 | T72: 2 | U72: 2 | V72: 0 | W72: 0 | X72: 0 | Y72: 0 | Z72: =SUM(V72:Y72) -> 0 | AA72: 0 | AB72: 0 | AC72: 0 | AD72: 0 | AE72: =SUM(AA72:AD72) -> 0 | AF72: 61 | AG72: 20 | AH72: 0 | AI72: 0 | AJ72: =SUM(AF72:AI72) -> 81 | AK72: 0 | AL72: 0 | AM72: 0 | AN72: =SUM(AK72:AM72) -> 0 | AO72: 0 | AP72: 0 | AQ72: 0 | AR72: =SUM(AO72:AQ72) -> 0 | AS72: 0 | AT72: 0 | AU72: 0 | AV72: 0 | AW72: =SUM(AS72:AV72) -> 0 | AX72: =SUM(AY72:AZ72) -> 81 | AY72: =SUM(AV72,AT72,AS72,AP72,AO72,AL72,AK72,AI72,AG72,AF72,AD72,AB72,AA72,Y72,W72,V72) -> 81 | AZ72: =SUM(AU72,AQ72,AM72,AH72,AC72,X72) -> 0 | BA72: 0 | BB72: =SUM(AX72+BA72) -> 81 | BC72: A DEFINIR | BD72: CEMIT | BE72: PROFISSIONAL | BG72: 1178818 | BI72: 2 | BJ72: PADRÃO ANTIGO | BK72: =Y72+AD72+AI72+AV72 -> 0 | BL72: =V72+W72+AA72+AB72+AF72+AG72+AK72+AL72+AO72+AP72+AS72+AT72 -> 81 | BM72: =IFERROR(__xludf.DUMMYFUNCTION("IFERROR(VLOOKUP(BG72,IMPORTRANGE(""https://docs.google.com/spreadsheets/d/1juPI-Fb8LD0YtltB2mlGEnp_R3UVu1t3wSFPzgCyHXE/edit?gid=0#gid=0"",""GERAL!A2:C""),3,0),""-"")"),"-") -> -
A73: NTE 02 - VELHO CHICO | B73: BARRA | C73: ANEXO | D73: 1179431 | E73: 1178809 | F73: 29464374 | G73: ANEXO - CEMIT - VELHO CHICO-BARRA - DISTRITO DE BREJO DO SACO | H73: DISTRITO DE BREJO DO SACO - SN(00029) | I73: CENTRO | J73: 27KM | K73: PRÓPRIO | L73: PEQUENO | M73: =IFERROR(__xludf.DUMMYFUNCTION("IFERROR(VLOOKUP(D73, IMPORTRANGE(""https://docs.google.com/spreadsheets/d/1MjHtlUikwobi2MaWJgy7tfLeBmhj1u-dRFRs_8GwSoA/edit#gid=0"",""Gestores Escolares!D7:J""),3,0),""VERIFICAR CÓD SEC"")"),"NEIDE RAFAEL DE SOUZA ROCHA") -> NEIDE RAFAEL DE SOUZA ROCHA | N73: =IFERROR(__xludf.DUMMYFUNCTION("IFERROR(VLOOKUP(D73, IMPORTRANGE(""https://docs.google.com/spreadsheets/d/1MjHtlUikwobi2MaWJgy7tfLeBmhj1u-dRFRs_8GwSoA/edit#gid=0"",""Gestores Escolares!D7:J""),4,0),""VERIFICAR CÓD SEC"")"),"(74) 9 9807-3175") -> (74) 9 9807-3175 | O73: =IFERROR(__xludf.DUMMYFUNCTION("IFERROR(VLOOKUP(D73, IMPORTRANGE(""https://docs.google.com/spreadsheets/d/1MjHtlUikwobi2MaWJgy7tfLeBmhj1u-dRFRs_8GwSoA/edit#gid=0"",""Gestores Escolares!D7:J""),6,0),""VERIFICAR CÓD SEC"")"),"FRANCISCO DE ARAUJO LEAL") -> FRANCISCO DE ARAUJO LEAL | P73: =IFERROR(__xludf.DUMMYFUNCTION("IFERROR(VLOOKUP(D73, IMPORTRANGE(""https://docs.google.com/spreadsheets/d/1MjHtlUikwobi2MaWJgy7tfLeBmhj1u-dRFRs_8GwSoA/edit#gid=0"",""Gestores Escolares!D7:J""),7,0),""VERIFICAR CÓD SEC"")"),"(74) 9 8836-8463") -> (74) 9 8836-8463 | Q73: =IFERROR(__xludf.DUMMYFUNCTION("IFERROR(VLOOKUP(D73, IMPORTRANGE(""https://docs.google.com/spreadsheets/d/1MjHtlUikwobi2MaWJgy7tfLeBmhj1u-dRFRs_8GwSoA/edit#gid=0"",""Gestores Escolares!D7:m""),9,0),""VERIFICAR CÓD SEC"")"),"CLAUDEMIR CELSO LIMA") -> CLAUDEMIR CELSO LIMA | R73: =IFERROR(__xludf.DUMMYFUNCTION("IFERROR(VLOOKUP(D73, IMPORTRANGE(""https://docs.google.com/spreadsheets/d/1MjHtlUikwobi2MaWJgy7tfLeBmhj1u-dRFRs_8GwSoA/edit#gid=0"",""Gestores Escolares!D7:m""),10,0),""VERIFICAR CÓD SEC"")"),"(74) 9 9952-3072") -> (74) 9 9952-3072 | T73: 3 | U73: 2 | V73: 0 | W73: 0 | X73: 0 | Y73: 0 | Z73: =SUM(V73:Y73) -> 0 | AA73: 0 | AB73: 0 | AC73: 0 | AD73: 0 | AE73: =SUM(AA73:AD73) -> 0 | AF73: 55 | AG73: 53 | AH73: 0 | AI73: 0 | AJ73: =SUM(AF73:AI73) -> 108 | AK73: 0 | AL73: 0 | AM73: 0 | AN73: =SUM(AK73:AM73) -> 0 | AO73: 0 | AP73: 0 | AQ73: 0 | AR73: =SUM(AO73:AQ73) -> 0 | AS73: 0 | AT73: 0 | AU73: 0 | AV73: 0 | AW73: =SUM(AS73:AV73) -> 0 | AX73: =SUM(AY73:AZ73) -> 108 | AY73: =SUM(AV73,AT73,AS73,AP73,AO73,AL73,AK73,AI73,AG73,AF73,AD73,AB73,AA73,Y73,W73,V73) -> 108 | AZ73: =SUM(AU73,AQ73,AM73,AH73,AC73,X73) -> 0 | BA73: 0 | BB73: =SUM(AX73+BA73) -> 108 | BC73: A DEFINIR | BD73: CEMIT | BE73: A DEFINIR | BG73: 1178809 | BI73: 3 | BJ73: PADRÃO ANTIGO | BK73: =Y73+AD73+AI73+AV73 -> 0 | BL73: =V73+W73+AA73+AB73+AF73+AG73+AK73+AL73+AO73+AP73+AS73+AT73 -> 108 | BM73: =IFERROR(__xludf.DUMMYFUNCTION("IFERROR(VLOOKUP(BG73,IMPORTRANGE(""https://docs.google.com/spreadsheets/d/1juPI-Fb8LD0YtltB2mlGEnp_R3UVu1t3wSFPzgCyHXE/edit?gid=0#gid=0"",""GERAL!A2:C""),3,0),""-"")"),"-") -> -
